Workbook

Sheet README
A1: Life Insurance Pricing & Profitability Model
A2: Personal actuarial project
A4: Purpose
A5: Build a term life insurance pricing model and understand how mortality, lapses, expenses, commission and reinsurance affect premiums and profitability.
A7: Model Structure
A8: The model starts with an individual term life policy and follows the pricing process through premium calculation, projected cash flows, reinsurance and profit testing.
A9: Then applied to a synthetic portfolio to compare profitability across different groups, review experience and test the impact of changing key assumptions.
A10: The Assumptions and Mortality sheets set out the basis used in the model. IFRS 17 GMM and Unit-Linked / VFA are included as simplified extensions of the main pricing model.
A12: Data and modelling basis
A13: Amounts are in AED. Policy and experience data are synthetic, while the product features and actuarial assumptions are illustrative and are not based on a specific insurer.
A14: Term cash flows use annual steps and year-end discounting. Profit is before tax and capital costs. Monthly premiums use a loading rather than monthly decrements.
A16: Excel conventions
... A18: Core results and sensitivities update automatically when the inputs are changed. The Checks sheet can be used to review the main validation and reconciliation checks.

Sheet Results Summary
A1: Results Summary
A2: Summary of the individual policy and synthetic portfolio results. Amounts are in AED.
A4: Technical annual premium (AED) | E4: Policy PVFP (AED) | I4: Policy NBM
A5: ='Pricing Calculator'!E8 -> 546.06076 | E5: ='Profit Testing'!B7 -> 344.85011 | I5: ='Profit Testing'!B8 -> 0.10461954
A7: Break even year | E7: Portfolio NBM | I7: Mortality A/E
A8: ='Profit Testing'!B9 -> 6 | E8: ='Portfolio Totals'!B14 -> 0.07998801 | I8: ='Experience Analysis'!B50 -> 1.2261366
A10: ="Policies priced: "&'Portfolio Totals'!B8&" Loss-making policies: "&'Portfolio Totals'!B18&" Portfolio PVFP: AED "&TEXT('Portfolio Totals'!B13,"#,##0") -> Policies priced: 169 Loss-making policies: 65 Portfolio PVFP: AED 2,56,267
A12: Projected annual policy profit | G12: Impact of key assumptions on policy PVFP
A30: Portfolio profitability by entry age
G31: Key observations
G32: ="The portfolio contains "&'Portfolio Totals'!B18&" loss-making policies. Segment results help identify where to investigate premium adequacy." -> The portfolio contains 65 loss-making policies. Segment results help identify where to investigate premium adequacy.
G35: ="Reinsurance changes policy PVFP by AED "&TEXT(Reinsurance!B11,"#,##0;(#,##0)")&". The flat ceded rate needs review alongside the reduction in retained claims." -> Reinsurance changes policy PVFP by AED 0. The flat ceded rate needs review alongside the reduction in retained claims.
G38: ="Mortality A/E is "&TEXT('Experience Analysis'!B50,"0.0%")&" based on "&'Experience Analysis'!B48&" deaths. "&'Assumption Review'!B24&"." -> Mortality A/E is 122.6% based on 26 deaths. Low credibility: retain basis and monitor.
G41: ="Gross GMM: initial CSM AED "&TEXT('IFRS 17 GMM'!B8,"#,##0")&"; loss component AED "&TEXT('IFRS 17 GMM'!B9,"#,##0")&". This differs from profitability after reinsurance." -> Gross GMM: initial CSM AED 256; loss component AED 0. This differs from profitability after reinsurance.
G44: ="The policy is most sensitive to "&Sensitivities!B38&", "&Sensitivities!B39&" and "&Sensitivities!B40&" among the assumptions tested." -> The policy is most sensitive to Expenses (±10%), Commission (pp) (±5.0pp) and Lapse rates (±20%) among the assumptions tested.
A49: Year | B49: Annual profit | C49: Discounted profit | E49: Driver | F49: Lower assumption | G49: Higher assumption | I49: Entry age | J49: Portfolio NBM
A50: =Cashflows!A4 -> 1 | B50: =Cashflows!L4 -> -712.31503 | C50: =Cashflows!N4 -> -688.22708 | E50: =Sensitivities!B38 -> Expenses (±10%) | F50: =Sensitivities!C38 -> 236.51577 | G50: =Sensitivities!D38 -> -236.51577 | I50: ='Portfolio Analysis'!A26 -> 20-29 | J50: ='Portfolio Analysis'!H26 -> 0.23642095
A51: =Cashflows!A5 -> 2 | B51: =Cashflows!L5 -> 228.46657 | C51: =Cashflows!N5 -> 213.27599 | E51: =Sensitivities!B39 -> Commission (pp) (±5.0pp) | F51: =Sensitivities!C39 -> 164.81153 | G51: =Sensitivities!D39 -> -164.81153 | I51: ='Portfolio Analysis'!A27 -> 30-39 | J51: ='Portfolio Analysis'!H27 -> 0.1195501
A52: =Cashflows!A6 -> 3 | B52: =Cashflows!L6 -> 194.83206 | C52: =Cashflows!N6 -> 175.72736 | E52: =Sensitivities!B40 -> Lapse rates (±20%) | F52: =Sensitivities!C40 -> 80.765358 | G52: =Sensitivities!D40 -> -75.304113 | I52: ='Portfolio Analysis'!A28 -> 40-49 | J52: ='Portfolio Analysis'!H28 -> 0.053280309
A53: =Cashflows!A7 -> 4 | B53: =Cashflows!L7 -> 168.01429 | C53: =Cashflows!N7 -> 146.41475 | E53: =Sensitivities!B41 -> Discount rate (±100bp) | F53: =Sensitivities!C41 -> 43.477434 | G53: =Sensitivities!D41 -> -40.291635 | I53: ='Portfolio Analysis'!A29 -> 50-59 | J53: ='Portfolio Analysis'!H29 -> -0.081048407
A54: =Cashflows!A8 -> 5 | B54: =Cashflows!L8 -> 145.95753 | C54: =Cashflows!N8 -> 122.89232 | E54: =Sensitivities!B42 -> Mortality (qx) (±10%) | F54: =Sensitivities!C42 -> 34.201242 | G54: =Sensitivities!D42 -> -34.185704 | I54: ='Portfolio Analysis'!A30 -> 60+ | J54: ='Portfolio Analysis'!H30 -> 0.16100417
A55: =Cashflows!A9 -> 6 | B55: =Cashflows!L9 -> 127.2692 | C55: =Cashflows!N9 -> 103.53358 | E55: =Sensitivities!B43 -> RI premium rate (±20%) | F55: =Sensitivities!C43 -> 0 | G55: =Sensitivities!D43 -> 0
A56: =Cashflows!A10 -> 7 | B56: =Cashflows!L10 -> 110.97831 | C56: =Cashflows!N10 -> 87.227952
A57: =Cashflows!A11 -> 8 | B57: =Cashflows!L11 -> 96.38961 | C57: =Cashflows!N11 -> 73.199383
A58: =Cashflows!A12 -> 9 | B58: =Cashflows!L12 -> 82.99289 | C58: =Cashflows!N12 -> 60.894454
A59: =Cashflows!A13 -> 10 | B59: =Cashflows!L13 -> 70.404962 | C59: =Cashflows!N13 -> 49.911402
A60: =Cashflows!A14 -> 11 | B60: =Cashflows!L14 -> 0 | C60: =Cashflows!N14 -> 0
A61: =Cashflows!A15 -> 12 | B61: =Cashflows!L15 -> 0 | C61: =Cashflows!N15 -> 0
A62: =Cashflows!A16 -> 13 | B62: =Cashflows!L16 -> 0 | C62: =Cashflows!N16 -> 0
A63: =Cashflows!A17 -> 14 | B63: =Cashflows!L17 -> 0 | C63: =Cashflows!N17 -> 0
A64: =Cashflows!A18 -> 15 | B64: =Cashflows!L18 -> 0 | C64: =Cashflows!N18 -> 0
A65: =Cashflows!A19 -> 16 | B65: =Cashflows!L19 -> 0 | C65: =Cashflows!N19 -> 0
A66: =Cashflows!A20 -> 17 | B66: =Cashflows!L20 -> 0 | C66: =Cashflows!N20 -> 0
A67: =Cashflows!A21 -> 18 | B67: =Cashflows!L21 -> 0 | C67: =Cashflows!N21 -> 0
... A89: =Cashflows!A43 -> 40 | B89: =Cashflows!L43 -> 0 | C89: =Cashflows!N43 -> 0

Sheet Pricing Calculator
A1: Term Life Pricing Calculator
A2: Change the yellow inputs to price a new policy. Amounts are in AED.
D3: Input status | E3: ='Premium Calculation'!B27 -> VALID | G3: Active scenario | H3: =Sensitivities!C16 -> Base
A5: 1. Customer & policy inputs | D5: 2. Premium | G5: 3. Policy profitability
A6: Entry age (years) | B6: 24 | D6: Charged annual premium (AED) | E6: ='Premium Calculation'!B29 -> 562.44258 | G6: PVFP (AED) | H6: ='Profit Testing'!B7 -> 344.85011
A7: Sex | B7: Male | D7: Premium per instalment (selected mode) | E7: ='Premium Calculation'!B21 -> 46.870215 | G7: New-business margin (NBM) | H7: ='Profit Testing'!B8 -> 0.10461954
A8: Smoker status | B8: Smoker | D8: Technical annual-mode premium | E8: =IFERROR('Premium Calculation'!B22/('Premium Calculation'!B23-'Premium Calculation'!B24-'Premium Calculation'!B25*'Premium Calculation'!B23),NA()) -> 546.06076 | G8: Target NBM | H8: =Assumptions!C16 -> 0.08
A9: Underwriting / risk class | B9: Preferred | D9: Technical monthly-mode instalment | E9: =IFERROR(E8*(1+Assumptions!C29)/12,NA()) -> 46.870215 | G9: Break-even year | H9: ='Profit Testing'!B9 -> 6
A10: Sum assured (AED) | B10: 100000 | D10: Premium per 1,000 sum assured | E10: ='Premium Calculation'!B20 -> 5.6244258 | G10: PV premiums (AED) | H10: ='Profit Testing'!B4 -> 3296.2306
A11: Policy term (years) | B11: 10 | D11: Pricing basis | E11: =IF(ISBLANK('Premium Calculation'!B28),"Solved to target NBM","Override in Term Life Pricing B28") -> Solved to target NBM | G11: Profitability indication | H11: =IF('Profit Testing'!B7<0,"Loss-making",IF('Profit Testing'!B8>=Assumptions!C16-0.000001,"At or above target","Below target")) -> At or above target
A12: Premium frequency | B12: Monthly | D12: Monthly premiums are based on the annual premium with a monthly payment loading applied; decrements are modelled annually.
A13: Distribution channel | B13: Bancassurance
A14: Initial commission applied | B14: ='Premium Calculation'!B32 -> 0.2
A15: Max entry age for this term | B15: =81-B11 -> 71
A16: Limits: entry age 20–(81 – term); policy term 1–40 years; sum assured > 0. Mortality rates are available up to age 80.
A18: 4. Reinsurance (surplus above retention)
A19: Sum assured | B19: =Reinsurance!B4 -> 100000
A20: Retained sum assured | B20: =Reinsurance!D4 -> 100000
A21: Ceded sum assured | B21: =Reinsurance!C4 -> 0
A22: Ceded share | B22: =IF(B19=0,0,B21/B19) -> 0
A23: PV RI recoveries | B23: =Reinsurance!B9 -> 0
A24: PV RI premiums | B24: =Reinsurance!B10 -> 0
A25: Reinsurance impact on PVFP | B25: =Reinsurance!B11 -> 0
A26: PVFP without reinsurance | B26: =Reinsurance!B12 -> 344.85011
A36: Reinsurance reduces the amount of claim risk retained by the insurer. Its overall impact can be seen by comparing the cost of reinsurance with the expected recoveries and the change in PVFP.
A50: Year | B50: Premium | C50: Net outgo | D50: Profit
A51: =Cashflows!A4 -> 1 | B51: =Cashflows!E4 -> 562.44258 | C51: =Cashflows!H4+Cashflows!I4+Cashflows!J4+Cashflows!K4 -> 1274.7576 | D51: =Cashflows!L4 -> -712.31503
A52: =Cashflows!A5 -> 2 | B52: =Cashflows!E5 -> 494.74026 | C52: =Cashflows!H5+Cashflows!I5+Cashflows!J5+Cashflows!K5 -> 266.27369 | D52: =Cashflows!L5 -> 228.46657
A53: =Cashflows!A6 -> 3 | B53: =Cashflows!E6 -> 444.07332 | C53: =Cashflows!H6+Cashflows!I6+Cashflows!J6+Cashflows!K6 -> 249.24126 | D53: =Cashflows!L6 -> 194.83206
A54: =Cashflows!A7 -> 4 | B54: =Cashflows!E7 -> 405.37099 | C54: =Cashflows!H7+Cashflows!I7+Cashflows!J7+Cashflows!K7 -> 237.3567 | D54: =Cashflows!L7 -> 168.01429
A55: =Cashflows!A8 -> 5 | B55: =Cashflows!E8 -> 375.2954 | C55: =Cashflows!H8+Cashflows!I8+Cashflows!J8+Cashflows!K8 -> 229.33788 | D55: =Cashflows!L8 -> 145.95753
A56: =Cashflows!A9 -> 6 | B56: =Cashflows!E9 -> 351.58184 | C56: =Cashflows!H9+Cashflows!I9+Cashflows!J9+Cashflows!K9 -> 224.31264 | D56: =Cashflows!L9 -> 127.2692
A57: =Cashflows!A10 -> 7 | B57: =Cashflows!E10 -> 332.6521 | C57: =Cashflows!H10+Cashflows!I10+Cashflows!J10+Cashflows!K10 -> 221.67378 | D57: =Cashflows!L10 -> 110.97831
A58: =Cashflows!A11 -> 8 | B58: =Cashflows!E11 -> 317.38 | C58: =Cashflows!H11+Cashflows!I11+Cashflows!J11+Cashflows!K11 -> 220.99039 | D58: =Cashflows!L11 -> 96.38961
A59: =Cashflows!A12 -> 9 | B59: =Cashflows!E12 -> 304.9448 | C59: =Cashflows!H12+Cashflows!I12+Cashflows!J12+Cashflows!K12 -> 221.95191 | D59: =Cashflows!L12 -> 82.99289
A60: =Cashflows!A13 -> 10 | B60: =Cashflows!E13 -> 294.737 | C60: =Cashflows!H13+Cashflows!I13+Cashflows!J13+Cashflows!K13 -> 224.33204 | D60: =Cashflows!L13 -> 70.404962
A61: =Cashflows!A14 -> 11 | B61: =Cashflows!E14 -> 0 | C61: =Cashflows!H14+Cashflows!I14+Cashflows!J14+Cashflows!K14 -> 0 | D61: =Cashflows!L14 -> 0
A62: =Cashflows!A15 -> 12 | B62: =Cashflows!E15 -> 0 | C62: =Cashflows!H15+Cashflows!I15+Cashflows!J15+Cashflows!K15 -> 0 | D62: =Cashflows!L15 -> 0
... A90: =Cashflows!A43 -> 40 | B90: =Cashflows!E43 -> 0 | C90: =Cashflows!H43+Cashflows!I43+Cashflows!J43+Cashflows!K43 -> 0 | D90: =Cashflows!L43 -> 0

Sheet Assumptions
A1: Assumptions
A3: Parameter | B3: Description | C3: Base case | D3: Unit | E3: Source / rationale
A4: Valuation_Date | B4: Reference date for portfolio calculations | C4: 2026-09-25 | D4: date | E4: Portfolio model
A5: Expense_Inflation | B5: Annual expense inflation | C5: 0.04 | D5: % | E5: Scenario assumption
A6: Discount_Rate | B6: Discount rate used for pricing and present value calculations | C6: 0.035 | D6: % | E6: Scenario assumption
A7: Investment_Return | B7: Assumed annual fund return for the unit-linked projection | C7: 0.025 | D7: % | E7: Scenario assumption
A8: Risk_Adjustment_Pct | B8: Risk adjustment as % of PV future claims and expenses | C8: 0.03 | D8: % | E8: Simplified assumption for the IFRS 17 illustration
A9: Acquisition_Expense | B9: Initial acquisition expense per policy | C9: 900 | D9: AED | E9: Portfolio assumption
A10: Maintenance_Expense | B10: Annual maintenance expense in Year 1 | C10: 220 | D10: AED p.a. | E10: Portfolio assumption
A11: Initial_Commission | B11: Default initial commission assumption | C11: 0.2 | D11: % | E11: Portfolio assumption
A12: Renewal_Commission | B12: Renewal commission as % of premium | C12: 0.05 | D12: % | E12: Portfolio assumption
A13: Base_Lapse | B13: Year 1 lapse rate | C13: 0.12 | D13: % | E13: Starting assumption for experience analysis
A14: Reinsurance_Retention | B14: Retention per life | C14: 500000 | D14: AED | E14: Portfolio assumption
A15: Reinsurance_Rate | B15: Reinsurance premium rate on ceded sum assured | C15: 0.0011 | D15: % of ceded SA | E15: Portfolio assumption
A16: Profit_Loading | B16: Target new-business margin (NBM) | C16: 0.08 | D16: % of premium | E16: Portfolio assumption
... A34: Bank_Commission | B34: Initial commission – Bancassurance channel | C34: 0.2 | D34: % | E34: Illustrative channel commission assumption
A37: Principle | B37: Explanation | E37: Classification | F37: Source
A38: Probability roll-forward | B38: Deaths first; lapses conditional on survival. | E38: General actuarial methodology
A39: Discounted profit | B39: PVFP = sum of discounted annual profits. | E39: General actuarial methodology
A40: IFRS 17 | B40: FCF, CSM and separate reinsurance-held accounting. | E40: Officially sourced context | F40: https://www.ifrs.org/issued-standards/list-of-standards/ifrs-17-insurance-contracts/

Sheet Mortality
A1: Mortality
A3: Age | B3: Female Non-smoker | C3: Female Smoker | D3: Male Non-smoker | E3: Male Smoker | F3: Preferred Factor | G3: Rated Factor
A4: 20 | B4: 0.00017186833 | C4: 0.00028358274 | D4: 0.00023252774 | E4: 0.00038367077 | F4: 0.8 | G4: 1.55
A5: 21 | B5: 0.00018618274 | C5: 0.00030720152 | D5: 0.00025189429 | E5: 0.00041562558 | F5: 0.8 | G5: 1.55
A6: 22 | B6: 0.00020168935 | C6: 0.00033278743 | D6: 0.00027287383 | E6: 0.00045024182 | F6: 0.8 | G6: 1.55
A7: 23 | B7: 0.00021848747 | C7: 0.00036050432 | D7: 0.00029560069 | E7: 0.00048774114 | F7: 0.8 | G7: 1.55
A8: 24 | B8: 0.00023668465 | C8: 0.00039052967 | D8: 0.00032022041 | E8: 0.00052836367 | F8: 0.8 | G8: 1.55
A9: 25 | B9: 0.00025639742 | C9: 0.00042305574 | D9: 0.00034689062 | E9: 0.00057236953 | F9: 0.8 | G9: 1.55
A10: 26 | B10: 0.00027775201 | C10: 0.00045829081 | D10: 0.00037578213 | E10: 0.00062004051 | F10: 0.8 | G10: 1.55
A11: 27 | B11: 0.00030088516 | C11: 0.00049646051 | D11: 0.00040707992 | E11: 0.00067168186 | F11: 0.8 | G11: 1.55
A12: 28 | B12: 0.000325945 | C12: 0.00053780925 | D12: 0.00044098441 | E12: 0.00072762428 | F12: 0.8 | G12: 1.55
A13: 29 | B13: 0.000353092 | C13: 0.0005826018 | D13: 0.00047771271 | E13: 0.00078822597 | F13: 0.8 | G13: 1.55
A14: 30 | B14: 0.0003825 | C14: 0.000631125 | D14: 0.0005175 | E14: 0.000853875 | F14: 0.8 | G14: 1.55
A15: 31 | B15: 0.0004143573 | C15: 0.00068368955 | D15: 0.00056060106 | E15: 0.00092499174 | F15: 0.8 | G15: 1.55
... A64: 80 | B64: 0.020883792 | C64: 0.034458257 | D64: 0.028254543 | E64: 0.046619995 | F64: 0.8 | G64: 1.55
A66: Illustrative mortality rates by age, sex and smoker status. Underwriting factors are shown in the Assumptions sheet.

Sheet Premium Calculation
A1: Premium Calculation
A2: Policy inputs are linked from the Pricing Calculator. An optional premium override can be entered below.
A3: Input or result | B3: Value | C3: Unit | D3: Explanation
A4: Entry age | B4: ='Pricing Calculator'!B6 -> 24 | C4: years | D4: Linked from Pricing Calculator!C6 (edit inputs there)
A5: Sex | B5: ='Pricing Calculator'!B7 -> Male | D5: Linked from Pricing Calculator!C7 (edit inputs there)
A6: Smoking status | B6: ='Pricing Calculator'!B8 -> Smoker | D6: Linked from Pricing Calculator!C8 (edit inputs there)
A7: Underwriting Class | B7: ='Pricing Calculator'!B9 -> Preferred | D7: Linked from Pricing Calculator!C9 (edit inputs there)
A8: Policy term | B8: ='Pricing Calculator'!B11 -> 10 | C8: years | D8: Linked from Pricing Calculator!C11 (edit inputs there)
A9: Sum assured | B9: ='Pricing Calculator'!B10 -> 100000 | C9: AED | D9: Linked from Pricing Calculator!C10 (edit inputs there)
A10: Premium frequency | B10: ='Pricing Calculator'!B12 -> Monthly | D10: Linked from Pricing Calculator!C12 (edit inputs there)
A11: Base qx | B11: {=_xlfn.XLOOKUP(B4,Mortality!$A$4:$A$64, _xlfn.XLOOKUP(B5&" "&B6,Mortality!$B$3:$E$3,Mortality!$B$4:$E$64))} -> 0.00052836367 | C11: % | D11: Mortality rate at entry age
A12: Underwriting-adjusted qx | B12: =B11*IF(B7="Preferred",Assumptions!C30,IF(B7="Rated",Assumptions!C31,1))*Assumptions!C21 -> 0.00042269093 | C12: % | D12: Base mortality adjusted for underwriting class
A13: Year 1 gross claims | B13: =B9*B12 -> 42.269093 | C13: AED | D13: Sum assured × adjusted mortality rate
A14: Ceded sum assured | B14: =MAX(B9-Assumptions!C14,0) -> 0 | C14: AED | D14: Surplus above retention
A15: Year 1 retained claims | B15: =B12*MIN(B9,Assumptions!C14) -> 42.269093 | C15: AED | D15: Expected claims after reinsurance recoveries
A16: Year 1 reinsurance premium | B16: =B14*Assumptions!C15 -> 0 | C16: AED | D16: Ceded sum assured × reinsurance premium rate
A17: Year 1 expenses | B17: =(Assumptions!C9+Assumptions!C10)*Assumptions!C23 -> 1120 | C17: AED | D17: Acquisition and maintenance expenses
A18: Year 1 commission | B18: =B29*(B32+Assumptions!C24) -> 112.48852 | C18: AED | D18: Charged premium × initial commission rate
A19: Technical annual premium | B19: =IF(B27="VALID",B22/(B23-B24-Assumptions!C16*B23)*IF(B10="Monthly",1+Assumptions!C29,1),NA()) -> 562.44258 | C19: AED | D19: Premium required to meet the target NBM
A20: Premium per 1,000 sum assured | B20: =B29/B9*1000 -> 5.6244258 | C20: AED | D20: Annual premium expressed per AED 1,000 of sum assured
A21: Premium per instalment | B21: =B29/IF(B10="Monthly",12,1) -> 46.870215 | C21: AED | D21: Premium payable for the selected payment frequency
A22: PV claims and expenses | B22: =SUM(Cashflows!Q4:Q43) -> 2705.0555 | C22: AED | D22: Present value of retained claims, expenses and reinsurance premiums
A23: PV unit premium annuity | B23: =SUM(Cashflows!O4:O43) -> 5.8605636 | C23: factor | D23: Present value factor for future premiums
A24: PV commission coefficient | B24: =SUM(Cashflows!P4:P43) -> 0.43795572 | C24: factor | D24: Present value factor for future commission payments
A25: Target NBM | B25: =Assumptions!C16 -> 0.08 | C25: % | D25: PVFP / PV premiums
A26: Premium equation residual | B26: =B19/IF(B10="Monthly",1+Assumptions!C29,1)*(B23-B24-B25*B23)-B22 -> 0 | C26: AED | D26: Should be zero when the premium is solved
A27: Input status | B27: =IFERROR(IF(AND(COUNT(B4,B8,B9)=3,COUNT(Assumptions!C5:C34)=30,Assumptions!C9>=0,Assumptions!C10>=0,Assumptions!C5>-1,Assumptions!C27>=0,Assumptions!C27<=1,Assumptions!C28>=0,Assumptions!C28<=1,Assumptions!C29>=0,Assumptions!C30>0,Assumptions!C31>0,B23-B24-Assumptions!C16*B23>0,B4=INT(B4),B4>=20,B8=INT(B8),B8>=1,B8<=40,B4+B8-1<=80,B9>0,OR(B5="Male",B5="Female"),OR(B6="Smoker",B6="Non-smoker"),OR(B7="Standard",B7="Preferred",B7="Rated"),OR(B10="Annual",B10="Monthly"),OR(B31="Direct",B31="Broker",B31="Bancassurance",B31="Generic"),Assumptions!C6+Assumptions!C25>-1,Assumptions!C13>=0,Assumptions!C13<=1,Assumptions!C14>=0,Assumptions!C15>=0,Assumptions!C21>=0,Assumptions!C22>=0,Assumptions!C23>=0,B32+Assumptions!C24>=0,B32+Assumptions!C24<1,Assumptions!C12+Assumptions!C24>=0,Assumptions!C12+Assumptions!C24<1,Assumptions!C16>=0,Assumptions!C16<1,OR(ISBLANK(B28),AND(ISNUMBER(B28),B28>=0))),"VALID","INVALID INPUT"),"INVALID INPUT") -> VALID | D27: Check the yellow input cells if the status is invalid
A28: Annual premium override | C28: AED | D28: Leave blank to use the technical premium; enter a value to test a different premium.
A29: Charged annual premium | B29: =IF(ISBLANK(B28),B19,B28) -> 562.44258 | C29: AED | D29: Premium used for profit testing, sensitivities and comparisons
A31: Distribution channel | B31: ='Pricing Calculator'!B13 -> Bancassurance | D31: Selected distribution channel from the Pricing Calculator
A32: Initial commission rate | B32: =IF(B31="Direct",Assumptions!C32,IF(B31="Broker",Assumptions!C33,IF(B31="Bancassurance",Assumptions!C34,Assumptions!C11))) -> 0.2 | C32: % | D32: Commission rate based on the selected distribution channel

Sheet Cashflows
A1: Projected Cash Flows
A2: Annual projection of premiums, claims, expenses, reinsurance and profit for the selected policy.
A3: Year | B3: Opening in-force | C3: Annual qx | D3: Lapse rate | E3: Premium | F3: Gross claims | G3: Ceded claims | H3: Retained claims | I3: Expenses | J3: Commission | K3: Reinsurance premium | L3: Annual profit | M3: Discount factor | N3: PV profit | O3: PV premium factor | P3: PV commission factor | Q3: PV claims & expenses | R3: Closing in-force | S3: Deaths | T3: Lapses | U3: Roll-forward check
A4: 1 | B4: =IF(A4<='Premium Calculation'!$B$8,1,0) -> 1 | C4: {=IF(B4=0,0,_xlfn.XLOOKUP('Premium Calculation'!$B$4+A4-1,Mortality!$A$4:$A$64,_xlfn.XLOOKUP('Premium Calculation'!$B$5&" "&'Premium Calculation'!$B$6,Mortality!$B$3:$E$3,Mortality!$B$4:$E$64))*IF('Premium Calculation'!$B$7="Preferred",Assumptions!$C$30,IF('Premium Calculation'!$B$7="Rated",Assumptions!$C$31,1))*Assumptions!$C$21)} -> 0.00042269093 | D4: =IF(B4=0,0,MIN(1,MAX(Assumptions!$C$27,Assumptions!$C$13*Assumptions!$C$28^(A4-1))*Assumptions!$C$22)) -> 0.12 | E4: =B4*'Premium Calculation'!$B$29 -> 562.44258 | F4: =B4*C4*'Premium Calculation'!$B$9 -> 42.269093 | G4: =B4*C4*'Premium Calculation'!$B$14 -> 0 | H4: =F4-G4 -> 42.269093 | I4: =B4*(Assumptions!$C$10*(1+Assumptions!$C$5)^(A4-1)+IF(A4=1,Assumptions!$C$9,0))*Assumptions!$C$23 -> 1120 | J4: =E4*(IF(A4=1,'Premium Calculation'!$B$32,Assumptions!$C$12)+Assumptions!$C$24) -> 112.48852 | K4: =B4*'Premium Calculation'!$B$14*Assumptions!$C$15 -> 0 | L4: =E4-H4-I4-J4-K4 -> -712.31503 | M4: =(1+Assumptions!$C$6+Assumptions!$C$25)^(-A4) -> 0.96618357 | N4: =L4*M4 -> -688.22708 | O4: =B4*M4 -> 0.96618357 | P4: =O4*(IF(A4=1,'Premium Calculation'!$B$32,Assumptions!$C$12)+Assumptions!$C$24) -> 0.19323671 | Q4: =(H4+I4+K4)*M4 -> 1122.9653 | R4: =B4-S4-T4 -> 0.87962803 | S4: =B4*C4 -> 0.00042269093 | T4: =(B4-S4)*D4 -> 0.11994928 | U4: =B4-R4-S4-T4 -> 0
A5: 2 | B5: =IF(A5<='Premium Calculation'!$B$8,R4,0) -> 0.87962803 | C5: {=IF(B5=0,0,_xlfn.XLOOKUP('Premium Calculation'!$B$4+A5-1,Mortality!$A$4:$A$64,_xlfn.XLOOKUP('Premium Calculation'!$B$5&" "&'Premium Calculation'!$B$6,Mortality!$B$3:$E$3,Mortality!$B$4:$E$64))*IF('Premium Calculation'!$B$7="Preferred",Assumptions!$C$30,IF('Premium Calculation'!$B$7="Rated",Assumptions!$C$31,1))*Assumptions!$C$21)} -> 0.00045789562 | D5: =IF(B5=0,0,MIN(1,MAX(Assumptions!$C$27,Assumptions!$C$13*Assumptions!$C$28^(A5-1))*Assumptions!$C$22)) -> 0.102 | E5: =B5*'Premium Calculation'!$B$29 -> 494.74026 | F5: =B5*C5*'Premium Calculation'!$B$9 -> 40.277783 | G5: =B5*C5*'Premium Calculation'!$B$14 -> 0 | H5: =F5-G5 -> 40.277783 | I5: =B5*(Assumptions!$C$10*(1+Assumptions!$C$5)^(A5-1)+IF(A5=1,Assumptions!$C$9,0))*Assumptions!$C$23 -> 201.25889 | J5: =E5*(IF(A5=1,'Premium Calculation'!$B$32,Assumptions!$C$12)+Assumptions!$C$24) -> 24.737013 | K5: =B5*'Premium Calculation'!$B$14*Assumptions!$C$15 -> 0 | L5: =E5-H5-I5-J5-K5 -> 228.46657 | M5: =(1+Assumptions!$C$6+Assumptions!$C$25)^(-A5) -> 0.9335107 | N5: =L5*M5 -> 213.27599 | O5: =B5*M5 -> 0.82114218 | P5: =O5*(IF(A5=1,'Premium Calculation'!$B$32,Assumptions!$C$12)+Assumptions!$C$24) -> 0.041057109 | Q5: =(H5+I5+K5)*M5 -> 225.47707 | R5: =B5-S5-T5 -> 0.78954428 | S5: =B5*C5 -> 0.00040277783 | T5: =(B5-S5)*D5 -> 0.089680976 | U5: =B5-R5-S5-T5 -> 0
A6: 3 | B6: =IF(A6<='Premium Calculation'!$B$8,R5,0) -> 0.78954428 | C6: {=IF(B6=0,0,_xlfn.XLOOKUP('Premium Calculation'!$B$4+A6-1,Mortality!$A$4:$A$64,_xlfn.XLOOKUP('Premium Calculation'!$B$5&" "&'Premium Calculation'!$B$6,Mortality!$B$3:$E$3,Mortality!$B$4:$E$64))*IF('Premium Calculation'!$B$7="Preferred",Assumptions!$C$30,IF('Premium Calculation'!$B$7="Rated",Assumptions!$C$31,1))*Assumptions!$C$21)} -> 0.00049603241 | D6: =IF(B6=0,0,MIN(1,MAX(Assumptions!$C$27,Assumptions!$C$13*Assumptions!$C$28^(A6-1))*Assumptions!$C$22)) -> 0.0867 | E6: =B6*'Premium Calculation'!$B$29 -> 444.07332 | F6: =B6*C6*'Premium Calculation'!$B$9 -> 39.163955 | G6: =B6*C6*'Premium Calculation'!$B$14 -> 0 | H6: =F6-G6 -> 39.163955 | I6: =B6*(Assumptions!$C$10*(1+Assumptions!$C$5)^(A6-1)+IF(A6=1,Assumptions!$C$9,0))*Assumptions!$C$23 -> 187.87364 | J6: =E6*(IF(A6=1,'Premium Calculation'!$B$32,Assumptions!$C$12)+Assumptions!$C$24) -> 22.203666 | K6: =B6*'Premium Calculation'!$B$14*Assumptions!$C$15 -> 0 | L6: =E6-H6-I6-J6-K6 -> 194.83206 | M6: =(1+Assumptions!$C$6+Assumptions!$C$25)^(-A6) -> 0.90194271 | N6: =L6*M6 -> 175.72736 | O6: =B6*M6 -> 0.7121237 | P6: =O6*(IF(A6=1,'Premium Calculation'!$B$32,Assumptions!$C$12)+Assumptions!$C$24) -> 0.035606185 | Q6: =(H6+I6+K6)*M6 -> 204.7749 | R6: =B6-S6-T6 -> 0.7207331 | S6: =B6*C6 -> 0.00039163955 | T6: =(B6-S6)*D6 -> 0.068419534 | U6: =B6-R6-S6-T6 -> 0
A7: 4 | B7: =IF(A7<='Premium Calculation'!$B$8,R6,0) -> 0.7207331 | C7: {=IF(B7=0,0,_xlfn.XLOOKUP('Premium Calculation'!$B$4+A7-1,Mortality!$A$4:$A$64,_xlfn.XLOOKUP('Premium Calculation'!$B$5&" "&'Premium Calculation'!$B$6,Mortality!$B$3:$E$3,Mortality!$B$4:$E$64))*IF('Premium Calculation'!$B$7="Preferred",Assumptions!$C$30,IF('Premium Calculation'!$B$7="Rated",Assumptions!$C$31,1))*Assumptions!$C$21)} -> 0.00053734549 | D7: =IF(B7=0,0,MIN(1,MAX(Assumptions!$C$27,Assumptions!$C$13*Assumptions!$C$28^(A7-1))*Assumptions!$C$22)) -> 0.073695 | E7: =B7*'Premium Calculation'!$B$29 -> 405.37099 | F7: =B7*C7*'Premium Calculation'!$B$9 -> 38.728268 | G7: =B7*C7*'Premium Calculation'!$B$14 -> 0 | H7: =F7-G7 -> 38.728268 | I7: =B7*(Assumptions!$C$10*(1+Assumptions!$C$5)^(A7-1)+IF(A7=1,Assumptions!$C$9,0))*Assumptions!$C$23 -> 178.35988 | J7: =E7*(IF(A7=1,'Premium Calculation'!$B$32,Assumptions!$C$12)+Assumptions!$C$24) -> 20.268549 | K7: =B7*'Premium Calculation'!$B$14*Assumptions!$C$15 -> 0 | L7: =E7-H7-I7-J7-K7 -> 168.01429 | M7: =(1+Assumptions!$C$6+Assumptions!$C$25)^(-A7) -> 0.87144223 | N7: =L7*M7 -> 146.41475 | O7: =B7*M7 -> 0.62807726 | P7: =O7*(IF(A7=1,'Premium Calculation'!$B$32,Assumptions!$C$12)+Assumptions!$C$24) -> 0.031403863 | Q7: =(H7+I7+K7)*M7 -> 189.17978 | R7: =B7-S7-T7 -> 0.66725994 | S7: =B7*C7 -> 0.00038728268 | T7: =(B7-S7)*D7 -> 0.053085885 | U7: =B7-R7-S7-T7 -> 0
A8: 5 | B8: =IF(A8<='Premium Calculation'!$B$8,R7,0) -> 0.66725994 | C8: {=IF(B8=0,0,_xlfn.XLOOKUP('Premium Calculation'!$B$4+A8-1,Mortality!$A$4:$A$64,_xlfn.XLOOKUP('Premium Calculation'!$B$5&" "&'Premium Calculation'!$B$6,Mortality!$B$3:$E$3,Mortality!$B$4:$E$64))*IF('Premium Calculation'!$B$7="Preferred",Assumptions!$C$30,IF('Premium Calculation'!$B$7="Rated",Assumptions!$C$31,1))*Assumptions!$C$21)} -> 0.00058209942 | D8: =IF(B8=0,0,MIN(1,MAX(Assumptions!$C$27,Assumptions!$C$13*Assumptions!$C$28^(A8-1))*Assumptions!$C$22)) -> 0.06264075 | E8: =B8*'Premium Calculation'!$B$29 -> 375.2954 | F8: =B8*C8*'Premium Calculation'!$B$9 -> 38.841162 | G8: =B8*C8*'Premium Calculation'!$B$14 -> 0 | H8: =F8-G8 -> 38.841162 | I8: =B8*(Assumptions!$C$10*(1+Assumptions!$C$5)^(A8-1)+IF(A8=1,Assumptions!$C$9,0))*Assumptions!$C$23 -> 171.73194 | J8: =E8*(IF(A8=1,'Premium Calculation'!$B$32,Assumptions!$C$12)+Assumptions!$C$24) -> 18.76477 | K8: =B8*'Premium Calculation'!$B$14*Assumptions!$C$15 -> 0 | L8: =E8-H8-I8-J8-K8 -> 145.95753 | M8: =(1+Assumptions!$C$6+Assumptions!$C$25)^(-A8) -> 0.84197317 | N8: =L8*M8 -> 122.89232 | O8: =B8*M8 -> 0.56181496 | P8: =O8*(IF(A8=1,'Premium Calculation'!$B$32,Assumptions!$C$12)+Assumptions!$C$24) -> 0.028090748 | Q8: =(H8+I8+K8)*M8 -> 177.29691 | R8: =B8-S8-T8 -> 0.62509819 | S8: =B8*C8 -> 0.00038841162 | T8: =(B8-S8)*D8 -> 0.041773332 | U8: =B8-R8-S8-T8 -> 0
A9: 6 | B9: =IF(A9<='Premium Calculation'!$B$8,R8,0) -> 0.62509819 | C9: {=IF(B9=0,0,_xlfn.XLOOKUP('Premium Calculation'!$B$4+A9-1,Mortality!$A$4:$A$64,_xlfn.XLOOKUP('Premium Calculation'!$B$5&" "&'Premium Calculation'!$B$6,Mortality!$B$3:$E$3,Mortality!$B$4:$E$64))*IF('Premium Calculation'!$B$7="Preferred",Assumptions!$C$30,IF('Premium Calculation'!$B$7="Rated",Assumptions!$C$31,1))*Assumptions!$C$21)} -> 0.00063058078 | D9: =IF(B9=0,0,MIN(1,MAX(Assumptions!$C$27,Assumptions!$C$13*Assumptions!$C$28^(A9-1))*Assumptions!$C$22)) -> 0.053244637 | E9: =B9*'Premium Calculation'!$B$29 -> 351.58184 | F9: =B9*C9*'Premium Calculation'!$B$9 -> 39.41749 | G9: =B9*C9*'Premium Calculation'!$B$14 -> 0 | H9: =F9-G9 -> 39.41749 | I9: =B9*(Assumptions!$C$10*(1+Assumptions!$C$5)^(A9-1)+IF(A9=1,Assumptions!$C$9,0))*Assumptions!$C$23 -> 167.31606 | J9: =E9*(IF(A9=1,'Premium Calculation'!$B$32,Assumptions!$C$12)+Assumptions!$C$24) -> 17.579092 | K9: =B9*'Premium Calculation'!$B$14*Assumptions!$C$15 -> 0 | L9: =E9-H9-I9-J9-K9 -> 127.2692 | M9: =(1+Assumptions!$C$6+Assumptions!$C$25)^(-A9) -> 0.81350064 | N9: =L9*M9 -> 103.53358 | O9: =B9*M9 -> 0.50851778 | P9: =O9*(IF(A9=1,'Premium Calculation'!$B$32,Assumptions!$C$12)+Assumptions!$C$24) -> 0.025425889 | Q9: =(H9+I9+K9)*M9 -> 168.17787 | R9: =B9-S9-T9 -> 0.59144188 | S9: =B9*C9 -> 0.0003941749 | T9: =(B9-S9)*D9 -> 0.033262139 | U9: =B9-R9-S9-T9 -> -5.5511151e-17
A10: 7 | B10: =IF(A10<='Premium Calculation'!$B$8,R9,0) -> 0.59144188 | C10: {=IF(B10=0,0,_xlfn.XLOOKUP('Premium Calculation'!$B$4+A10-1,Mortality!$A$4:$A$64,_xlfn.XLOOKUP('Premium Calculation'!$B$5&" "&'Premium Calculation'!$B$6,Mortality!$B$3:$E$3,Mortality!$B$4:$E$64))*IF('Premium Calculation'!$B$7="Preferred",Assumptions!$C$30,IF('Premium Calculation'!$B$7="Rated",Assumptions!$C$31,1))*Assumptions!$C$21)} -> 0.0006831 | D10: =IF(B10=0,0,MIN(1,MAX(Assumptions!$C$27,Assumptions!$C$13*Assumptions!$C$28^(A10-1))*Assumptions!$C$22)) -> 0.045257942 | E10: =B10*'Premium Calculation'!$B$29 -> 332.6521 | F10: =B10*C10*'Premium Calculation'!$B$9 -> 40.401395 | G10: =B10*C10*'Premium Calculation'!$B$14 -> 0 | H10: =F10-G10 -> 40.401395 | I10: =B10*(Assumptions!$C$10*(1+Assumptions!$C$5)^(A10-1)+IF(A10=1,Assumptions!$C$9,0))*Assumptions!$C$23 -> 164.63978 | J10: =E10*(IF(A10=1,'Premium Calculation'!$B$32,Assumptions!$C$12)+Assumptions!$C$24) -> 16.632605 | K10: =B10*'Premium Calculation'!$B$14*Assumptions!$C$15 -> 0 | L10: =E10-H10-I10-J10-K10 -> 110.97831 | M10: =(1+Assumptions!$C$6+Assumptions!$C$25)^(-A10) -> 0.78599096 | N10: =L10*M10 -> 87.227952 | O10: =B10*M10 -> 0.46486797 | P10: =O10*(IF(A10=1,'Premium Calculation'!$B$32,Assumptions!$C$12)+Assumptions!$C$24) -> 0.023243399 | Q10: =(H10+I10+K10)*M10 -> 161.16051 | R10: =B10-S10-T10 -> 0.56428871 | S10: =B10*C10 -> 0.00040401395 | T10: =(B10-S10)*D10 -> 0.026749157 | U10: =B10-R10-S10-T10 -> 0
A11: 8 | B11: =IF(A11<='Premium Calculation'!$B$8,R10,0) -> 0.56428871 | C11: {=IF(B11=0,0,_xlfn.XLOOKUP('Premium Calculation'!$B$4+A11-1,Mortality!$A$4:$A$64,_xlfn.XLOOKUP('Premium Calculation'!$B$5&" "&'Premium Calculation'!$B$6,Mortality!$B$3:$E$3,Mortality!$B$4:$E$64))*IF('Premium Calculation'!$B$7="Preferred",Assumptions!$C$30,IF('Premium Calculation'!$B$7="Rated",Assumptions!$C$31,1))*Assumptions!$C$21)} -> 0.0007399934 | D11: =IF(B11=0,0,MIN(1,MAX(Assumptions!$C$27,Assumptions!$C$13*Assumptions!$C$28^(A11-1))*Assumptions!$C$22)) -> 0.038469251 | E11: =B11*'Premium Calculation'!$B$29 -> 317.38 | F11: =B11*C11*'Premium Calculation'!$B$9 -> 41.756992 | G11: =B11*C11*'Premium Calculation'!$B$14 -> 0 | H11: =F11-G11 -> 41.756992 | I11: =B11*(Assumptions!$C$10*(1+Assumptions!$C$5)^(A11-1)+IF(A11=1,Assumptions!$C$9,0))*Assumptions!$C$23 -> 163.3644 | J11: =E11*(IF(A11=1,'Premium Calculation'!$B$32,Assumptions!$C$12)+Assumptions!$C$24) -> 15.869 | K11: =B11*'Premium Calculation'!$B$14*Assumptions!$C$15 -> 0 | L11: =E11-H11-I11-J11-K11 -> 96.38961 | M11: =(1+Assumptions!$C$6+Assumptions!$C$25)^(-A11) -> 0.75941156 | N11: =L11*M11 -> 73.199383 | O11: =B11*M11 -> 0.42852737 | P11: =O11*(IF(A11=1,'Premium Calculation'!$B$32,Assumptions!$C$12)+Assumptions!$C$24) -> 0.021426368 | Q11: =(H11+I11+K11)*M11 -> 155.77155 | R11: =B11-S11-T11 -> 0.54217944 | S11: =B11*C11 -> 0.00041756992 | T11: =(B11-S11)*D11 -> 0.0216917 | U11: =B11-R11-S11-T11 -> -5.8980598e-17
A12: 9 | B12: =IF(A12<='Premium Calculation'!$B$8,R11,0) -> 0.54217944 | C12: {=IF(B12=0,0,_xlfn.XLOOKUP('Premium Calculation'!$B$4+A12-1,Mortality!$A$4:$A$64,_xlfn.XLOOKUP('Premium Calculation'!$B$5&" "&'Premium Calculation'!$B$6,Mortality!$B$3:$E$3,Mortality!$B$4:$E$64))*IF('Premium Calculation'!$B$7="Preferred",Assumptions!$C$30,IF('Premium Calculation'!$B$7="Rated",Assumptions!$C$31,1))*Assumptions!$C$21)} -> 0.00080162528 | D12: =IF(B12=0,0,MIN(1,MAX(Assumptions!$C$27,Assumptions!$C$13*Assumptions!$C$28^(A12-1))*Assumptions!$C$22)) -> 0.032698863 | E12: =B12*'Premium Calculation'!$B$29 -> 304.9448 | F12: =B12*C12*'Premium Calculation'!$B$9 -> 43.462474 | G12: =B12*C12*'Premium Calculation'!$B$14 -> 0 | H12: =F12-G12 -> 43.462474 | I12: =B12*(Assumptions!$C$10*(1+Assumptions!$C$5)^(A12-1)+IF(A12=1,Assumptions!$C$9,0))*Assumptions!$C$23 -> 163.2422 | J12: =E12*(IF(A12=1,'Premium Calculation'!$B$32,Assumptions!$C$12)+Assumptions!$C$24) -> 15.24724 | K12: =B12*'Premium Calculation'!$B$14*Assumptions!$C$15 -> 0 | L12: =E12-H12-I12-J12-K12 -> 82.99289 | M12: =(1+Assumptions!$C$6+Assumptions!$C$25)^(-A12) -> 0.73373097 | N12: =L12*M12 -> 60.894454 | O12: =B12*M12 -> 0.39781385 | P12: =O12*(IF(A12=1,'Premium Calculation'!$B$32,Assumptions!$C$12)+Assumptions!$C$24) -> 0.019890692 | Q12: =(H12+I12+K12)*M12 -> 151.66562 | R12: =B12-S12-T12 -> 0.52403037 | S12: =B12*C12 -> 0.00043462474 | T12: =(B12-S12)*D12 -> 0.017714439 | U12: =B12-R12-S12-T12 -> 0
A13: 10 | B13: =IF(A13<='Premium Calculation'!$B$8,R12,0) -> 0.52403037 | C13: {=IF(B13=0,0,_xlfn.XLOOKUP('Premium Calculation'!$B$4+A13-1,Mortality!$A$4:$A$64,_xlfn.XLOOKUP('Premium Calculation'!$B$5&" "&'Premium Calculation'!$B$6,Mortality!$B$3:$E$3,Mortality!$B$4:$E$64))*IF('Premium Calculation'!$B$7="Preferred",Assumptions!$C$30,IF('Premium Calculation'!$B$7="Rated",Assumptions!$C$31,1))*Assumptions!$C$21)} -> 0.00086839029 | D13: =IF(B13=0,0,MIN(1,MAX(Assumptions!$C$27,Assumptions!$C$13*Assumptions!$C$28^(A13-1))*Assumptions!$C$22)) -> 0.027794034 | E13: =B13*'Premium Calculation'!$B$29 -> 294.737 | F13: =B13*C13*'Premium Calculation'!$B$9 -> 45.506289 | G13: =B13*C13*'Premium Calculation'!$B$14 -> 0 | H13: =F13-G13 -> 45.506289 | I13: =B13*(Assumptions!$C$10*(1+Assumptions!$C$5)^(A13-1)+IF(A13=1,Assumptions!$C$9,0))*Assumptions!$C$23 -> 164.0889 | J13: =E13*(IF(A13=1,'Premium Calculation'!$B$32,Assumptions!$C$12)+Assumptions!$C$24) -> 14.73685 | K13: =B13*'Premium Calculation'!$B$14*Assumptions!$C$15 -> 0 | L13: =E13-H13-I13-J13-K13 -> 70.404962 | M13: =(1+Assumptions!$C$6+Assumptions!$C$25)^(-A13) -> 0.70891881 | N13: =L13*M13 -> 49.911402 | O13: =B13*M13 -> 0.37149499 | P13: =O13*(IF(A13=1,'Premium Calculation'!$B$32,Assumptions!$C$12)+Assumptions!$C$24) -> 0.01857475 | Q13: =(H13+I13+K13)*M13 -> 148.58597 | R13: =B13-S13-T13 -> 0.50902304 | S13: =B13*C13 -> 0.00045506289 | T13: =(B13-S13)*D13 -> 0.01455227 | U13: =B13-R13-S13-T13 -> 2.6020852e-17
A14: 11 | B14: =IF(A14<='Premium Calculation'!$B$8,R13,0) -> 0 | C14: {=IF(B14=0,0,_xlfn.XLOOKUP('Premium Calculation'!$B$4+A14-1,Mortality!$A$4:$A$64,_xlfn.XLOOKUP('Premium Calculation'!$B$5&" "&'Premium Calculation'!$B$6,Mortality!$B$3:$E$3,Mortality!$B$4:$E$64))*IF('Premium Calculation'!$B$7="Preferred",Assumptions!$C$30,IF('Premium Calculation'!$B$7="Rated",Assumptions!$C$31,1))*Assumptions!$C$21)} -> 0 | D14: =IF(B14=0,0,MIN(1,MAX(Assumptions!$C$27,Assumptions!$C$13*Assumptions!$C$28^(A14-1))*Assumptions!$C$22)) -> 0 | E14: =B14*'Premium Calculation'!$B$29 -> 0 | F14: =B14*C14*'Premium Calculation'!$B$9 -> 0 | G14: =B14*C14*'Premium Calculation'!$B$14 -> 0 | H14: =F14-G14 -> 0 | I14: =B14*(Assumptions!$C$10*(1+Assumptions!$C$5)^(A14-1)+IF(A14=1,Assumptions!$C$9,0))*Assumptions!$C$23 -> 0 | J14: =E14*(IF(A14=1,'Premium Calculation'!$B$32,Assumptions!$C$12)+Assumptions!$C$24) -> 0 | K14: =B14*'Premium Calculation'!$B$14*Assumptions!$C$15 -> 0 | L14: =E14-H14-I14-J14-K14 -> 0 | M14: =(1+Assumptions!$C$6+Assumptions!$C$25)^(-A14) -> 0.68494571 | N14: =L14*M14 -> 0 | O14: =B14*M14 -> 0 | P14: =O14*(IF(A14=1,'Premium Calculation'!$B$32,Assumptions!$C$12)+Assumptions!$C$24) -> 0 | Q14: =(H14+I14+K14)*M14 -> 0 | R14: =B14-S14-T14 -> 0 | S14: =B14*C14 -> 0 | T14: =(B14-S14)*D14 -> 0 | U14: =B14-R14-S14-T14 -> 0
A15: 12 | B15: =IF(A15<='Premium Calculation'!$B$8,R14,0) -> 0 | C15: {=IF(B15=0,0,_xlfn.XLOOKUP('Premium Calculation'!$B$4+A15-1,Mortality!$A$4:$A$64,_xlfn.XLOOKUP('Premium Calculation'!$B$5&" "&'Premium Calculation'!$B$6,Mortality!$B$3:$E$3,Mortality!$B$4:$E$64))*IF('Premium Calculation'!$B$7="Preferred",Assumptions!$C$30,IF('Premium Calculation'!$B$7="Rated",Assumptions!$C$31,1))*Assumptions!$C$21)} -> 0 | D15: =IF(B15=0,0,MIN(1,MAX(Assumptions!$C$27,Assumptions!$C$13*Assumptions!$C$28^(A15-1))*Assumptions!$C$22)) -> 0 | E15: =B15*'Premium Calculation'!$B$29 -> 0 | F15: =B15*C15*'Premium Calculation'!$B$9 -> 0 | G15: =B15*C15*'Premium Calculation'!$B$14 -> 0 | H15: =F15-G15 -> 0 | I15: =B15*(Assumptions!$C$10*(1+Assumptions!$C$5)^(A15-1)+IF(A15=1,Assumptions!$C$9,0))*Assumptions!$C$23 -> 0 | J15: =E15*(IF(A15=1,'Premium Calculation'!$B$32,Assumptions!$C$12)+Assumptions!$C$24) -> 0 | K15: =B15*'Premium Calculation'!$B$14*Assumptions!$C$15 -> 0 | L15: =E15-H15-I15-J15-K15 -> 0 | M15: =(1+Assumptions!$C$6+Assumptions!$C$25)^(-A15) -> 0.6617833 | N15: =L15*M15 -> 0 | O15: =B15*M15 -> 0 | P15: =O15*(IF(A15=1,'Premium Calculation'!$B$32,Assumptions!$C$12)+Assumptions!$C$24) -> 0 | Q15: =(H15+I15+K15)*M15 -> 0 | R15: =B15-S15-T15 -> 0 | S15: =B15*C15 -> 0 | T15: =(B15-S15)*D15 -> 0 | U15: =B15-R15-S15-T15 -> 0
A16: 13 | B16: =IF(A16<='Premium Calculation'!$B$8,R15,0) -> 0 | C16: {=IF(B16=0,0,_xlfn.XLOOKUP('Premium Calculation'!$B$4+A16-1,Mortality!$A$4:$A$64,_xlfn.XLOOKUP('Premium Calculation'!$B$5&" "&'Premium Calculation'!$B$6,Mortality!$B$3:$E$3,Mortality!$B$4:$E$64))*IF('Premium Calculation'!$B$7="Preferred",Assumptions!$C$30,IF('Premium Calculation'!$B$7="Rated",Assumptions!$C$31,1))*Assumptions!$C$21)} -> 0 | D16: =IF(B16=0,0,MIN(1,MAX(Assumptions!$C$27,Assumptions!$C$13*Assumptions!$C$28^(A16-1))*Assumptions!$C$22)) -> 0 | E16: =B16*'Premium Calculation'!$B$29 -> 0 | F16: =B16*C16*'Premium Calculation'!$B$9 -> 0 | G16: =B16*C16*'Premium Calculation'!$B$14 -> 0 | H16: =F16-G16 -> 0 | I16: =B16*(Assumptions!$C$10*(1+Assumptions!$C$5)^(A16-1)+IF(A16=1,Assumptions!$C$9,0))*Assumptions!$C$23 -> 0 | J16: =E16*(IF(A16=1,'Premium Calculation'!$B$32,Assumptions!$C$12)+Assumptions!$C$24) -> 0 | K16: =B16*'Premium Calculation'!$B$14*Assumptions!$C$15 -> 0 | L16: =E16-H16-I16-J16-K16 -> 0 | M16: =(1+Assumptions!$C$6+Assumptions!$C$25)^(-A16) -> 0.63940415 | N16: =L16*M16 -> 0 | O16: =B16*M16 -> 0 | P16: =O16*(IF(A16=1,'Premium Calculation'!$B$32,Assumptions!$C$12)+Assumptions!$C$24) -> 0 | Q16: =(H16+I16+K16)*M16 -> 0 | R16: =B16-S16-T16 -> 0 | S16: =B16*C16 -> 0 | T16: =(B16-S16)*D16 -> 0 | U16: =B16-R16-S16-T16 -> 0
... A43: 40 | B43: =IF(A43<='Premium Calculation'!$B$8,R42,0) -> 0 | C43: {=IF(B43=0,0,_xlfn.XLOOKUP('Premium Calculation'!$B$4+A43-1,Mortality!$A$4:$A$64,_xlfn.XLOOKUP('Premium Calculation'!$B$5&" "&'Premium Calculation'!$B$6,Mortality!$B$3:$E$3,Mortality!$B$4:$E$64))*IF('Premium Calculation'!$B$7="Preferred",Assumptions!$C$30,IF('Premium Calculation'!$B$7="Rated",Assumptions!$C$31,1))*Assumptions!$C$21)} -> 0 | D43: =IF(B43=0,0,MIN(1,MAX(Assumptions!$C$27,Assumptions!$C$13*Assumptions!$C$28^(A43-1))*Assumptions!$C$22)) -> 0 | E43: =B43*'Premium Calculation'!$B$29 -> 0 | F43: =B43*C43*'Premium Calculation'!$B$9 -> 0 | G43: =B43*C43*'Premium Calculation'!$B$14 -> 0 | H43: =F43-G43 -> 0 | I43: =B43*(Assumptions!$C$10*(1+Assumptions!$C$5)^(A43-1)+IF(A43=1,Assumptions!$C$9,0))*Assumptions!$C$23 -> 0 | J43: =E43*(IF(A43=1,'Premium Calculation'!$B$32,Assumptions!$C$12)+Assumptions!$C$24) -> 0 | K43: =B43*'Premium Calculation'!$B$14*Assumptions!$C$15 -> 0 | L43: =E43-H43-I43-J43-K43 -> 0 | M43: =(1+Assumptions!$C$6+Assumptions!$C$25)^(-A43) -> 0.25257247 | N43: =L43*M43 -> 0 | O43: =B43*M43 -> 0 | P43: =O43*(IF(A43=1,'Premium Calculation'!$B$32,Assumptions!$C$12)+Assumptions!$C$24) -> 0 | Q43: =(H43+I43+K43)*M43 -> 0 | R43: =B43-S43-T43 -> 0 | S43: =B43*C43 -> 0 | T43: =(B43-S43)*D43 -> 0 | U43: =B43-R43-S43-T43 -> 0
A46: Annual projection with financial cash flows assumed at year end. Death is applied before lapses, and no surrender benefit is assumed for the term policy.

Sheet Reinsurance
A1: Reinsurance
A3: Metric | B3: Gross | C3: Ceded | D3: Net / retained | E3: Unit | F3: Comment
A4: Sum assured | B4: ='Premium Calculation'!B9 -> 100000 | C4: ='Premium Calculation'!B14 -> 0 | D4: =B4-C4 -> 100000 | E4: AED | F4: Amount above the retention limit is ceded
A5: Expected Year 1 claim | B5: =Cashflows!F4 -> 42.269093 | C5: =Cashflows!G4 -> 0 | D5: =Cashflows!H4 -> 42.269093 | E5: AED | F5: Expected claim cost in Year 1
A6: Year 1 reinsurance premium | B6: - | C6: =Cashflows!K4 -> 0 | D6: =-C6 -> 0 | E6: AED | F6: Cost of reinsurance
A7: Year 1 claim and reinsurance cost | B7: =Cashflows!F4 -> 42.269093 | C7: =Cashflows!G4-Cashflows!K4 -> 0 | D7: =B7-C7 -> 42.269093 | E7: AED | F7: Claims and reinsurance premium combined
A9: PV reinsurance recoveries | B9: =SUMPRODUCT(Cashflows!G4:G43,Cashflows!M4:M43) -> 0
A10: PV reinsurance premiums | B10: =SUMPRODUCT(Cashflows!K4:K43,Cashflows!M4:M43) -> 0
A11: Reinsurance impact on PVFP | B11: =B9-B10 -> 0
A12: PVFP without reinsurance | B12: ='Profit Testing'!B7-B11 -> 344.85011
A15: This section compares the economic impact of reinsurance on projected cash flows. Separate IFRS 17 accounting for reinsurance contracts held is not included.

Sheet Profit Testing
A1: Profit Testing
A3: Metric | B3: Value | C3: Unit | D3: Definition | F3: Year | G3: Cumulative discounted profit | H3: Break-even reached?
A4: PV premiums | B4: =SUMPRODUCT(Cashflows!E4:E43,Cashflows!M4:M43) -> 3296.2306 | C4: AED | D4: Present value of projected premiums | F4: 1 | G4: =SUM(Cashflows!$N$4:N4) -> -688.22708 | H4: =IF(AND(F4<='Premium Calculation'!$B$8,G4>=0),"Yes","No") -> No
A5: PV retained claims | B5: =SUMPRODUCT(Cashflows!H4:H43,Cashflows!M4:M43) -> 339.89781 | C5: AED | D5: Expected claims after RI recoveries | F5: 2 | G5: =SUM(Cashflows!$N$4:N5) -> -474.95109 | H5: =IF(AND(F5<='Premium Calculation'!$B$8,G5>=0),"Yes","No") -> No
A6: PV other outgo | B6: =SUMPRODUCT(Cashflows!I4:I43,Cashflows!M4:M43)+SUMPRODUCT(Cashflows!J4:J43,Cashflows!M4:M43)+SUMPRODUCT(Cashflows!K4:K43,Cashflows!M4:M43) -> 2611.4826 | C6: AED | D6: Expenses, commission and RI premiums | F6: 3 | G6: =SUM(Cashflows!$N$4:N6) -> -299.22373 | H6: =IF(AND(F6<='Premium Calculation'!$B$8,G6>=0),"Yes","No") -> No
A7: PVFP | B7: =SUM(Cashflows!N4:N43) -> 344.85011 | C7: AED | D7: Present value of future profits, before tax and capital costs | F7: 4 | G7: =SUM(Cashflows!$N$4:N7) -> -152.80898 | H7: =IF(AND(F7<='Premium Calculation'!$B$8,G7>=0),"Yes","No") -> No
A8: NBM | B8: =IF(B4=0,"n.a.",B7/B4) -> 0.10461954 | C8: % | D8: PVFP / PV premiums | F8: 5 | G8: =SUM(Cashflows!$N$4:N8) -> -29.91666 | H8: =IF(AND(F8<='Premium Calculation'!$B$8,G8>=0),"Yes","No") -> No
A9: Break-even year | B9: =IF(COUNTIF(H4:H43,"Yes")=0,"Not reached",_xlfn.XLOOKUP("Yes",H4:H43,F4:F43)) -> 6 | D9: First non-negative cumulative discounted profit | F9: 6 | G9: =SUM(Cashflows!$N$4:N9) -> 73.616918 | H9: =IF(AND(F9<='Premium Calculation'!$B$8,G9>=0),"Yes","No") -> Yes
A10: Profit status | B10: =IF(B7>=0,"Non-negative","Loss-making") -> Non-negative | D10: Indicates whether PVFP is positive or negative | F10: 7 | G10: =SUM(Cashflows!$N$4:N10) -> 160.84487 | H10: =IF(AND(F10<='Premium Calculation'!$B$8,G10>=0),"Yes","No") -> Yes
A11: Profit reconciliation | B11: =B4-B5-B6-B7 -> -1.1937118e-12 | C11: AED | D11: Should be zero if the cash flows reconcile | F11: 8 | G11: =SUM(Cashflows!$N$4:N11) -> 234.04425 | H11: =IF(AND(F11<='Premium Calculation'!$B$8,G11>=0),"Yes","No") -> Yes
F12: 9 | G12: =SUM(Cashflows!$N$4:N12) -> 294.93871 | H12: =IF(AND(F12<='Premium Calculation'!$B$8,G12>=0),"Yes","No") -> Yes
F13: 10 | G13: =SUM(Cashflows!$N$4:N13) -> 344.85011 | H13: =IF(AND(F13<='Premium Calculation'!$B$8,G13>=0),"Yes","No") -> Yes
A14: Financial cash flows are assumed to occur at year end in this annual projection. | F14: 11 | G14: =SUM(Cashflows!$N$4:N14) -> 344.85011 | H14: =IF(AND(F14<='Premium Calculation'!$B$8,G14>=0),"Yes","No") -> No
F15: 12 | G15: =SUM(Cashflows!$N$4:N15) -> 344.85011 | H15: =IF(AND(F15<='Premium Calculation'!$B$8,G15>=0),"Yes","No") -> No
A16: PVFP is calculated after RI and before tax and capital costs. | F16: 13 | G16: =SUM(Cashflows!$N$4:N16) -> 344.85011 | H16: =IF(AND(F16<='Premium Calculation'!$B$8,G16>=0),"Yes","No") -> No
F17: 14 | G17: =SUM(Cashflows!$N$4:N17) -> 344.85011 | H17: =IF(AND(F17<='Premium Calculation'!$B$8,G17>=0),"Yes","No") -> No
A18: NBM = PVFP / PV premiums. Break-even uses discounted profits. | F18: 15 | G18: =SUM(Cashflows!$N$4:N18) -> 344.85011 | H18: =IF(AND(F18<='Premium Calculation'!$B$8,G18>=0),"Yes","No") -> No
F19: 16 | G19: =SUM(Cashflows!$N$4:N19) -> 344.85011 | H19: =IF(AND(F19<='Premium Calculation'!$B$8,G19>=0),"Yes","No") -> No
F20: 17 | G20: =SUM(Cashflows!$N$4:N20) -> 344.85011 | H20: =IF(AND(F20<='Premium Calculation'!$B$8,G20>=0),"Yes","No") -> No
F21: 18 | G21: =SUM(Cashflows!$N$4:N21) -> 344.85011 | H21: =IF(AND(F21<='Premium Calculation'!$B$8,G21>=0),"Yes","No") -> No
F22: 19 | G22: =SUM(Cashflows!$N$4:N22) -> 344.85011 | H22: =IF(AND(F22<='Premium Calculation'!$B$8,G22>=0),"Yes","No") -> No
F23: 20 | G23: =SUM(Cashflows!$N$4:N23) -> 344.85011 | H23: =IF(AND(F23<='Premium Calculation'!$B$8,G23>=0),"Yes","No") -> No
F24: 21 | G24: =SUM(Cashflows!$N$4:N24) -> 344.85011 | H24: =IF(AND(F24<='Premium Calculation'!$B$8,G24>=0),"Yes","No") -> No
F25: 22 | G25: =SUM(Cashflows!$N$4:N25) -> 344.85011 | H25: =IF(AND(F25<='Premium Calculation'!$B$8,G25>=0),"Yes","No") -> No
F26: 23 | G26: =SUM(Cashflows!$N$4:N26) -> 344.85011 | H26: =IF(AND(F26<='Premium Calculation'!$B$8,G26>=0),"Yes","No") -> No
F27: 24 | G27: =SUM(Cashflows!$N$4:N27) -> 344.85011 | H27: =IF(AND(F27<='Premium Calculation'!$B$8,G27>=0),"Yes","No") -> No
F28: 25 | G28: =SUM(Cashflows!$N$4:N28) -> 344.85011 | H28: =IF(AND(F28<='Premium Calculation'!$B$8,G28>=0),"Yes","No") -> No
F29: 26 | G29: =SUM(Cashflows!$N$4:N29) -> 344.85011 | H29: =IF(AND(F29<='Premium Calculation'!$B$8,G29>=0),"Yes","No") -> No
F30: 27 | G30: =SUM(Cashflows!$N$4:N30) -> 344.85011 | H30: =IF(AND(F30<='Premium Calculation'!$B$8,G30>=0),"Yes","No") -> No
... F43: 40 | G43: =SUM(Cashflows!$N$4:N43) -> 344.85011 | H43: =IF(AND(F43<='Premium Calculation'!$B$8,G43>=0),"Yes","No") -> No

Sheet Portfolio Analysis
A1: Portfolio Analysis
A2: Analysis of profitability across the synthetic term life portfolio.
A3: Results are compared across key policy and customer segments to identify differences in premium adequacy and profitability.
A5: Portfolio observations
A6: Segment | C6: Lowest NBM | E6: NBM | F6: Highest NBM | H6: NBM | I6: Loss-making policies
A7: Channel | C7: =_xlfn.XLOOKUP(MIN($H$19:$H$21),$H$19:$H$21,$A$19:$A$21) -> Direct | E7: =MIN($H$19:$H$21) -> 0.027449464 | F7: =_xlfn.XLOOKUP(MAX($H$19:$H$21),$H$19:$H$21,$A$19:$A$21) -> Bancassurance | H7: =MAX($H$19:$H$21) -> 0.11053529 | I7: =_xlfn.XLOOKUP(MIN($H$19:$H$21),$H$19:$H$21,$I$19:$I$21)&" of "&_xlfn.XLOOKUP(MIN($H$19:$H$21),$H$19:$H$21,$B$19:$B$21) -> 20 of 52
A8: Entry-age band | C8: =_xlfn.XLOOKUP(MIN($H$26:$H$30),$H$26:$H$30,$A$26:$A$30) -> 50-59 | E8: =MIN($H$26:$H$30) -> -0.081048407 | F8: =_xlfn.XLOOKUP(MAX($H$26:$H$30),$H$26:$H$30,$A$26:$A$30) -> 20-29 | H8: =MAX($H$26:$H$30) -> 0.23642095 | I8: =_xlfn.XLOOKUP(MIN($H$26:$H$30),$H$26:$H$30,$I$26:$I$30)&" of "&_xlfn.XLOOKUP(MIN($H$26:$H$30),$H$26:$H$30,$B$26:$B$30) -> 25 of 32
A9: Sex | C9: =_xlfn.XLOOKUP(MIN($H$35:$H$36),$H$35:$H$36,$A$35:$A$36) -> Male | E9: =MIN($H$35:$H$36) -> 0.067523529 | F9: =_xlfn.XLOOKUP(MAX($H$35:$H$36),$H$35:$H$36,$A$35:$A$36) -> Female | H9: =MAX($H$35:$H$36) -> 0.10244139 | I9: =_xlfn.XLOOKUP(MIN($H$35:$H$36),$H$35:$H$36,$I$35:$I$36)&" of "&_xlfn.XLOOKUP(MIN($H$35:$H$36),$H$35:$H$36,$B$35:$B$36) -> 41 of 108
A10: Smoker status | C10: =_xlfn.XLOOKUP(MIN($H$41:$H$42),$H$41:$H$42,$A$41:$A$42) -> Smoker | E10: =MIN($H$41:$H$42) -> 0.059364413 | F10: =_xlfn.XLOOKUP(MAX($H$41:$H$42),$H$41:$H$42,$A$41:$A$42) -> Non-smoker | H10: =MAX($H$41:$H$42) -> 0.087001004 | I10: =_xlfn.XLOOKUP(MIN($H$41:$H$42),$H$41:$H$42,$I$41:$I$42)&" of "&_xlfn.XLOOKUP(MIN($H$41:$H$42),$H$41:$H$42,$B$41:$B$42) -> 16 of 33
A11: Underwriting class | C11: =_xlfn.XLOOKUP(MIN($H$47:$H$49),$H$47:$H$49,$A$47:$A$49) -> Rated | E11: =MIN($H$47:$H$49) -> 0.0083845365 | F11: =_xlfn.XLOOKUP(MAX($H$47:$H$49),$H$47:$H$49,$A$47:$A$49) -> Standard | H11: =MAX($H$47:$H$49) -> 0.09284291 | I11: =_xlfn.XLOOKUP(MIN($H$47:$H$49),$H$47:$H$49,$I$47:$I$49)&" of "&_xlfn.XLOOKUP(MIN($H$47:$H$49),$H$47:$H$49,$B$47:$B$49) -> 9 of 19
A12: Sum-assured band (AED) | C12: =_xlfn.XLOOKUP(MIN($H$54:$H$57),$H$54:$H$57,$A$54:$A$57) -> 250k-500k | E12: =MIN($H$54:$H$57) -> -0.09855425 | F12: =_xlfn.XLOOKUP(MAX($H$54:$H$57),$H$54:$H$57,$A$54:$A$57) -> Over 1m | H12: =MAX($H$54:$H$57) -> 0.265673 | I12: =_xlfn.XLOOKUP(MIN($H$54:$H$57),$H$54:$H$57,$I$54:$I$57)&" of "&_xlfn.XLOOKUP(MIN($H$54:$H$57),$H$54:$H$57,$B$54:$B$57) -> 35 of 61
A13: Premium frequency | C13: =_xlfn.XLOOKUP(MIN($H$62:$H$63),$H$62:$H$63,$A$62:$A$63) -> Monthly | E13: =MIN($H$62:$H$63) -> 0.065369441 | F13: =_xlfn.XLOOKUP(MAX($H$62:$H$63),$H$62:$H$63,$A$62:$A$63) -> Annual | H13: =MAX($H$62:$H$63) -> 0.096804275 | I13: =_xlfn.XLOOKUP(MIN($H$62:$H$63),$H$62:$H$63,$I$62:$I$63)&" of "&_xlfn.XLOOKUP(MIN($H$62:$H$63),$H$62:$H$63,$B$62:$B$63) -> 38 of 93
A14: Policy term (years) | C14: =_xlfn.XLOOKUP(MIN($H$68:$H$71),$H$68:$H$71,$A$68:$A$71) -> 25 | E14: =MIN($H$68:$H$71) -> -0.061358489 | F14: =_xlfn.XLOOKUP(MAX($H$68:$H$71),$H$68:$H$71,$A$68:$A$71) -> 10 | H14: =MAX($H$68:$H$71) -> 0.1838517 | I14: =_xlfn.XLOOKUP(MIN($H$68:$H$71),$H$68:$H$71,$I$68:$I$71)&" of "&_xlfn.XLOOKUP(MIN($H$68:$H$71),$H$68:$H$71,$B$68:$B$71) -> 14 of 22
A17: By channel
A18: Channel | B18: Policies | C18: Charged prem. | D18: Technical prem. | E18: Adequacy | F18: PV premiums | G18: PVFP | H18: NBM | I18: Loss-making | J18: % loss-making | K18: Share of PVFP | L18: Profitability
A19: Direct | B19: =COUNTIFS('Policy Calculations'!$K$30:$K$279,$A19,'Policy Calculations'!$T$30:$T$279,1) -> 52 | C19: =SUMIFS('Policy Calculations'!$M$30:$M$279,'Policy Calculations'!$K$30:$K$279,$A19,'Policy Calculations'!$T$30:$T$279,1) -> 104688.1 | D19: =SUMIFS('Policy Calculations'!$AF$30:$AF$279,'Policy Calculations'!$K$30:$K$279,$A19,'Policy Calculations'!$T$30:$T$279,1) -> 112641.43 | E19: =IF(D19=0,"",C19/D19) -> 0.92939251 | F19: =SUMIFS('Policy Calculations'!$AH$30:$AH$279,'Policy Calculations'!$K$30:$K$279,$A19,'Policy Calculations'!$T$30:$T$279,1) -> 804459.56 | G19: =SUMIFS('Policy Calculations'!$AI$30:$AI$279,'Policy Calculations'!$K$30:$K$279,$A19,'Policy Calculations'!$T$30:$T$279,1) -> 22081.984 | H19: =IF(F19=0,"",G19/F19) -> 0.027449464 | I19: =COUNTIFS('Policy Calculations'!$K$30:$K$279,$A19,'Policy Calculations'!$AR$30:$AR$279,"Loss-making") -> 20 | J19: =IF(B19=0,"",I19/B19) -> 0.38461538 | K19: =IF('Portfolio Totals'!$B$13=0,"",G19/'Portfolio Totals'!$B$13) -> 0.086167796 | L19: =IF(B19=0,"No policies",IF(G19<0,"Loss-making segment",IF(H19<Assumptions!$C$16-0.00001,"Below target","At or above target"))) -> Below target
A20: Broker | B20: =COUNTIFS('Policy Calculations'!$K$30:$K$279,$A20,'Policy Calculations'!$T$30:$T$279,1) -> 52 | C20: =SUMIFS('Policy Calculations'!$M$30:$M$279,'Policy Calculations'!$K$30:$K$279,$A20,'Policy Calculations'!$T$30:$T$279,1) -> 137646.31 | D20: =SUMIFS('Policy Calculations'!$AF$30:$AF$279,'Policy Calculations'!$K$30:$K$279,$A20,'Policy Calculations'!$T$30:$T$279,1) -> 138784.98 | E20: =IF(D20=0,"",C20/D20) -> 0.99179547 | F20: =SUMIFS('Policy Calculations'!$AH$30:$AH$279,'Policy Calculations'!$K$30:$K$279,$A20,'Policy Calculations'!$T$30:$T$279,1) -> 1043157.6 | G20: =SUMIFS('Policy Calculations'!$AI$30:$AI$279,'Policy Calculations'!$K$30:$K$279,$A20,'Policy Calculations'!$T$30:$T$279,1) -> 84276.908 | H20: =IF(F20=0,"",G20/F20) -> 0.080790197 | I20: =COUNTIFS('Policy Calculations'!$K$30:$K$279,$A20,'Policy Calculations'!$AR$30:$AR$279,"Loss-making") -> 23 | J20: =IF(B20=0,"",I20/B20) -> 0.44230769 | K20: =IF('Portfolio Totals'!$B$13=0,"",G20/'Portfolio Totals'!$B$13) -> 0.32886336 | L20: =IF(B20=0,"No policies",IF(G20<0,"Loss-making segment",IF(H20<Assumptions!$C$16-0.00001,"Below target","At or above target"))) -> At or above target
A21: Bancassurance | B21: =COUNTIFS('Policy Calculations'!$K$30:$K$279,$A21,'Policy Calculations'!$T$30:$T$279,1) -> 65 | C21: =SUMIFS('Policy Calculations'!$M$30:$M$279,'Policy Calculations'!$K$30:$K$279,$A21,'Policy Calculations'!$T$30:$T$279,1) -> 187546.49 | D21: =SUMIFS('Policy Calculations'!$AF$30:$AF$279,'Policy Calculations'!$K$30:$K$279,$A21,'Policy Calculations'!$T$30:$T$279,1) -> 180931.69 | E21: =IF(D21=0,"",C21/D21) -> 1.0365596 | F21: =SUMIFS('Policy Calculations'!$AH$30:$AH$279,'Policy Calculations'!$K$30:$K$279,$A21,'Policy Calculations'!$T$30:$T$279,1) -> 1356203.6 | G21: =SUMIFS('Policy Calculations'!$AI$30:$AI$279,'Policy Calculations'!$K$30:$K$279,$A21,'Policy Calculations'!$T$30:$T$279,1) -> 149908.35 | H21: =IF(F21=0,"",G21/F21) -> 0.11053529 | I21: =COUNTIFS('Policy Calculations'!$K$30:$K$279,$A21,'Policy Calculations'!$AR$30:$AR$279,"Loss-making") -> 22 | J21: =IF(B21=0,"",I21/B21) -> 0.33846154 | K21: =IF('Portfolio Totals'!$B$13=0,"",G21/'Portfolio Totals'!$B$13) -> 0.58496884 | L21: =IF(B21=0,"No policies",IF(G21<0,"Loss-making segment",IF(H21<Assumptions!$C$16-0.00001,"Below target","At or above target"))) -> At or above target
A22: Total | B22: =SUM(B19:B21) -> 169 | C22: =SUM(C19:C21) -> 429880.9 | D22: =SUM(D19:D21) -> 432358.1 | E22: =IF(D22=0,"",C22/D22) -> 0.9942705 | F22: =SUM(F19:F21) -> 3203820.8 | G22: =SUM(G19:G21) -> 256267.25 | H22: =IF(F22=0,"",G22/F22) -> 0.07998801 | I22: =SUM(I19:I21) -> 65 | J22: =IF(B22=0,"",I22/B22) -> 0.38461538 | K22: =G22-'Portfolio Totals'!$B$13 -> 0 | L22: =IF(ABS(K22)<0.01,"Reconciles to portfolio","CHECK") -> Reconciles to portfolio
A24: By entry-age band
A25: Entry-age band | B25: Policies | C25: Charged prem. | D25: Technical prem. | E25: Adequacy | F25: PV premiums | G25: PVFP | H25: NBM | I25: Loss-making | J25: % loss-making | K25: Share of PVFP | L25: Assessment
A26: 20-29 | B26: =COUNTIFS('Policy Calculations'!$AP$30:$AP$279,$A26,'Policy Calculations'!$T$30:$T$279,1) -> 34 | C26: =SUMIFS('Policy Calculations'!$M$30:$M$279,'Policy Calculations'!$AP$30:$AP$279,$A26,'Policy Calculations'!$T$30:$T$279,1) -> 47484.16 | D26: =SUMIFS('Policy Calculations'!$AF$30:$AF$279,'Policy Calculations'!$AP$30:$AP$279,$A26,'Policy Calculations'!$T$30:$T$279,1) -> 38941.752 | E26: =IF(D26=0,"",C26/D26) -> 1.2193637 | F26: =SUMIFS('Policy Calculations'!$AH$30:$AH$279,'Policy Calculations'!$AP$30:$AP$279,$A26,'Policy Calculations'!$T$30:$T$279,1) -> 372230.06 | G26: =SUMIFS('Policy Calculations'!$AI$30:$AI$279,'Policy Calculations'!$AP$30:$AP$279,$A26,'Policy Calculations'!$T$30:$T$279,1) -> 88002.983 | H26: =IF(F26=0,"",G26/F26) -> 0.23642095 | I26: =COUNTIFS('Policy Calculations'!$AP$30:$AP$279,$A26,'Policy Calculations'!$AR$30:$AR$279,"Loss-making") -> 5 | J26: =IF(B26=0,"",I26/B26) -> 0.14705882 | K26: =IF('Portfolio Totals'!$B$13=0,"",G26/'Portfolio Totals'!$B$13) -> 0.34340316 | L26: =IF(B26=0,"No policies",IF(G26<0,"Loss-making segment",IF(H26<Assumptions!$C$16-0.00001,"Below target","At or above target"))) -> At or above target
A27: 30-39 | B27: =COUNTIFS('Policy Calculations'!$AP$30:$AP$279,$A27,'Policy Calculations'!$T$30:$T$279,1) -> 46 | C27: =SUMIFS('Policy Calculations'!$M$30:$M$279,'Policy Calculations'!$AP$30:$AP$279,$A27,'Policy Calculations'!$T$30:$T$279,1) -> 77395.17 | D27: =SUMIFS('Policy Calculations'!$AF$30:$AF$279,'Policy Calculations'!$AP$30:$AP$279,$A27,'Policy Calculations'!$T$30:$T$279,1) -> 74741.957 | E27: =IF(D27=0,"",C27/D27) -> 1.0354983 | F27: =SUMIFS('Policy Calculations'!$AH$30:$AH$279,'Policy Calculations'!$AP$30:$AP$279,$A27,'Policy Calculations'!$T$30:$T$279,1) -> 618458.75 | G27: =SUMIFS('Policy Calculations'!$AI$30:$AI$279,'Policy Calculations'!$AP$30:$AP$279,$A27,'Policy Calculations'!$T$30:$T$279,1) -> 73936.805 | H27: =IF(F27=0,"",G27/F27) -> 0.1195501 | I27: =COUNTIFS('Policy Calculations'!$AP$30:$AP$279,$A27,'Policy Calculations'!$AR$30:$AR$279,"Loss-making") -> 9 | J27: =IF(B27=0,"",I27/B27) -> 0.19565217 | K27: =IF('Portfolio Totals'!$B$13=0,"",G27/'Portfolio Totals'!$B$13) -> 0.28851446 | L27: =IF(B27=0,"No policies",IF(G27<0,"Loss-making segment",IF(H27<Assumptions!$C$16-0.00001,"Below target","At or above target"))) -> At or above target
A28: 40-49 | B28: =COUNTIFS('Policy Calculations'!$AP$30:$AP$279,$A28,'Policy Calculations'!$T$30:$T$279,1) -> 41 | C28: =SUMIFS('Policy Calculations'!$M$30:$M$279,'Policy Calculations'!$AP$30:$AP$279,$A28,'Policy Calculations'!$T$30:$T$279,1) -> 94532.21 | D28: =SUMIFS('Policy Calculations'!$AF$30:$AF$279,'Policy Calculations'!$AP$30:$AP$279,$A28,'Policy Calculations'!$T$30:$T$279,1) -> 97935.199 | E28: =IF(D28=0,"",C28/D28) -> 0.96525265 | F28: =SUMIFS('Policy Calculations'!$AH$30:$AH$279,'Policy Calculations'!$AP$30:$AP$279,$A28,'Policy Calculations'!$T$30:$T$279,1) -> 717786.45 | G28: =SUMIFS('Policy Calculations'!$AI$30:$AI$279,'Policy Calculations'!$AP$30:$AP$279,$A28,'Policy Calculations'!$T$30:$T$279,1) -> 38243.883 | H28: =IF(F28=0,"",G28/F28) -> 0.053280309 | I28: =COUNTIFS('Policy Calculations'!$AP$30:$AP$279,$A28,'Policy Calculations'!$AR$30:$AR$279,"Loss-making") -> 17 | J28: =IF(B28=0,"",I28/B28) -> 0.41463415 | K28: =IF('Portfolio Totals'!$B$13=0,"",G28/'Portfolio Totals'!$B$13) -> 0.14923438 | L28: =IF(B28=0,"No policies",IF(G28<0,"Loss-making segment",IF(H28<Assumptions!$C$16-0.00001,"Below target","At or above target"))) -> Below target
A29: 50-59 | B29: =COUNTIFS('Policy Calculations'!$AP$30:$AP$279,$A29,'Policy Calculations'!$T$30:$T$279,1) -> 32 | C29: =SUMIFS('Policy Calculations'!$M$30:$M$279,'Policy Calculations'!$AP$30:$AP$279,$A29,'Policy Calculations'!$T$30:$T$279,1) -> 99499.53 | D29: =SUMIFS('Policy Calculations'!$AF$30:$AF$279,'Policy Calculations'!$AP$30:$AP$279,$A29,'Policy Calculations'!$T$30:$T$279,1) -> 119144.88 | E29: =IF(D29=0,"",C29/D29) -> 0.83511374 | F29: =SUMIFS('Policy Calculations'!$AH$30:$AH$279,'Policy Calculations'!$AP$30:$AP$279,$A29,'Policy Calculations'!$T$30:$T$279,1) -> 762947 | G29: =SUMIFS('Policy Calculations'!$AI$30:$AI$279,'Policy Calculations'!$AP$30:$AP$279,$A29,'Policy Calculations'!$T$30:$T$279,1) -> -61835.638 | H29: =IF(F29=0,"",G29/F29) -> -0.081048407 | I29: =COUNTIFS('Policy Calculations'!$AP$30:$AP$279,$A29,'Policy Calculations'!$AR$30:$AR$279,"Loss-making") -> 25 | J29: =IF(B29=0,"",I29/B29) -> 0.78125 | K29: =IF('Portfolio Totals'!$B$13=0,"",G29/'Portfolio Totals'!$B$13) -> -0.24129357 | L29: =IF(B29=0,"No policies",IF(G29<0,"Loss-making segment",IF(H29<Assumptions!$C$16-0.00001,"Below target","At or above target"))) -> Loss-making segment
A30: 60+ | B30: =COUNTIFS('Policy Calculations'!$AP$30:$AP$279,$A30,'Policy Calculations'!$T$30:$T$279,1) -> 16 | C30: =SUMIFS('Policy Calculations'!$M$30:$M$279,'Policy Calculations'!$AP$30:$AP$279,$A30,'Policy Calculations'!$T$30:$T$279,1) -> 110969.83 | D30: =SUMIFS('Policy Calculations'!$AF$30:$AF$279,'Policy Calculations'!$AP$30:$AP$279,$A30,'Policy Calculations'!$T$30:$T$279,1) -> 101594.31 | E30: =IF(D30=0,"",C30/D30) -> 1.092284 | F30: =SUMIFS('Policy Calculations'!$AH$30:$AH$279,'Policy Calculations'!$AP$30:$AP$279,$A30,'Policy Calculations'!$T$30:$T$279,1) -> 732398.52 | G30: =SUMIFS('Policy Calculations'!$AI$30:$AI$279,'Policy Calculations'!$AP$30:$AP$279,$A30,'Policy Calculations'!$T$30:$T$279,1) -> 117919.21 | H30: =IF(F30=0,"",G30/F30) -> 0.16100417 | I30: =COUNTIFS('Policy Calculations'!$AP$30:$AP$279,$A30,'Policy Calculations'!$AR$30:$AR$279,"Loss-making") -> 9 | J30: =IF(B30=0,"",I30/B30) -> 0.5625 | K30: =IF('Portfolio Totals'!$B$13=0,"",G30/'Portfolio Totals'!$B$13) -> 0.46014157 | L30: =IF(B30=0,"No policies",IF(G30<0,"Loss-making segment",IF(H30<Assumptions!$C$16-0.00001,"Below target","At or above target"))) -> At or above target
A31: Total | B31: =SUM(B26:B30) -> 169 | C31: =SUM(C26:C30) -> 429880.9 | D31: =SUM(D26:D30) -> 432358.1 | E31: =IF(D31=0,"",C31/D31) -> 0.9942705 | F31: =SUM(F26:F30) -> 3203820.8 | G31: =SUM(G26:G30) -> 256267.25 | H31: =IF(F31=0,"",G31/F31) -> 0.07998801 | I31: =SUM(I26:I30) -> 65 | J31: =IF(B31=0,"",I31/B31) -> 0.38461538 | K31: =G31-'Portfolio Totals'!$B$13 -> 0
A33: By sex
A34: Sex | B34: Policies | C34: Charged prem. | D34: Technical prem. | E34: Adequacy | F34: PV premiums | G34: PVFP | H34: NBM | I34: Loss-making | J34: % loss-making | K34: Share of PVFP | L34: Assessment
A35: Male | B35: =COUNTIFS('Policy Calculations'!$E$30:$E$279,$A35,'Policy Calculations'!$T$30:$T$279,1) -> 108 | C35: =SUMIFS('Policy Calculations'!$M$30:$M$279,'Policy Calculations'!$E$30:$E$279,$A35,'Policy Calculations'!$T$30:$T$279,1) -> 278179.03 | D35: =SUMIFS('Policy Calculations'!$AF$30:$AF$279,'Policy Calculations'!$E$30:$E$279,$A35,'Policy Calculations'!$T$30:$T$279,1) -> 285398.52 | E35: =IF(D35=0,"",C35/D35) -> 0.97470383 | F35: =SUMIFS('Policy Calculations'!$AH$30:$AH$279,'Policy Calculations'!$E$30:$E$279,$A35,'Policy Calculations'!$T$30:$T$279,1) -> 2060166.5 | G35: =SUMIFS('Policy Calculations'!$AI$30:$AI$279,'Policy Calculations'!$E$30:$E$279,$A35,'Policy Calculations'!$T$30:$T$279,1) -> 139109.71 | H35: =IF(F35=0,"",G35/F35) -> 0.067523529 | I35: =COUNTIFS('Policy Calculations'!$E$30:$E$279,$A35,'Policy Calculations'!$AR$30:$AR$279,"Loss-making") -> 41 | J35: =IF(B35=0,"",I35/B35) -> 0.37962963 | K35: =IF('Portfolio Totals'!$B$13=0,"",G35/'Portfolio Totals'!$B$13) -> 0.54283062 | L35: =IF(B35=0,"No policies",IF(G35<0,"Loss-making segment",IF(H35<Assumptions!$C$16-0.00001,"Below target","At or above target"))) -> Below target
A36: Female | B36: =COUNTIFS('Policy Calculations'!$E$30:$E$279,$A36,'Policy Calculations'!$T$30:$T$279,1) -> 61 | C36: =SUMIFS('Policy Calculations'!$M$30:$M$279,'Policy Calculations'!$E$30:$E$279,$A36,'Policy Calculations'!$T$30:$T$279,1) -> 151701.87 | D36: =SUMIFS('Policy Calculations'!$AF$30:$AF$279,'Policy Calculations'!$E$30:$E$279,$A36,'Policy Calculations'!$T$30:$T$279,1) -> 146959.58 | E36: =IF(D36=0,"",C36/D36) -> 1.0322694 | F36: =SUMIFS('Policy Calculations'!$AH$30:$AH$279,'Policy Calculations'!$E$30:$E$279,$A36,'Policy Calculations'!$T$30:$T$279,1) -> 1143654.3 | G36: =SUMIFS('Policy Calculations'!$AI$30:$AI$279,'Policy Calculations'!$E$30:$E$279,$A36,'Policy Calculations'!$T$30:$T$279,1) -> 117157.54 | H36: =IF(F36=0,"",G36/F36) -> 0.10244139 | I36: =COUNTIFS('Policy Calculations'!$E$30:$E$279,$A36,'Policy Calculations'!$AR$30:$AR$279,"Loss-making") -> 24 | J36: =IF(B36=0,"",I36/B36) -> 0.39344262 | K36: =IF('Portfolio Totals'!$B$13=0,"",G36/'Portfolio Totals'!$B$13) -> 0.45716938 | L36: =IF(B36=0,"No policies",IF(G36<0,"Loss-making segment",IF(H36<Assumptions!$C$16-0.00001,"Below target","At or above target"))) -> At or above target
A37: Total | B37: =SUM(B35:B36) -> 169 | C37: =SUM(C35:C36) -> 429880.9 | D37: =SUM(D35:D36) -> 432358.1 | E37: =IF(D37=0,"",C37/D37) -> 0.9942705 | F37: =SUM(F35:F36) -> 3203820.8 | G37: =SUM(G35:G36) -> 256267.25 | H37: =IF(F37=0,"",G37/F37) -> 0.07998801 | I37: =SUM(I35:I36) -> 65 | J37: =IF(B37=0,"",I37/B37) -> 0.38461538 | K37: =G37-'Portfolio Totals'!$B$13 -> 0
A39: By smoker status
A40: Smoker status | B40: Policies | C40: Charged prem. | D40: Technical prem. | E40: Adequacy | F40: PV premiums | G40: PVFP | H40: NBM | I40: Loss-making | J40: % loss-making | K40: Share of PVFP | L40: Assessment
A41: Non-smoker | B41: =COUNTIFS('Policy Calculations'!$F$30:$F$279,$A41,'Policy Calculations'!$T$30:$T$279,1) -> 136 | C41: =SUMIFS('Policy Calculations'!$M$30:$M$279,'Policy Calculations'!$F$30:$F$279,$A41,'Policy Calculations'!$T$30:$T$279,1) -> 317068.96 | D41: =SUMIFS('Policy Calculations'!$AF$30:$AF$279,'Policy Calculations'!$F$30:$F$279,$A41,'Policy Calculations'!$T$30:$T$279,1) -> 315769.2 | E41: =IF(D41=0,"",C41/D41) -> 1.0041162 | F41: =SUMIFS('Policy Calculations'!$AH$30:$AH$279,'Policy Calculations'!$F$30:$F$279,$A41,'Policy Calculations'!$T$30:$T$279,1) -> 2390827 | G41: =SUMIFS('Policy Calculations'!$AI$30:$AI$279,'Policy Calculations'!$F$30:$F$279,$A41,'Policy Calculations'!$T$30:$T$279,1) -> 208004.35 | H41: =IF(F41=0,"",G41/F41) -> 0.087001004 | I41: =COUNTIFS('Policy Calculations'!$F$30:$F$279,$A41,'Policy Calculations'!$AR$30:$AR$279,"Loss-making") -> 49 | J41: =IF(B41=0,"",I41/B41) -> 0.36029412 | K41: =IF('Portfolio Totals'!$B$13=0,"",G41/'Portfolio Totals'!$B$13) -> 0.81166967 | L41: =IF(B41=0,"No policies",IF(G41<0,"Loss-making segment",IF(H41<Assumptions!$C$16-0.00001,"Below target","At or above target"))) -> At or above target
A42: Smoker | B42: =COUNTIFS('Policy Calculations'!$F$30:$F$279,$A42,'Policy Calculations'!$T$30:$T$279,1) -> 33 | C42: =SUMIFS('Policy Calculations'!$M$30:$M$279,'Policy Calculations'!$F$30:$F$279,$A42,'Policy Calculations'!$T$30:$T$279,1) -> 112811.94 | D42: =SUMIFS('Policy Calculations'!$AF$30:$AF$279,'Policy Calculations'!$F$30:$F$279,$A42,'Policy Calculations'!$T$30:$T$279,1) -> 116588.9 | E42: =IF(D42=0,"",C42/D42) -> 0.96760447 | F42: =SUMIFS('Policy Calculations'!$AH$30:$AH$279,'Policy Calculations'!$F$30:$F$279,$A42,'Policy Calculations'!$T$30:$T$279,1) -> 812993.73 | G42: =SUMIFS('Policy Calculations'!$AI$30:$AI$279,'Policy Calculations'!$F$30:$F$279,$A42,'Policy Calculations'!$T$30:$T$279,1) -> 48262.896 | H42: =IF(F42=0,"",G42/F42) -> 0.059364413 | I42: =COUNTIFS('Policy Calculations'!$F$30:$F$279,$A42,'Policy Calculations'!$AR$30:$AR$279,"Loss-making") -> 16 | J42: =IF(B42=0,"",I42/B42) -> 0.48484848 | K42: =IF('Portfolio Totals'!$B$13=0,"",G42/'Portfolio Totals'!$B$13) -> 0.18833033 | L42: =IF(B42=0,"No policies",IF(G42<0,"Loss-making segment",IF(H42<Assumptions!$C$16-0.00001,"Below target","At or above target"))) -> Below target
A43: Total | B43: =SUM(B41:B42) -> 169 | C43: =SUM(C41:C42) -> 429880.9 | D43: =SUM(D41:D42) -> 432358.1 | E43: =IF(D43=0,"",C43/D43) -> 0.9942705 | F43: =SUM(F41:F42) -> 3203820.8 | G43: =SUM(G41:G42) -> 256267.25 | H43: =IF(F43=0,"",G43/F43) -> 0.07998801 | I43: =SUM(I41:I42) -> 65 | J43: =IF(B43=0,"",I43/B43) -> 0.38461538 | K43: =G43-'Portfolio Totals'!$B$13 -> 0
A45: By underwriting class
A46: Underwriting class | B46: Policies | C46: Charged prem. | D46: Technical prem. | E46: Adequacy | F46: PV premiums | G46: PVFP | H46: NBM | I46: Loss-making | J46: % loss-making | K46: Share of PVFP | L46: Assessment
A47: Preferred | B47: =COUNTIFS('Policy Calculations'!$G$30:$G$279,$A47,'Policy Calculations'!$T$30:$T$279,1) -> 25 | C47: =SUMIFS('Policy Calculations'!$M$30:$M$279,'Policy Calculations'!$G$30:$G$279,$A47,'Policy Calculations'!$T$30:$T$279,1) -> 65974.29 | D47: =SUMIFS('Policy Calculations'!$AF$30:$AF$279,'Policy Calculations'!$G$30:$G$279,$A47,'Policy Calculations'!$T$30:$T$279,1) -> 66860.246 | E47: =IF(D47=0,"",C47/D47) -> 0.98674913 | F47: =SUMIFS('Policy Calculations'!$AH$30:$AH$279,'Policy Calculations'!$G$30:$G$279,$A47,'Policy Calculations'!$T$30:$T$279,1) -> 495995.03 | G47: =SUMIFS('Policy Calculations'!$AI$30:$AI$279,'Policy Calculations'!$G$30:$G$279,$A47,'Policy Calculations'!$T$30:$T$279,1) -> 33521.554 | H47: =IF(F47=0,"",G47/F47) -> 0.067584455 | I47: =COUNTIFS('Policy Calculations'!$G$30:$G$279,$A47,'Policy Calculations'!$AR$30:$AR$279,"Loss-making") -> 11 | J47: =IF(B47=0,"",I47/B47) -> 0.44 | K47: =IF('Portfolio Totals'!$B$13=0,"",G47/'Portfolio Totals'!$B$13) -> 0.13080702 | L47: =IF(B47=0,"No policies",IF(G47<0,"Loss-making segment",IF(H47<Assumptions!$C$16-0.00001,"Below target","At or above target"))) -> Below target
A48: Standard | B48: =COUNTIFS('Policy Calculations'!$G$30:$G$279,$A48,'Policy Calculations'!$T$30:$T$279,1) -> 125 | C48: =SUMIFS('Policy Calculations'!$M$30:$M$279,'Policy Calculations'!$G$30:$G$279,$A48,'Policy Calculations'!$T$30:$T$279,1) -> 319155.25 | D48: =SUMIFS('Policy Calculations'!$AF$30:$AF$279,'Policy Calculations'!$G$30:$G$279,$A48,'Policy Calculations'!$T$30:$T$279,1) -> 316249.82 | E48: =IF(D48=0,"",C48/D48) -> 1.0091871 | F48: =SUMIFS('Policy Calculations'!$AH$30:$AH$279,'Policy Calculations'!$G$30:$G$279,$A48,'Policy Calculations'!$T$30:$T$279,1) -> 2368525.7 | G48: =SUMIFS('Policy Calculations'!$AI$30:$AI$279,'Policy Calculations'!$G$30:$G$279,$A48,'Policy Calculations'!$T$30:$T$279,1) -> 219900.82 | H48: =IF(F48=0,"",G48/F48) -> 0.09284291 | I48: =COUNTIFS('Policy Calculations'!$G$30:$G$279,$A48,'Policy Calculations'!$AR$30:$AR$279,"Loss-making") -> 45 | J48: =IF(B48=0,"",I48/B48) -> 0.36 | K48: =IF('Portfolio Totals'!$B$13=0,"",G48/'Portfolio Totals'!$B$13) -> 0.85809179 | L48: =IF(B48=0,"No policies",IF(G48<0,"Loss-making segment",IF(H48<Assumptions!$C$16-0.00001,"Below target","At or above target"))) -> At or above target
A49: Rated | B49: =COUNTIFS('Policy Calculations'!$G$30:$G$279,$A49,'Policy Calculations'!$T$30:$T$279,1) -> 19 | C49: =SUMIFS('Policy Calculations'!$M$30:$M$279,'Policy Calculations'!$G$30:$G$279,$A49,'Policy Calculations'!$T$30:$T$279,1) -> 44751.36 | D49: =SUMIFS('Policy Calculations'!$AF$30:$AF$279,'Policy Calculations'!$G$30:$G$279,$A49,'Policy Calculations'!$T$30:$T$279,1) -> 49248.027 | E49: =IF(D49=0,"",C49/D49) -> 0.90869346 | F49: =SUMIFS('Policy Calculations'!$AH$30:$AH$279,'Policy Calculations'!$G$30:$G$279,$A49,'Policy Calculations'!$T$30:$T$279,1) -> 339300.02 | G49: =SUMIFS('Policy Calculations'!$AI$30:$AI$279,'Policy Calculations'!$G$30:$G$279,$A49,'Policy Calculations'!$T$30:$T$279,1) -> 2844.8734 | H49: =IF(F49=0,"",G49/F49) -> 0.0083845365 | I49: =COUNTIFS('Policy Calculations'!$G$30:$G$279,$A49,'Policy Calculations'!$AR$30:$AR$279,"Loss-making") -> 9 | J49: =IF(B49=0,"",I49/B49) -> 0.47368421 | K49: =IF('Portfolio Totals'!$B$13=0,"",G49/'Portfolio Totals'!$B$13) -> 0.011101198 | L49: =IF(B49=0,"No policies",IF(G49<0,"Loss-making segment",IF(H49<Assumptions!$C$16-0.00001,"Below target","At or above target"))) -> Below target
A50: Total | B50: =SUM(B47:B49) -> 169 | C50: =SUM(C47:C49) -> 429880.9 | D50: =SUM(D47:D49) -> 432358.1 | E50: =IF(D50=0,"",C50/D50) -> 0.9942705 | F50: =SUM(F47:F49) -> 3203820.8 | G50: =SUM(G47:G49) -> 256267.25 | H50: =IF(F50=0,"",G50/F50) -> 0.07998801 | I50: =SUM(I47:I49) -> 65 | J50: =IF(B50=0,"",I50/B50) -> 0.38461538 | K50: =G50-'Portfolio Totals'!$B$13 -> 0
A52: By sum-assured band (aed)
A53: Sum-assured band (AED) | B53: Policies | C53: Charged prem. | D53: Technical prem. | E53: Adequacy | F53: PV premiums | G53: PVFP | H53: NBM | I53: Loss-making | J53: % loss-making | K53: Share of PVFP | L53: Assessment
A54: Up to 250k | B54: =COUNTIFS('Policy Calculations'!$AQ$30:$AQ$279,$A54,'Policy Calculations'!$T$30:$T$279,1) -> 54 | C54: =SUMIFS('Policy Calculations'!$M$30:$M$279,'Policy Calculations'!$AQ$30:$AQ$279,$A54,'Policy Calculations'!$T$30:$T$279,1) -> 76839.99 | D54: =SUMIFS('Policy Calculations'!$AF$30:$AF$279,'Policy Calculations'!$AQ$30:$AQ$279,$A54,'Policy Calculations'!$T$30:$T$279,1) -> 82962.69 | E54: =IF(D54=0,"",C54/D54) -> 0.92619936 | F54: =SUMIFS('Policy Calculations'!$AH$30:$AH$279,'Policy Calculations'!$AQ$30:$AQ$279,$A54,'Policy Calculations'!$T$30:$T$279,1) -> 598613.07 | G54: =SUMIFS('Policy Calculations'!$AI$30:$AI$279,'Policy Calculations'!$AQ$30:$AQ$279,$A54,'Policy Calculations'!$T$30:$T$279,1) -> 14963.024 | H54: =IF(F54=0,"",G54/F54) -> 0.024996153 | I54: =COUNTIFS('Policy Calculations'!$AQ$30:$AQ$279,$A54,'Policy Calculations'!$AR$30:$AR$279,"Loss-making") -> 22 | J54: =IF(B54=0,"",I54/B54) -> 0.40740741 | K54: =IF('Portfolio Totals'!$B$13=0,"",G54/'Portfolio Totals'!$B$13) -> 0.058388359 | L54: =IF(B54=0,"No policies",IF(G54<0,"Loss-making segment",IF(H54<Assumptions!$C$16-0.00001,"Below target","At or above target"))) -> Below target
A55: 250k-500k | B55: =COUNTIFS('Policy Calculations'!$AQ$30:$AQ$279,$A55,'Policy Calculations'!$T$30:$T$279,1) -> 61 | C55: =SUMIFS('Policy Calculations'!$M$30:$M$279,'Policy Calculations'!$AQ$30:$AQ$279,$A55,'Policy Calculations'!$T$30:$T$279,1) -> 121647.57 | D55: =SUMIFS('Policy Calculations'!$AF$30:$AF$279,'Policy Calculations'!$AQ$30:$AQ$279,$A55,'Policy Calculations'!$T$30:$T$279,1) -> 148969.24 | E55: =IF(D55=0,"",C55/D55) -> 0.81659522 | F55: =SUMIFS('Policy Calculations'!$AH$30:$AH$279,'Policy Calculations'!$AQ$30:$AQ$279,$A55,'Policy Calculations'!$T$30:$T$279,1) -> 886955 | G55: =SUMIFS('Policy Calculations'!$AI$30:$AI$279,'Policy Calculations'!$AQ$30:$AQ$279,$A55,'Policy Calculations'!$T$30:$T$279,1) -> -87413.185 | H55: =IF(F55=0,"",G55/F55) -> -0.09855425 | I55: =COUNTIFS('Policy Calculations'!$AQ$30:$AQ$279,$A55,'Policy Calculations'!$AR$30:$AR$279,"Loss-making") -> 35 | J55: =IF(B55=0,"",I55/B55) -> 0.57377049 | K55: =IF('Portfolio Totals'!$B$13=0,"",G55/'Portfolio Totals'!$B$13) -> -0.34110167 | L55: =IF(B55=0,"No policies",IF(G55<0,"Loss-making segment",IF(H55<Assumptions!$C$16-0.00001,"Below target","At or above target"))) -> Loss-making segment
A56: 500k-1m | B56: =COUNTIFS('Policy Calculations'!$AQ$30:$AQ$279,$A56,'Policy Calculations'!$T$30:$T$279,1) -> 38 | C56: =SUMIFS('Policy Calculations'!$M$30:$M$279,'Policy Calculations'!$AQ$30:$AQ$279,$A56,'Policy Calculations'!$T$30:$T$279,1) -> 151723.21 | D56: =SUMIFS('Policy Calculations'!$AF$30:$AF$279,'Policy Calculations'!$AQ$30:$AQ$279,$A56,'Policy Calculations'!$T$30:$T$279,1) -> 138990.58 | E56: =IF(D56=0,"",C56/D56) -> 1.0916078 | F56: =SUMIFS('Policy Calculations'!$AH$30:$AH$279,'Policy Calculations'!$AQ$30:$AQ$279,$A56,'Policy Calculations'!$T$30:$T$279,1) -> 1135047.4 | G56: =SUMIFS('Policy Calculations'!$AI$30:$AI$279,'Policy Calculations'!$AQ$30:$AQ$279,$A56,'Policy Calculations'!$T$30:$T$279,1) -> 173775.52 | H56: =IF(F56=0,"",G56/F56) -> 0.15309978 | I56: =COUNTIFS('Policy Calculations'!$AQ$30:$AQ$279,$A56,'Policy Calculations'!$AR$30:$AR$279,"Loss-making") -> 5 | J56: =IF(B56=0,"",I56/B56) -> 0.13157895 | K56: =IF('Portfolio Totals'!$B$13=0,"",G56/'Portfolio Totals'!$B$13) -> 0.67810271 | L56: =IF(B56=0,"No policies",IF(G56<0,"Loss-making segment",IF(H56<Assumptions!$C$16-0.00001,"Below target","At or above target"))) -> At or above target
A57: Over 1m | B57: =COUNTIFS('Policy Calculations'!$AQ$30:$AQ$279,$A57,'Policy Calculations'!$T$30:$T$279,1) -> 16 | C57: =SUMIFS('Policy Calculations'!$M$30:$M$279,'Policy Calculations'!$AQ$30:$AQ$279,$A57,'Policy Calculations'!$T$30:$T$279,1) -> 79670.13 | D57: =SUMIFS('Policy Calculations'!$AF$30:$AF$279,'Policy Calculations'!$AQ$30:$AQ$279,$A57,'Policy Calculations'!$T$30:$T$279,1) -> 61435.582 | E57: =IF(D57=0,"",C57/D57) -> 1.2968076 | F57: =SUMIFS('Policy Calculations'!$AH$30:$AH$279,'Policy Calculations'!$AQ$30:$AQ$279,$A57,'Policy Calculations'!$T$30:$T$279,1) -> 583205.27 | G57: =SUMIFS('Policy Calculations'!$AI$30:$AI$279,'Policy Calculations'!$AQ$30:$AQ$279,$A57,'Policy Calculations'!$T$30:$T$279,1) -> 154941.89 | H57: =IF(F57=0,"",G57/F57) -> 0.265673 | I57: =COUNTIFS('Policy Calculations'!$AQ$30:$AQ$279,$A57,'Policy Calculations'!$AR$30:$AR$279,"Loss-making") -> 3 | J57: =IF(B57=0,"",I57/B57) -> 0.1875 | K57: =IF('Portfolio Totals'!$B$13=0,"",G57/'Portfolio Totals'!$B$13) -> 0.6046106 | L57: =IF(B57=0,"No policies",IF(G57<0,"Loss-making segment",IF(H57<Assumptions!$C$16-0.00001,"Below target","At or above target"))) -> At or above target
A58: Total | B58: =SUM(B54:B57) -> 169 | C58: =SUM(C54:C57) -> 429880.9 | D58: =SUM(D54:D57) -> 432358.1 | E58: =IF(D58=0,"",C58/D58) -> 0.9942705 | F58: =SUM(F54:F57) -> 3203820.8 | G58: =SUM(G54:G57) -> 256267.25 | H58: =IF(F58=0,"",G58/F58) -> 0.07998801 | I58: =SUM(I54:I57) -> 65 | J58: =IF(B58=0,"",I58/B58) -> 0.38461538 | K58: =G58-'Portfolio Totals'!$B$13 -> 0
A60: By premium frequency
A61: Premium frequency | B61: Policies | C61: Charged prem. | D61: Technical prem. | E61: Adequacy | F61: PV premiums | G61: PVFP | H61: NBM | I61: Loss-making | J61: % loss-making | K61: Share of PVFP | L61: Assessment
A62: Annual | B62: =COUNTIFS('Policy Calculations'!$J$30:$J$279,$A62,'Policy Calculations'!$T$30:$T$279,1) -> 76 | C62: =SUMIFS('Policy Calculations'!$M$30:$M$279,'Policy Calculations'!$J$30:$J$279,$A62,'Policy Calculations'!$T$30:$T$279,1) -> 189700.67 | D62: =SUMIFS('Policy Calculations'!$AF$30:$AF$279,'Policy Calculations'!$J$30:$J$279,$A62,'Policy Calculations'!$T$30:$T$279,1) -> 185248.76 | E62: =IF(D62=0,"",C62/D62) -> 1.0240321 | F62: =SUMIFS('Policy Calculations'!$AH$30:$AH$279,'Policy Calculations'!$J$30:$J$279,$A62,'Policy Calculations'!$T$30:$T$279,1) -> 1489916.4 | G62: =SUMIFS('Policy Calculations'!$AI$30:$AI$279,'Policy Calculations'!$J$30:$J$279,$A62,'Policy Calculations'!$T$30:$T$279,1) -> 144230.28 | H62: =IF(F62=0,"",G62/F62) -> 0.096804275 | I62: =COUNTIFS('Policy Calculations'!$J$30:$J$279,$A62,'Policy Calculations'!$AR$30:$AR$279,"Loss-making") -> 27 | J62: =IF(B62=0,"",I62/B62) -> 0.35526316 | K62: =IF('Portfolio Totals'!$B$13=0,"",G62/'Portfolio Totals'!$B$13) -> 0.56281198 | L62: =IF(B62=0,"No policies",IF(G62<0,"Loss-making segment",IF(H62<Assumptions!$C$16-0.00001,"Below target","At or above target"))) -> At or above target
A63: Monthly | B63: =COUNTIFS('Policy Calculations'!$J$30:$J$279,$A63,'Policy Calculations'!$T$30:$T$279,1) -> 93 | C63: =SUMIFS('Policy Calculations'!$M$30:$M$279,'Policy Calculations'!$J$30:$J$279,$A63,'Policy Calculations'!$T$30:$T$279,1) -> 240180.23 | D63: =SUMIFS('Policy Calculations'!$AF$30:$AF$279,'Policy Calculations'!$J$30:$J$279,$A63,'Policy Calculations'!$T$30:$T$279,1) -> 247109.34 | E63: =IF(D63=0,"",C63/D63) -> 0.97195934 | F63: =SUMIFS('Policy Calculations'!$AH$30:$AH$279,'Policy Calculations'!$J$30:$J$279,$A63,'Policy Calculations'!$T$30:$T$279,1) -> 1713904.4 | G63: =SUMIFS('Policy Calculations'!$AI$30:$AI$279,'Policy Calculations'!$J$30:$J$279,$A63,'Policy Calculations'!$T$30:$T$279,1) -> 112036.97 | H63: =IF(F63=0,"",G63/F63) -> 0.065369441 | I63: =COUNTIFS('Policy Calculations'!$J$30:$J$279,$A63,'Policy Calculations'!$AR$30:$AR$279,"Loss-making") -> 38 | J63: =IF(B63=0,"",I63/B63) -> 0.40860215 | K63: =IF('Portfolio Totals'!$B$13=0,"",G63/'Portfolio Totals'!$B$13) -> 0.43718802 | L63: =IF(B63=0,"No policies",IF(G63<0,"Loss-making segment",IF(H63<Assumptions!$C$16-0.00001,"Below target","At or above target"))) -> Below target
A64: Total | B64: =SUM(B62:B63) -> 169 | C64: =SUM(C62:C63) -> 429880.9 | D64: =SUM(D62:D63) -> 432358.1 | E64: =IF(D64=0,"",C64/D64) -> 0.9942705 | F64: =SUM(F62:F63) -> 3203820.8 | G64: =SUM(G62:G63) -> 256267.25 | H64: =IF(F64=0,"",G64/F64) -> 0.07998801 | I64: =SUM(I62:I63) -> 65 | J64: =IF(B64=0,"",I64/B64) -> 0.38461538 | K64: =G64-'Portfolio Totals'!$B$13 -> 0
A66: By policy term (years)
A67: Policy term (years) | B67: Policies | C67: Charged prem. | D67: Technical prem. | E67: Adequacy | F67: PV premiums | G67: PVFP | H67: NBM | I67: Loss-making | J67: % loss-making | K67: Share of PVFP | L67: Assessment
A68: 10 | B68: =COUNTIFS('Policy Calculations'!$H$30:$H$279,$A68,'Policy Calculations'!$T$30:$T$279,1) -> 28 | C68: =SUMIFS('Policy Calculations'!$M$30:$M$279,'Policy Calculations'!$H$30:$H$279,$A68,'Policy Calculations'!$T$30:$T$279,1) -> 87192.83 | D68: =SUMIFS('Policy Calculations'!$AF$30:$AF$279,'Policy Calculations'!$H$30:$H$279,$A68,'Policy Calculations'!$T$30:$T$279,1) -> 78382.411 | E68: =IF(D68=0,"",C68/D68) -> 1.112403 | F68: =SUMIFS('Policy Calculations'!$AH$30:$AH$279,'Policy Calculations'!$H$30:$H$279,$A68,'Policy Calculations'!$T$30:$T$279,1) -> 501431.47 | G68: =SUMIFS('Policy Calculations'!$AI$30:$AI$279,'Policy Calculations'!$H$30:$H$279,$A68,'Policy Calculations'!$T$30:$T$279,1) -> 92189.029 | H68: =IF(F68=0,"",G68/F68) -> 0.1838517 | I68: =COUNTIFS('Policy Calculations'!$H$30:$H$279,$A68,'Policy Calculations'!$AR$30:$AR$279,"Loss-making") -> 9 | J68: =IF(B68=0,"",I68/B68) -> 0.32142857 | K68: =IF('Portfolio Totals'!$B$13=0,"",G68/'Portfolio Totals'!$B$13) -> 0.35973785 | L68: =IF(B68=0,"No policies",IF(G68<0,"Loss-making segment",IF(H68<Assumptions!$C$16-0.00001,"Below target","At or above target"))) -> At or above target
A69: 15 | B69: =COUNTIFS('Policy Calculations'!$H$30:$H$279,$A69,'Policy Calculations'!$T$30:$T$279,1) -> 63 | C69: =SUMIFS('Policy Calculations'!$M$30:$M$279,'Policy Calculations'!$H$30:$H$279,$A69,'Policy Calculations'!$T$30:$T$279,1) -> 176877.18 | D69: =SUMIFS('Policy Calculations'!$AF$30:$AF$279,'Policy Calculations'!$H$30:$H$279,$A69,'Policy Calculations'!$T$30:$T$279,1) -> 172543.97 | E69: =IF(D69=0,"",C69/D69) -> 1.0251136 | F69: =SUMIFS('Policy Calculations'!$AH$30:$AH$279,'Policy Calculations'!$H$30:$H$279,$A69,'Policy Calculations'!$T$30:$T$279,1) -> 1279523.6 | G69: =SUMIFS('Policy Calculations'!$AI$30:$AI$279,'Policy Calculations'!$H$30:$H$279,$A69,'Policy Calculations'!$T$30:$T$279,1) -> 148509.86 | H69: =IF(F69=0,"",G69/F69) -> 0.11606653 | I69: =COUNTIFS('Policy Calculations'!$H$30:$H$279,$A69,'Policy Calculations'!$AR$30:$AR$279,"Loss-making") -> 24 | J69: =IF(B69=0,"",I69/B69) -> 0.38095238 | K69: =IF('Portfolio Totals'!$B$13=0,"",G69/'Portfolio Totals'!$B$13) -> 0.57951167 | L69: =IF(B69=0,"No policies",IF(G69<0,"Loss-making segment",IF(H69<Assumptions!$C$16-0.00001,"Below target","At or above target"))) -> At or above target
A70: 20 | B70: =COUNTIFS('Policy Calculations'!$H$30:$H$279,$A70,'Policy Calculations'!$T$30:$T$279,1) -> 56 | C70: =SUMIFS('Policy Calculations'!$M$30:$M$279,'Policy Calculations'!$H$30:$H$279,$A70,'Policy Calculations'!$T$30:$T$279,1) -> 134296.96 | D70: =SUMIFS('Policy Calculations'!$AF$30:$AF$279,'Policy Calculations'!$H$30:$H$279,$A70,'Policy Calculations'!$T$30:$T$279,1) -> 143950.65 | E70: =IF(D70=0,"",C70/D70) -> 0.93293747 | F70: =SUMIFS('Policy Calculations'!$AH$30:$AH$279,'Policy Calculations'!$H$30:$H$279,$A70,'Policy Calculations'!$T$30:$T$279,1) -> 1127538.7 | G70: =SUMIFS('Policy Calculations'!$AI$30:$AI$279,'Policy Calculations'!$H$30:$H$279,$A70,'Policy Calculations'!$T$30:$T$279,1) -> 33689.177 | H70: =IF(F70=0,"",G70/F70) -> 0.029878512 | I70: =COUNTIFS('Policy Calculations'!$H$30:$H$279,$A70,'Policy Calculations'!$AR$30:$AR$279,"Loss-making") -> 18 | J70: =IF(B70=0,"",I70/B70) -> 0.32142857 | K70: =IF('Portfolio Totals'!$B$13=0,"",G70/'Portfolio Totals'!$B$13) -> 0.13146111 | L70: =IF(B70=0,"No policies",IF(G70<0,"Loss-making segment",IF(H70<Assumptions!$C$16-0.00001,"Below target","At or above target"))) -> Below target
A71: 25 | B71: =COUNTIFS('Policy Calculations'!$H$30:$H$279,$A71,'Policy Calculations'!$T$30:$T$279,1) -> 22 | C71: =SUMIFS('Policy Calculations'!$M$30:$M$279,'Policy Calculations'!$H$30:$H$279,$A71,'Policy Calculations'!$T$30:$T$279,1) -> 31513.93 | D71: =SUMIFS('Policy Calculations'!$AF$30:$AF$279,'Policy Calculations'!$H$30:$H$279,$A71,'Policy Calculations'!$T$30:$T$279,1) -> 37481.06 | E71: =IF(D71=0,"",C71/D71) -> 0.84079613 | F71: =SUMIFS('Policy Calculations'!$AH$30:$AH$279,'Policy Calculations'!$H$30:$H$279,$A71,'Policy Calculations'!$T$30:$T$279,1) -> 295327.01 | G71: =SUMIFS('Policy Calculations'!$AI$30:$AI$279,'Policy Calculations'!$H$30:$H$279,$A71,'Policy Calculations'!$T$30:$T$279,1) -> -18120.819 | H71: =IF(F71=0,"",G71/F71) -> -0.061358489 | I71: =COUNTIFS('Policy Calculations'!$H$30:$H$279,$A71,'Policy Calculations'!$AR$30:$AR$279,"Loss-making") -> 14 | J71: =IF(B71=0,"",I71/B71) -> 0.63636364 | K71: =IF('Portfolio Totals'!$B$13=0,"",G71/'Portfolio Totals'!$B$13) -> -0.070710633 | L71: =IF(B71=0,"No policies",IF(G71<0,"Loss-making segment",IF(H71<Assumptions!$C$16-0.00001,"Below target","At or above target"))) -> Loss-making segment
A72: Total | B72: =SUM(B68:B71) -> 169 | C72: =SUM(C68:C71) -> 429880.9 | D72: =SUM(D68:D71) -> 432358.1 | E72: =IF(D72=0,"",C72/D72) -> 0.9942705 | F72: =SUM(F68:F71) -> 3203820.8 | G72: =SUM(G68:G71) -> 256267.25 | H72: =IF(F72=0,"",G72/F72) -> 0.07998801 | I72: =SUM(I68:I71) -> 65 | J72: =IF(B72=0,"",I72/B72) -> 0.38461538 | K72: =G72-'Portfolio Totals'!$B$13 -> 0
A78: Policies requiring further review
A79: Rank · Policy ID | B79: Entry age | C79: Profile (sex · smoker · UW class) | E79: Term | F79: Sum assured | G79: Channel | H79: Frequency | I79: Charged prem. | J79: Technical prem. | K79: Adequacy | L79: PVFP | M79: NBM
A80: =IFERROR("1. "&INDEX('Policy Calculations'!$A$30:$A$279,MATCH(SMALL('Policy Calculations'!$AS$30:$AS$279,1),'Policy Calculations'!$AS$30:$AS$279,0)),"") -> 1. POL100246 | B80: =IFERROR(INDEX('Policy Calculations'!$D$30:$D$279,MATCH(SMALL('Policy Calculations'!$AS$30:$AS$279,1),'Policy Calculations'!$AS$30:$AS$279,0)),"") -> 59 | C80: =IFERROR(INDEX('Policy Calculations'!$E$30:$E$279,MATCH(SMALL('Policy Calculations'!$AS$30:$AS$279,1),'Policy Calculations'!$AS$30:$AS$279,0))&" · "&INDEX('Policy Calculations'!$F$30:$F$279,MATCH(SMALL('Policy Calculations'!$AS$30:$AS$279,1),'Policy Calculations'!$AS$30:$AS$279,0))&" · "&INDEX('Policy Calculations'!$G$30:$G$279,MATCH(SMALL('Policy Calculations'!$AS$30:$AS$279,1),'Policy Calculations'!$AS$30:$AS$279,0)),"") -> Male · Non-smoker · Standard | E80: =IFERROR(INDEX('Policy Calculations'!$H$30:$H$279,MATCH(SMALL('Policy Calculations'!$AS$30:$AS$279,1),'Policy Calculations'!$AS$30:$AS$279,0)),"") -> 20 | F80: =IFERROR(INDEX('Policy Calculations'!$I$30:$I$279,MATCH(SMALL('Policy Calculations'!$AS$30:$AS$279,1),'Policy Calculations'!$AS$30:$AS$279,0)),"") -> 500000 | G80: =IFERROR(INDEX('Policy Calculations'!$K$30:$K$279,MATCH(SMALL('Policy Calculations'!$AS$30:$AS$279,1),'Policy Calculations'!$AS$30:$AS$279,0)),"") -> Bancassurance | H80: =IFERROR(INDEX('Policy Calculations'!$J$30:$J$279,MATCH(SMALL('Policy Calculations'!$AS$30:$AS$279,1),'Policy Calculations'!$AS$30:$AS$279,0)),"") -> Monthly | I80: =IFERROR(INDEX('Policy Calculations'!$M$30:$M$279,MATCH(SMALL('Policy Calculations'!$AS$30:$AS$279,1),'Policy Calculations'!$AS$30:$AS$279,0)),"") -> 3861.89 | J80: =IFERROR(INDEX('Policy Calculations'!$AF$30:$AF$279,MATCH(SMALL('Policy Calculations'!$AS$30:$AS$279,1),'Policy Calculations'!$AS$30:$AS$279,0)),"") -> 6488.4779 | K80: =IFERROR(INDEX('Policy Calculations'!$AK$30:$AK$279,MATCH(SMALL('Policy Calculations'!$AS$30:$AS$279,1),'Policy Calculations'!$AS$30:$AS$279,0)),"") -> 0.59519198 | L80: =IFERROR(INDEX('Policy Calculations'!$AI$30:$AI$279,MATCH(SMALL('Policy Calculations'!$AS$30:$AS$279,1),'Policy Calculations'!$AS$30:$AS$279,0)),"") -> -14415.996 | M80: =IFERROR(INDEX('Policy Calculations'!$AJ$30:$AJ$279,MATCH(SMALL('Policy Calculations'!$AS$30:$AS$279,1),'Policy Calculations'!$AS$30:$AS$279,0)),"") -> -0.45791743
A81: =IFERROR("2. "&INDEX('Policy Calculations'!$A$30:$A$279,MATCH(SMALL('Policy Calculations'!$AS$30:$AS$279,2),'Policy Calculations'!$AS$30:$AS$279,0)),"") -> 2. POL100189 | B81: =IFERROR(INDEX('Policy Calculations'!$D$30:$D$279,MATCH(SMALL('Policy Calculations'!$AS$30:$AS$279,2),'Policy Calculations'!$AS$30:$AS$279,0)),"") -> 58 | C81: =IFERROR(INDEX('Policy Calculations'!$E$30:$E$279,MATCH(SMALL('Policy Calculations'!$AS$30:$AS$279,2),'Policy Calculations'!$AS$30:$AS$279,0))&" · "&INDEX('Policy Calculations'!$F$30:$F$279,MATCH(SMALL('Policy Calculations'!$AS$30:$AS$279,2),'Policy Calculations'!$AS$30:$AS$279,0))&" · "&INDEX('Policy Calculations'!$G$30:$G$279,MATCH(SMALL('Policy Calculations'!$AS$30:$AS$279,2),'Policy Calculations'!$AS$30:$AS$279,0)),"") -> Male · Non-smoker · Standard | E81: =IFERROR(INDEX('Policy Calculations'!$H$30:$H$279,MATCH(SMALL('Policy Calculations'!$AS$30:$AS$279,2),'Policy Calculations'!$AS$30:$AS$279,0)),"") -> 20 | F81: =IFERROR(INDEX('Policy Calculations'!$I$30:$I$279,MATCH(SMALL('Policy Calculations'!$AS$30:$AS$279,2),'Policy Calculations'!$AS$30:$AS$279,0)),"") -> 500000 | G81: =IFERROR(INDEX('Policy Calculations'!$K$30:$K$279,MATCH(SMALL('Policy Calculations'!$AS$30:$AS$279,2),'Policy Calculations'!$AS$30:$AS$279,0)),"") -> Bancassurance | H81: =IFERROR(INDEX('Policy Calculations'!$J$30:$J$279,MATCH(SMALL('Policy Calculations'!$AS$30:$AS$279,2),'Policy Calculations'!$AS$30:$AS$279,0)),"") -> Monthly | I81: =IFERROR(INDEX('Policy Calculations'!$M$30:$M$279,MATCH(SMALL('Policy Calculations'!$AS$30:$AS$279,2),'Policy Calculations'!$AS$30:$AS$279,0)),"") -> 3623.02 | J81: =IFERROR(INDEX('Policy Calculations'!$AF$30:$AF$279,MATCH(SMALL('Policy Calculations'!$AS$30:$AS$279,2),'Policy Calculations'!$AS$30:$AS$279,0)),"") -> 6038.6316 | K81: =IFERROR(INDEX('Policy Calculations'!$AK$30:$AK$279,MATCH(SMALL('Policy Calculations'!$AS$30:$AS$279,2),'Policy Calculations'!$AS$30:$AS$279,0)),"") -> 0.59997367 | L81: =IFERROR(INDEX('Policy Calculations'!$AI$30:$AI$279,MATCH(SMALL('Policy Calculations'!$AS$30:$AS$279,2),'Policy Calculations'!$AS$30:$AS$279,0)),"") -> -13256.261 | M81: =IFERROR(INDEX('Policy Calculations'!$AJ$30:$AJ$279,MATCH(SMALL('Policy Calculations'!$AS$30:$AS$279,2),'Policy Calculations'!$AS$30:$AS$279,0)),"") -> -0.44688612
A82: =IFERROR("3. "&INDEX('Policy Calculations'!$A$30:$A$279,MATCH(SMALL('Policy Calculations'!$AS$30:$AS$279,3),'Policy Calculations'!$AS$30:$AS$279,0)),"") -> 3. POL100066 | B82: =IFERROR(INDEX('Policy Calculations'!$D$30:$D$279,MATCH(SMALL('Policy Calculations'!$AS$30:$AS$279,3),'Policy Calculations'!$AS$30:$AS$279,0)),"") -> 54 | C82: =IFERROR(INDEX('Policy Calculations'!$E$30:$E$279,MATCH(SMALL('Policy Calculations'!$AS$30:$AS$279,3),'Policy Calculations'!$AS$30:$AS$279,0))&" · "&INDEX('Policy Calculations'!$F$30:$F$279,MATCH(SMALL('Policy Calculations'!$AS$30:$AS$279,3),'Policy Calculations'!$AS$30:$AS$279,0))&" · "&INDEX('Policy Calculations'!$G$30:$G$279,MATCH(SMALL('Policy Calculations'!$AS$30:$AS$279,3),'Policy Calculations'!$AS$30:$AS$279,0)),"") -> Female · Smoker · Standard | E82: =IFERROR(INDEX('Policy Calculations'!$H$30:$H$279,MATCH(SMALL('Policy Calculations'!$AS$30:$AS$279,3),'Policy Calculations'!$AS$30:$AS$279,0)),"") -> 20 | F82: =IFERROR(INDEX('Policy Calculations'!$I$30:$I$279,MATCH(SMALL('Policy Calculations'!$AS$30:$AS$279,3),'Policy Calculations'!$AS$30:$AS$279,0)),"") -> 500000 | G82: =IFERROR(INDEX('Policy Calculations'!$K$30:$K$279,MATCH(SMALL('Policy Calculations'!$AS$30:$AS$279,3),'Policy Calculations'!$AS$30:$AS$279,0)),"") -> Direct | H82: =IFERROR(INDEX('Policy Calculations'!$J$30:$J$279,MATCH(SMALL('Policy Calculations'!$AS$30:$AS$279,3),'Policy Calculations'!$AS$30:$AS$279,0)),"") -> Annual | I82: =IFERROR(INDEX('Policy Calculations'!$M$30:$M$279,MATCH(SMALL('Policy Calculations'!$AS$30:$AS$279,3),'Policy Calculations'!$AS$30:$AS$279,0)),"") -> 3294.88 | J82: =IFERROR(INDEX('Policy Calculations'!$AF$30:$AF$279,MATCH(SMALL('Policy Calculations'!$AS$30:$AS$279,3),'Policy Calculations'!$AS$30:$AS$279,0)),"") -> 5188.2634 | K82: =IFERROR(INDEX('Policy Calculations'!$AK$30:$AK$279,MATCH(SMALL('Policy Calculations'!$AS$30:$AS$279,3),'Policy Calculations'!$AS$30:$AS$279,0)),"") -> 0.63506413 | L82: =IFERROR(INDEX('Policy Calculations'!$AI$30:$AI$279,MATCH(SMALL('Policy Calculations'!$AS$30:$AS$279,3),'Policy Calculations'!$AS$30:$AS$279,0)),"") -> -11305.722 | M82: =IFERROR(INDEX('Policy Calculations'!$AJ$30:$AJ$279,MATCH(SMALL('Policy Calculations'!$AS$30:$AS$279,3),'Policy Calculations'!$AS$30:$AS$279,0)),"") -> -0.41657017
A83: =IFERROR("4. "&INDEX('Policy Calculations'!$A$30:$A$279,MATCH(SMALL('Policy Calculations'!$AS$30:$AS$279,4),'Policy Calculations'!$AS$30:$AS$279,0)),"") -> 4. POL100148 | B83: =IFERROR(INDEX('Policy Calculations'!$D$30:$D$279,MATCH(SMALL('Policy Calculations'!$AS$30:$AS$279,4),'Policy Calculations'!$AS$30:$AS$279,0)),"") -> 54 | C83: =IFERROR(INDEX('Policy Calculations'!$E$30:$E$279,MATCH(SMALL('Policy Calculations'!$AS$30:$AS$279,4),'Policy Calculations'!$AS$30:$AS$279,0))&" · "&INDEX('Policy Calculations'!$F$30:$F$279,MATCH(SMALL('Policy Calculations'!$AS$30:$AS$279,4),'Policy Calculations'!$AS$30:$AS$279,0))&" · "&INDEX('Policy Calculations'!$G$30:$G$279,MATCH(SMALL('Policy Calculations'!$AS$30:$AS$279,4),'Policy Calculations'!$AS$30:$AS$279,0)),"") -> Female · Smoker · Preferred | E83: =IFERROR(INDEX('Policy Calculations'!$H$30:$H$279,MATCH(SMALL('Policy Calculations'!$AS$30:$AS$279,4),'Policy Calculations'!$AS$30:$AS$279,0)),"") -> 20 | F83: =IFERROR(INDEX('Policy Calculations'!$I$30:$I$279,MATCH(SMALL('Policy Calculations'!$AS$30:$AS$279,4),'Policy Calculations'!$AS$30:$AS$279,0)),"") -> 500000 | G83: =IFERROR(INDEX('Policy Calculations'!$K$30:$K$279,MATCH(SMALL('Policy Calculations'!$AS$30:$AS$279,4),'Policy Calculations'!$AS$30:$AS$279,0)),"") -> Direct | H83: =IFERROR(INDEX('Policy Calculations'!$J$30:$J$279,MATCH(SMALL('Policy Calculations'!$AS$30:$AS$279,4),'Policy Calculations'!$AS$30:$AS$279,0)),"") -> Monthly | I83: =IFERROR(INDEX('Policy Calculations'!$M$30:$M$279,MATCH(SMALL('Policy Calculations'!$AS$30:$AS$279,4),'Policy Calculations'!$AS$30:$AS$279,0)),"") -> 2786.9 | J83: =IFERROR(INDEX('Policy Calculations'!$AF$30:$AF$279,MATCH(SMALL('Policy Calculations'!$AS$30:$AS$279,4),'Policy Calculations'!$AS$30:$AS$279,0)),"") -> 4388.593 | K83: =IFERROR(INDEX('Policy Calculations'!$AK$30:$AK$279,MATCH(SMALL('Policy Calculations'!$AS$30:$AS$279,4),'Policy Calculations'!$AS$30:$AS$279,0)),"") -> 0.63503268 | L83: =IFERROR(INDEX('Policy Calculations'!$AI$30:$AI$279,MATCH(SMALL('Policy Calculations'!$AS$30:$AS$279,4),'Policy Calculations'!$AS$30:$AS$279,0)),"") -> -8736.7735 | M83: =IFERROR(INDEX('Policy Calculations'!$AJ$30:$AJ$279,MATCH(SMALL('Policy Calculations'!$AS$30:$AS$279,4),'Policy Calculations'!$AS$30:$AS$279,0)),"") -> -0.37703241
A84: =IFERROR("5. "&INDEX('Policy Calculations'!$A$30:$A$279,MATCH(SMALL('Policy Calculations'!$AS$30:$AS$279,5),'Policy Calculations'!$AS$30:$AS$279,0)),"") -> 5. POL100194 | B84: =IFERROR(INDEX('Policy Calculations'!$D$30:$D$279,MATCH(SMALL('Policy Calculations'!$AS$30:$AS$279,5),'Policy Calculations'!$AS$30:$AS$279,0)),"") -> 53 | C84: =IFERROR(INDEX('Policy Calculations'!$E$30:$E$279,MATCH(SMALL('Policy Calculations'!$AS$30:$AS$279,5),'Policy Calculations'!$AS$30:$AS$279,0))&" · "&INDEX('Policy Calculations'!$F$30:$F$279,MATCH(SMALL('Policy Calculations'!$AS$30:$AS$279,5),'Policy Calculations'!$AS$30:$AS$279,0))&" · "&INDEX('Policy Calculations'!$G$30:$G$279,MATCH(SMALL('Policy Calculations'!$AS$30:$AS$279,5),'Policy Calculations'!$AS$30:$AS$279,0)),"") -> Male · Non-smoker · Standard | E84: =IFERROR(INDEX('Policy Calculations'!$H$30:$H$279,MATCH(SMALL('Policy Calculations'!$AS$30:$AS$279,5),'Policy Calculations'!$AS$30:$AS$279,0)),"") -> 20 | F84: =IFERROR(INDEX('Policy Calculations'!$I$30:$I$279,MATCH(SMALL('Policy Calculations'!$AS$30:$AS$279,5),'Policy Calculations'!$AS$30:$AS$279,0)),"") -> 500000 | G84: =IFERROR(INDEX('Policy Calculations'!$K$30:$K$279,MATCH(SMALL('Policy Calculations'!$AS$30:$AS$279,5),'Policy Calculations'!$AS$30:$AS$279,0)),"") -> Broker | H84: =IFERROR(INDEX('Policy Calculations'!$J$30:$J$279,MATCH(SMALL('Policy Calculations'!$AS$30:$AS$279,5),'Policy Calculations'!$AS$30:$AS$279,0)),"") -> Annual | I84: =IFERROR(INDEX('Policy Calculations'!$M$30:$M$279,MATCH(SMALL('Policy Calculations'!$AS$30:$AS$279,5),'Policy Calculations'!$AS$30:$AS$279,0)),"") -> 2677.49 | J84: =IFERROR(INDEX('Policy Calculations'!$AF$30:$AF$279,MATCH(SMALL('Policy Calculations'!$AS$30:$AS$279,5),'Policy Calculations'!$AS$30:$AS$279,0)),"") -> 4143.2212 | K84: =IFERROR(INDEX('Policy Calculations'!$AK$30:$AK$279,MATCH(SMALL('Policy Calculations'!$AS$30:$AS$279,5),'Policy Calculations'!$AS$30:$AS$279,0)),"") -> 0.6462339 | L84: =IFERROR(INDEX('Policy Calculations'!$AI$30:$AI$279,MATCH(SMALL('Policy Calculations'!$AS$30:$AS$279,5),'Policy Calculations'!$AS$30:$AS$279,0)),"") -> -8556.6107 | M84: =IFERROR(INDEX('Policy Calculations'!$AJ$30:$AJ$279,MATCH(SMALL('Policy Calculations'!$AS$30:$AS$279,5),'Policy Calculations'!$AS$30:$AS$279,0)),"") -> -0.38356535
A85: =IFERROR("6. "&INDEX('Policy Calculations'!$A$30:$A$279,MATCH(SMALL('Policy Calculations'!$AS$30:$AS$279,6),'Policy Calculations'!$AS$30:$AS$279,0)),"") -> 6. POL100120 | B85: =IFERROR(INDEX('Policy Calculations'!$D$30:$D$279,MATCH(SMALL('Policy Calculations'!$AS$30:$AS$279,6),'Policy Calculations'!$AS$30:$AS$279,0)),"") -> 49 | C85: =IFERROR(INDEX('Policy Calculations'!$E$30:$E$279,MATCH(SMALL('Policy Calculations'!$AS$30:$AS$279,6),'Policy Calculations'!$AS$30:$AS$279,0))&" · "&INDEX('Policy Calculations'!$F$30:$F$279,MATCH(SMALL('Policy Calculations'!$AS$30:$AS$279,6),'Policy Calculations'!$AS$30:$AS$279,0))&" · "&INDEX('Policy Calculations'!$G$30:$G$279,MATCH(SMALL('Policy Calculations'!$AS$30:$AS$279,6),'Policy Calculations'!$AS$30:$AS$279,0)),"") -> Male · Non-smoker · Rated | E85: =IFERROR(INDEX('Policy Calculations'!$H$30:$H$279,MATCH(SMALL('Policy Calculations'!$AS$30:$AS$279,6),'Policy Calculations'!$AS$30:$AS$279,0)),"") -> 25 | F85: =IFERROR(INDEX('Policy Calculations'!$I$30:$I$279,MATCH(SMALL('Policy Calculations'!$AS$30:$AS$279,6),'Policy Calculations'!$AS$30:$AS$279,0)),"") -> 250000 | G85: =IFERROR(INDEX('Policy Calculations'!$K$30:$K$279,MATCH(SMALL('Policy Calculations'!$AS$30:$AS$279,6),'Policy Calculations'!$AS$30:$AS$279,0)),"") -> Broker | H85: =IFERROR(INDEX('Policy Calculations'!$J$30:$J$279,MATCH(SMALL('Policy Calculations'!$AS$30:$AS$279,6),'Policy Calculations'!$AS$30:$AS$279,0)),"") -> Monthly | I85: =IFERROR(INDEX('Policy Calculations'!$M$30:$M$279,MATCH(SMALL('Policy Calculations'!$AS$30:$AS$279,6),'Policy Calculations'!$AS$30:$AS$279,0)),"") -> 1699.41 | J85: =IFERROR(INDEX('Policy Calculations'!$AF$30:$AF$279,MATCH(SMALL('Policy Calculations'!$AS$30:$AS$279,6),'Policy Calculations'!$AS$30:$AS$279,0)),"") -> 2966.6808 | K85: =IFERROR(INDEX('Policy Calculations'!$AK$30:$AK$279,MATCH(SMALL('Policy Calculations'!$AS$30:$AS$279,6),'Policy Calculations'!$AS$30:$AS$279,0)),"") -> 0.5728321 | L85: =IFERROR(INDEX('Policy Calculations'!$AI$30:$AI$279,MATCH(SMALL('Policy Calculations'!$AS$30:$AS$279,6),'Policy Calculations'!$AS$30:$AS$279,0)),"") -> -7821.7159 | M85: =IFERROR(INDEX('Policy Calculations'!$AJ$30:$AJ$279,MATCH(SMALL('Policy Calculations'!$AS$30:$AS$279,6),'Policy Calculations'!$AS$30:$AS$279,0)),"") -> -0.50966496
A86: =IFERROR("7. "&INDEX('Policy Calculations'!$A$30:$A$279,MATCH(SMALL('Policy Calculations'!$AS$30:$AS$279,7),'Policy Calculations'!$AS$30:$AS$279,0)),"") -> 7. POL100044 | B86: =IFERROR(INDEX('Policy Calculations'!$D$30:$D$279,MATCH(SMALL('Policy Calculations'!$AS$30:$AS$279,7),'Policy Calculations'!$AS$30:$AS$279,0)),"") -> 59 | C86: =IFERROR(INDEX('Policy Calculations'!$E$30:$E$279,MATCH(SMALL('Policy Calculations'!$AS$30:$AS$279,7),'Policy Calculations'!$AS$30:$AS$279,0))&" · "&INDEX('Policy Calculations'!$F$30:$F$279,MATCH(SMALL('Policy Calculations'!$AS$30:$AS$279,7),'Policy Calculations'!$AS$30:$AS$279,0))&" · "&INDEX('Policy Calculations'!$G$30:$G$279,MATCH(SMALL('Policy Calculations'!$AS$30:$AS$279,7),'Policy Calculations'!$AS$30:$AS$279,0)),"") -> Male · Non-smoker · Standard | E86: =IFERROR(INDEX('Policy Calculations'!$H$30:$H$279,MATCH(SMALL('Policy Calculations'!$AS$30:$AS$279,7),'Policy Calculations'!$AS$30:$AS$279,0)),"") -> 20 | F86: =IFERROR(INDEX('Policy Calculations'!$I$30:$I$279,MATCH(SMALL('Policy Calculations'!$AS$30:$AS$279,7),'Policy Calculations'!$AS$30:$AS$279,0)),"") -> 250000 | G86: =IFERROR(INDEX('Policy Calculations'!$K$30:$K$279,MATCH(SMALL('Policy Calculations'!$AS$30:$AS$279,7),'Policy Calculations'!$AS$30:$AS$279,0)),"") -> Broker | H86: =IFERROR(INDEX('Policy Calculations'!$J$30:$J$279,MATCH(SMALL('Policy Calculations'!$AS$30:$AS$279,7),'Policy Calculations'!$AS$30:$AS$279,0)),"") -> Annual | I86: =IFERROR(INDEX('Policy Calculations'!$M$30:$M$279,MATCH(SMALL('Policy Calculations'!$AS$30:$AS$279,7),'Policy Calculations'!$AS$30:$AS$279,0)),"") -> 2170.94 | J86: =IFERROR(INDEX('Policy Calculations'!$AF$30:$AF$279,MATCH(SMALL('Policy Calculations'!$AS$30:$AS$279,7),'Policy Calculations'!$AS$30:$AS$279,0)),"") -> 3407.5965 | K86: =IFERROR(INDEX('Policy Calculations'!$AK$30:$AK$279,MATCH(SMALL('Policy Calculations'!$AS$30:$AS$279,7),'Policy Calculations'!$AS$30:$AS$279,0)),"") -> 0.63708835 | L86: =IFERROR(INDEX('Policy Calculations'!$AI$30:$AI$279,MATCH(SMALL('Policy Calculations'!$AS$30:$AS$279,7),'Policy Calculations'!$AS$30:$AS$279,0)),"") -> -7115.7853 | M86: =IFERROR(INDEX('Policy Calculations'!$AJ$30:$AJ$279,MATCH(SMALL('Policy Calculations'!$AS$30:$AS$279,7),'Policy Calculations'!$AS$30:$AS$279,0)),"") -> -0.40208459
A87: =IFERROR("8. "&INDEX('Policy Calculations'!$A$30:$A$279,MATCH(SMALL('Policy Calculations'!$AS$30:$AS$279,8),'Policy Calculations'!$AS$30:$AS$279,0)),"") -> 8. POL100162 | B87: =IFERROR(INDEX('Policy Calculations'!$D$30:$D$279,MATCH(SMALL('Policy Calculations'!$AS$30:$AS$279,8),'Policy Calculations'!$AS$30:$AS$279,0)),"") -> 47 | C87: =IFERROR(INDEX('Policy Calculations'!$E$30:$E$279,MATCH(SMALL('Policy Calculations'!$AS$30:$AS$279,8),'Policy Calculations'!$AS$30:$AS$279,0))&" · "&INDEX('Policy Calculations'!$F$30:$F$279,MATCH(SMALL('Policy Calculations'!$AS$30:$AS$279,8),'Policy Calculations'!$AS$30:$AS$279,0))&" · "&INDEX('Policy Calculations'!$G$30:$G$279,MATCH(SMALL('Policy Calculations'!$AS$30:$AS$279,8),'Policy Calculations'!$AS$30:$AS$279,0)),"") -> Male · Smoker · Standard | E87: =IFERROR(INDEX('Policy Calculations'!$H$30:$H$279,MATCH(SMALL('Policy Calculations'!$AS$30:$AS$279,8),'Policy Calculations'!$AS$30:$AS$279,0)),"") -> 25 | F87: =IFERROR(INDEX('Policy Calculations'!$I$30:$I$279,MATCH(SMALL('Policy Calculations'!$AS$30:$AS$279,8),'Policy Calculations'!$AS$30:$AS$279,0)),"") -> 250000 | G87: =IFERROR(INDEX('Policy Calculations'!$K$30:$K$279,MATCH(SMALL('Policy Calculations'!$AS$30:$AS$279,8),'Policy Calculations'!$AS$30:$AS$279,0)),"") -> Bancassurance | H87: =IFERROR(INDEX('Policy Calculations'!$J$30:$J$279,MATCH(SMALL('Policy Calculations'!$AS$30:$AS$279,8),'Policy Calculations'!$AS$30:$AS$279,0)),"") -> Monthly | I87: =IFERROR(INDEX('Policy Calculations'!$M$30:$M$279,MATCH(SMALL('Policy Calculations'!$AS$30:$AS$279,8),'Policy Calculations'!$AS$30:$AS$279,0)),"") -> 1598.92 | J87: =IFERROR(INDEX('Policy Calculations'!$AF$30:$AF$279,MATCH(SMALL('Policy Calculations'!$AS$30:$AS$279,8),'Policy Calculations'!$AS$30:$AS$279,0)),"") -> 2728.0581 | K87: =IFERROR(INDEX('Policy Calculations'!$AK$30:$AK$279,MATCH(SMALL('Policy Calculations'!$AS$30:$AS$279,8),'Policy Calculations'!$AS$30:$AS$279,0)),"") -> 0.5861019 | L87: =IFERROR(INDEX('Policy Calculations'!$AI$30:$AI$279,MATCH(SMALL('Policy Calculations'!$AS$30:$AS$279,8),'Policy Calculations'!$AS$30:$AS$279,0)),"") -> -6975.6167 | M87: =IFERROR(INDEX('Policy Calculations'!$AJ$30:$AJ$279,MATCH(SMALL('Policy Calculations'!$AS$30:$AS$279,8),'Policy Calculations'!$AS$30:$AS$279,0)),"") -> -0.48066646
A88: =IFERROR("9. "&INDEX('Policy Calculations'!$A$30:$A$279,MATCH(SMALL('Policy Calculations'!$AS$30:$AS$279,9),'Policy Calculations'!$AS$30:$AS$279,0)),"") -> 9. POL100024 | B88: =IFERROR(INDEX('Policy Calculations'!$D$30:$D$279,MATCH(SMALL('Policy Calculations'!$AS$30:$AS$279,9),'Policy Calculations'!$AS$30:$AS$279,0)),"") -> 53 | C88: =IFERROR(INDEX('Policy Calculations'!$E$30:$E$279,MATCH(SMALL('Policy Calculations'!$AS$30:$AS$279,9),'Policy Calculations'!$AS$30:$AS$279,0))&" · "&INDEX('Policy Calculations'!$F$30:$F$279,MATCH(SMALL('Policy Calculations'!$AS$30:$AS$279,9),'Policy Calculations'!$AS$30:$AS$279,0))&" · "&INDEX('Policy Calculations'!$G$30:$G$279,MATCH(SMALL('Policy Calculations'!$AS$30:$AS$279,9),'Policy Calculations'!$AS$30:$AS$279,0)),"") -> Male · Non-smoker · Rated | E88: =IFERROR(INDEX('Policy Calculations'!$H$30:$H$279,MATCH(SMALL('Policy Calculations'!$AS$30:$AS$279,9),'Policy Calculations'!$AS$30:$AS$279,0)),"") -> 20 | F88: =IFERROR(INDEX('Policy Calculations'!$I$30:$I$279,MATCH(SMALL('Policy Calculations'!$AS$30:$AS$279,9),'Policy Calculations'!$AS$30:$AS$279,0)),"") -> 250000 | G88: =IFERROR(INDEX('Policy Calculations'!$K$30:$K$279,MATCH(SMALL('Policy Calculations'!$AS$30:$AS$279,9),'Policy Calculations'!$AS$30:$AS$279,0)),"") -> Broker | H88: =IFERROR(INDEX('Policy Calculations'!$J$30:$J$279,MATCH(SMALL('Policy Calculations'!$AS$30:$AS$279,9),'Policy Calculations'!$AS$30:$AS$279,0)),"") -> Annual | I88: =IFERROR(INDEX('Policy Calculations'!$M$30:$M$279,MATCH(SMALL('Policy Calculations'!$AS$30:$AS$279,9),'Policy Calculations'!$AS$30:$AS$279,0)),"") -> 2107.43 | J88: =IFERROR(INDEX('Policy Calculations'!$AF$30:$AF$279,MATCH(SMALL('Policy Calculations'!$AS$30:$AS$279,9),'Policy Calculations'!$AS$30:$AS$279,0)),"") -> 3290.6603 | K88: =IFERROR(INDEX('Policy Calculations'!$AK$30:$AK$279,MATCH(SMALL('Policy Calculations'!$AS$30:$AS$279,9),'Policy Calculations'!$AS$30:$AS$279,0)),"") -> 0.6404277 | L88: =IFERROR(INDEX('Policy Calculations'!$AI$30:$AI$279,MATCH(SMALL('Policy Calculations'!$AS$30:$AS$279,9),'Policy Calculations'!$AS$30:$AS$279,0)),"") -> -6804.9152 | M88: =IFERROR(INDEX('Policy Calculations'!$AJ$30:$AJ$279,MATCH(SMALL('Policy Calculations'!$AS$30:$AS$279,9),'Policy Calculations'!$AS$30:$AS$279,0)),"") -> -0.39518891
A89: =IFERROR("10. "&INDEX('Policy Calculations'!$A$30:$A$279,MATCH(SMALL('Policy Calculations'!$AS$30:$AS$279,10),'Policy Calculations'!$AS$30:$AS$279,0)),"") -> 10. POL100013 | B89: =IFERROR(INDEX('Policy Calculations'!$D$30:$D$279,MATCH(SMALL('Policy Calculations'!$AS$30:$AS$279,10),'Policy Calculations'!$AS$30:$AS$279,0)),"") -> 63 | C89: =IFERROR(INDEX('Policy Calculations'!$E$30:$E$279,MATCH(SMALL('Policy Calculations'!$AS$30:$AS$279,10),'Policy Calculations'!$AS$30:$AS$279,0))&" · "&INDEX('Policy Calculations'!$F$30:$F$279,MATCH(SMALL('Policy Calculations'!$AS$30:$AS$279,10),'Policy Calculations'!$AS$30:$AS$279,0))&" · "&INDEX('Policy Calculations'!$G$30:$G$279,MATCH(SMALL('Policy Calculations'!$AS$30:$AS$279,10),'Policy Calculations'!$AS$30:$AS$279,0)),"") -> Female · Non-smoker · Preferred | E89: =IFERROR(INDEX('Policy Calculations'!$H$30:$H$279,MATCH(SMALL('Policy Calculations'!$AS$30:$AS$279,10),'Policy Calculations'!$AS$30:$AS$279,0)),"") -> 15 | F89: =IFERROR(INDEX('Policy Calculations'!$I$30:$I$279,MATCH(SMALL('Policy Calculations'!$AS$30:$AS$279,10),'Policy Calculations'!$AS$30:$AS$279,0)),"") -> 500000 | G89: =IFERROR(INDEX('Policy Calculations'!$K$30:$K$279,MATCH(SMALL('Policy Calculations'!$AS$30:$AS$279,10),'Policy Calculations'!$AS$30:$AS$279,0)),"") -> Broker | H89: =IFERROR(INDEX('Policy Calculations'!$J$30:$J$279,MATCH(SMALL('Policy Calculations'!$AS$30:$AS$279,10),'Policy Calculations'!$AS$30:$AS$279,0)),"") -> Monthly | I89: =IFERROR(INDEX('Policy Calculations'!$M$30:$M$279,MATCH(SMALL('Policy Calculations'!$AS$30:$AS$279,10),'Policy Calculations'!$AS$30:$AS$279,0)),"") -> 3284.94 | J89: =IFERROR(INDEX('Policy Calculations'!$AF$30:$AF$279,MATCH(SMALL('Policy Calculations'!$AS$30:$AS$279,10),'Policy Calculations'!$AS$30:$AS$279,0)),"") -> 4711.8228 | K89: =IFERROR(INDEX('Policy Calculations'!$AK$30:$AK$279,MATCH(SMALL('Policy Calculations'!$AS$30:$AS$279,10),'Policy Calculations'!$AS$30:$AS$279,0)),"") -> 0.69716968 | L89: =IFERROR(INDEX('Policy Calculations'!$AI$30:$AI$279,MATCH(SMALL('Policy Calculations'!$AS$30:$AS$279,10),'Policy Calculations'!$AS$30:$AS$279,0)),"") -> -5944.1266 | M89: =IFERROR(INDEX('Policy Calculations'!$AJ$30:$AJ$279,MATCH(SMALL('Policy Calculations'!$AS$30:$AS$279,10),'Policy Calculations'!$AS$30:$AS$279,0)),"") -> -0.25103165

Sheet Experience Analysis
A1: Experience Analysis
A2: Experience analysis based on synthetic policy data generated for this project. Results are used to compare observed mortality and lapse experience with the illustrative pricing assumptions.
A4: Sex | B4: UW Class | C4: Exposure | D4: Actual deaths | E4: Expected deaths | F4: A/E | H4: Policy sample analysis | I4: Policies | J4: Exposure | K4: Actual deaths | L4: Expected deaths | M4: A/E
A5: Female | B5: Preferred | C5: 585.2337 | D5: 1 | E5: 0.829543 | F5: =D5/E5 -> 1.205483 | H5: Age <30 | I5: =COUNTIFS('Policy Data'!$C$4:$C$253,"<30") -> 48 | J5: =SUMIFS('Policy Data'!$L$4:$L$253,'Policy Data'!$C$4:$C$253,"<30") -> 37.3195 | K5: =SUMIFS('Policy Data'!$O$4:$O$253,'Policy Data'!$C$4:$C$253,"<30") -> 0 | L5: =SUMIFS('Policy Data'!$N$4:$N$253,'Policy Data'!$C$4:$C$253,"<30") -> 0.013764 | M5: =IF(L5=0,"n.a.",K5/L5) -> 0
A6: Female | B6: Rated | C6: 300.5844 | D6: 1 | E6: 0.911433 | F6: =D6/E6 -> 1.0971734 | H6: Age 30-39 | I6: =COUNTIFS('Policy Data'!$C$4:$C$253,">=30",'Policy Data'!$C$4:$C$253,"<40") -> 62 | J6: =SUMIFS('Policy Data'!$L$4:$L$253,'Policy Data'!$C$4:$C$253,">=30",'Policy Data'!$C$4:$C$253,"<40") -> 46.0285 | K6: =SUMIFS('Policy Data'!$O$4:$O$253,'Policy Data'!$C$4:$C$253,">=30",'Policy Data'!$C$4:$C$253,"<40") -> 0 | L6: =SUMIFS('Policy Data'!$N$4:$N$253,'Policy Data'!$C$4:$C$253,">=30",'Policy Data'!$C$4:$C$253,"<40") -> 0.037479 | M6: =IF(L6=0,"n.a.",K6/L6) -> 0
A7: Female | B7: Standard | C7: 2921.1237 | D7: 6 | E7: 5.625677 | F7: =D7/E7 -> 1.0665383 | H7: Age 40-49 | I7: =COUNTIFS('Policy Data'!$C$4:$C$253,">=40",'Policy Data'!$C$4:$C$253,"<50") -> 56 | J7: =SUMIFS('Policy Data'!$L$4:$L$253,'Policy Data'!$C$4:$C$253,">=40",'Policy Data'!$C$4:$C$253,"<50") -> 41.8975 | K7: =SUMIFS('Policy Data'!$O$4:$O$253,'Policy Data'!$C$4:$C$253,">=40",'Policy Data'!$C$4:$C$253,"<50") -> 0 | L7: =SUMIFS('Policy Data'!$N$4:$N$253,'Policy Data'!$C$4:$C$253,">=40",'Policy Data'!$C$4:$C$253,"<50") -> 0.073999 | M7: =IF(L7=0,"n.a.",K7/L7) -> 0
A8: Male | B8: Preferred | C8: 843.0149 | D8: 3 | E8: 1.762499 | F8: =D8/E8 -> 1.7021286 | H8: Age 50+ | I8: =COUNTIFS('Policy Data'!$C$4:$C$253,">=50") -> 84 | J8: =SUMIFS('Policy Data'!$L$4:$L$253,'Policy Data'!$C$4:$C$253,">=50") -> 63.6388 | K8: =SUMIFS('Policy Data'!$O$4:$O$253,'Policy Data'!$C$4:$C$253,">=50") -> 0 | L8: =SUMIFS('Policy Data'!$N$4:$N$253,'Policy Data'!$C$4:$C$253,">=50") -> 0.32257 | M8: =IF(L8=0,"n.a.",K8/L8) -> 0
A9: Male | B9: Rated | C9: 389.4984 | D9: 2 | E9: 1.574031 | F9: =D9/E9 -> 1.270623 | H9: Non-smoker | I9: =COUNTIFS('Policy Data'!$E$4:$E$253,"Non-smoker") -> 203 | J9: =SUMIFS('Policy Data'!$L$4:$L$253,'Policy Data'!$E$4:$E$253,"Non-smoker") -> 153.6036 | K9: =SUMIFS('Policy Data'!$O$4:$O$253,'Policy Data'!$E$4:$E$253,"Non-smoker") -> 0 | L9: =SUMIFS('Policy Data'!$N$4:$N$253,'Policy Data'!$E$4:$E$253,"Non-smoker") -> 0.314183 | M9: =IF(L9=0,"n.a.",K9/L9) -> 0
A10: Male | B10: Standard | C10: 3987.3533 | D10: 13 | E10: 10.501633 | F10: =D10/E10 -> 1.2379027 | H10: Smoker | I10: =COUNTIFS('Policy Data'!$E$4:$E$253,"Smoker") -> 47 | J10: =SUMIFS('Policy Data'!$L$4:$L$253,'Policy Data'!$E$4:$E$253,"Smoker") -> 35.2807 | K10: =SUMIFS('Policy Data'!$O$4:$O$253,'Policy Data'!$E$4:$E$253,"Smoker") -> 0 | L10: =SUMIFS('Policy Data'!$N$4:$N$253,'Policy Data'!$E$4:$E$253,"Smoker") -> 0.133629 | M10: =IF(L10=0,"n.a.",K10/L10) -> 0
H11: Duration 1-2 | I11: =COUNTIFS('Policy Data'!$K$4:$K$253,"<=2") -> 72 | J11: =SUMIFS('Policy Data'!$L$4:$L$253,'Policy Data'!$K$4:$K$253,"<=2") -> 52.4703 | K11: =SUMIFS('Policy Data'!$O$4:$O$253,'Policy Data'!$K$4:$K$253,"<=2") -> 0 | L11: =SUMIFS('Policy Data'!$N$4:$N$253,'Policy Data'!$K$4:$K$253,"<=2") -> 0.122047 | M11: =IF(L11=0,"n.a.",K11/L11) -> 0
H12: Duration 3+ | I12: =COUNTIFS('Policy Data'!$K$4:$K$253,">=3") -> 178 | J12: =SUMIFS('Policy Data'!$L$4:$L$253,'Policy Data'!$K$4:$K$253,">=3") -> 136.414 | K12: =SUMIFS('Policy Data'!$O$4:$O$253,'Policy Data'!$K$4:$K$253,">=3") -> 0 | L12: =SUMIFS('Policy Data'!$N$4:$N$253,'Policy Data'!$K$4:$K$253,">=3") -> 0.325765 | M12: =IF(L12=0,"n.a.",K12/L12) -> 0
A13: Duration | B13: Product | C13: Premium frequency | D13: Exposure | E13: Observed lapse rate
A14: 1 | B14: Term Life | C14: Annual | D14: 296.4876 | E14: 0.12479443
A15: 1 | B15: Term Life | C15: Monthly | D15: 607.4157 | E15: 0.17615613 | H15: This analysis uses the 250 synthetic policies in the Policy Data sheet. Age, smoker status and duration are separate views of the same policies and should not be added together.
A16: 1 | B16: Unit-Linked | C16: Annual | D16: 148.6151 | E16: 0.087474288
A17: 1 | B17: Unit-Linked | C17: Monthly | D17: 231.3876 | E17: 0.17287011
A18: 2 | B18: Term Life | C18: Annual | D18: 353.3362 | E18: 0.10188597
A19: 2 | B19: Term Life | C19: Monthly | D19: 581.6789 | E19: 0.14956705
A20: 2 | B20: Unit-Linked | C20: Annual | D20: 135.7369 | E20: 0.1105079
A21: 2 | B21: Unit-Linked | C21: Monthly | D21: 232.4196 | E21: 0.10326151
A22: 3 | B22: Term Life | C22: Annual | D22: 327.4372 | E22: 0.088566601
A23: 3 | B23: Term Life | C23: Monthly | D23: 593.2943 | E23: 0.11292878
A24: 3 | B24: Unit-Linked | C24: Annual | D24: 110.6022 | E24: 0.045207057
A25: 3 | B25: Unit-Linked | C25: Monthly | D25: 212.9712 | E25: 0.12677771
A26: 4 | B26: Term Life | C26: Annual | D26: 324.7444 | E26: 0.076983622
A27: 4 | B27: Term Life | C27: Monthly | D27: 602.6278 | E27: 0.10122334
... A41: 7 | B41: Unit-Linked | C41: Monthly | D41: 233.6946 | E41: 0.034232712
A45: Supplied synthetic study totals | B45: Value | C45: Definition
A46: Policies | B46: 12000 | C46: Synthetic experience dataset used for the mortality and lapse analysis
A47: Exposure | B47: 9026.8084 | C47: Policy-years
A48: Actual deaths | B48: 26 | C48: Events
A49: Expected deaths | B49: 21.204816 | C49: Sum of supplied rounded expected deaths
A50: Mortality A/E | B50: =B48/B49 -> 1.2261366 | C50: Actual / expected
A51: Lapses | B51: 803 | C51: Events
A52: Lapse incidence | B52: =B51/B47 -> 0.088957244 | C52: Events per exposed policy-year
A53: Annualised lapse-only persistency | B53: =EXP(-B52) -> 0.91488469 | C53: Constant-force proxy, excludes mortality
A54: Dual death/lapse flags | B54: 3 | C54: 3 records contain both death and lapse flags and are excluded from assumption calibration
A56: Data basis: Policy and experience data are synthetic and were generated for this project. Mortality and lapse experience is illustrative and is intended to demonstrate the experience-analysis methodology rather than represent the experience of a specific insurer or market.

Sheet Assumption Review
A1: Assumption Review
A2: Review of mortality and lapse experience to assess whether changes to the current pricing assumptions are supported by the data.
A4: Credibility parameters
A5: Full-credibility standard (deaths) | B5: =(NORMSINV(0.5+B6/2)/B7)^2 -> 1082.2174 | C5: Limited-fluctuation credibility standard
A6: Probability that estimate is within tolerance | B6: 0.9
A7: Tolerance (k) | B7: 0.05
A8: Current basis A/E | B8: 1
A10: A. Mortality
A11: Actual deaths | B11: ='Experience Analysis'!B48 -> 26 | C11: Experience Analysis B47
A12: Expected deaths – expected basis | B12: ='Experience Analysis'!B49 -> 21.204816 | C12: Experience Analysis B48
A13: A/E vs study expected basis | B13: =B11/B12 -> 1.2261366 | C13: Headline A/E shown on Experience Analysis
A14: Approx. 95% interval – lower | B14: =MAX(0,(B11-1.96*SQRT(B11))/B12) -> 0.75482484 | C14: Normal approximation to Poisson count
A15: Approx. 95% interval – upper | B15: =(B11+1.96*SQRT(B11))/B12 -> 1.6974483 | C15: Interval includes 1.00 ⇒ not statistically distinguishable from expected
A16: Sample expected deaths – study basis (250 records) | B16: =SUM('Policy Calculations'!$EA$30:$EA$279) -> 0.447812 | C16: Policy Data column N
A17: Sample expected deaths – pricing basis (250 records) | B17: =SUM('Policy Calculations'!$EB$30:$EB$279) -> 0.58083935 | C17: Exposure × Mortality qx (attained age) × UW factor
A18: Basis bridge: study ÷ pricing expected | B18: =B16/B17 -> 0.77097393 | C18: Study basis is lighter than the pricing table (select-type effect)
A19: Implied A/E vs pricing basis | B19: =B13*B18 -> 0.94531932 | C19: Approximation: assumes sample mix represents the full study
A20: Credibility factor Z | B20: =MIN(1,SQRT(B11/B5)) -> 0.15499919 | C20: Limited-fluctuation credibility on death count
A21: Credibility-weighted A/E | B21: =B20*B19+(1-B20)*B8 -> 0.99152454 | C21: Z × implied A/E + (1 − Z) × prior
A22: Potential mortality multiplier | B22: =IF(ISNUMBER(B23),B23,ROUND(B21,3)) -> 0.992 | C22: Applied multiplicatively to live Assumptions C21 in the impact test
A23: Actuarial judgement override (optional) | C23: Leave blank to use the credibility result
A24: Interpretation | B24: =IF(B20<0.5,"Low credibility: retain basis and monitor",IF(ABS(B22-1)<0.025,"Retain current basis","Investigate before changing basis")) -> Low credibility: retain basis and monitor
A27: B. Term life lapse experience
A28: Duration | B28: Exposure – annual pay | C28: Exposure – monthly pay | D28: Exposure – total | E28: Actual lapses | F28: Pricing lapse rate | G28: Expected lapses | H28: A/E | I28: Actual – annual pay | J28: Actual – monthly pay
A29: 1 | B29: =SUMIFS('Experience Analysis'!$D$14:$D$41,'Experience Analysis'!$A$14:$A$41,$A29,'Experience Analysis'!$B$14:$B$41,"Term Life",'Experience Analysis'!$C$14:$C$41,"Annual") -> 296.4876 | C29: =SUMIFS('Experience Analysis'!$D$14:$D$41,'Experience Analysis'!$A$14:$A$41,$A29,'Experience Analysis'!$B$14:$B$41,"Term Life",'Experience Analysis'!$C$14:$C$41,"Monthly") -> 607.4157 | D29: =B29+C29 -> 903.9033 | E29: =I29+J29 -> 144 | F29: =MIN(1,MAX(Assumptions!$C$27,Assumptions!$C$13*Assumptions!$C$28^(A29-1))) -> 0.12 | G29: =D29*F29 -> 108.4684 | H29: =IF(G29=0,"",E29/G29) -> 1.3275756 | I29: =SUMPRODUCT(('Experience Analysis'!$A$14:$A$41=$A29)*('Experience Analysis'!$B$14:$B$41="Term Life")*('Experience Analysis'!$C$14:$C$41="Annual")*'Experience Analysis'!$D$14:$D$41*'Experience Analysis'!$E$14:$E$41) -> 37 | J29: =SUMPRODUCT(('Experience Analysis'!$A$14:$A$41=$A29)*('Experience Analysis'!$B$14:$B$41="Term Life")*('Experience Analysis'!$C$14:$C$41="Monthly")*'Experience Analysis'!$D$14:$D$41*'Experience Analysis'!$E$14:$E$41) -> 107
A30: 2 | B30: =SUMIFS('Experience Analysis'!$D$14:$D$41,'Experience Analysis'!$A$14:$A$41,$A30,'Experience Analysis'!$B$14:$B$41,"Term Life",'Experience Analysis'!$C$14:$C$41,"Annual") -> 353.3362 | C30: =SUMIFS('Experience Analysis'!$D$14:$D$41,'Experience Analysis'!$A$14:$A$41,$A30,'Experience Analysis'!$B$14:$B$41,"Term Life",'Experience Analysis'!$C$14:$C$41,"Monthly") -> 581.6789 | D30: =B30+C30 -> 935.0151 | E30: =I30+J30 -> 123 | F30: =MIN(1,MAX(Assumptions!$C$27,Assumptions!$C$13*Assumptions!$C$28^(A30-1))) -> 0.102 | G30: =D30*F30 -> 95.37154 | H30: =IF(G30=0,"",E30/G30) -> 1.2896929 | I30: =SUMPRODUCT(('Experience Analysis'!$A$14:$A$41=$A30)*('Experience Analysis'!$B$14:$B$41="Term Life")*('Experience Analysis'!$C$14:$C$41="Annual")*'Experience Analysis'!$D$14:$D$41*'Experience Analysis'!$E$14:$E$41) -> 36 | J30: =SUMPRODUCT(('Experience Analysis'!$A$14:$A$41=$A30)*('Experience Analysis'!$B$14:$B$41="Term Life")*('Experience Analysis'!$C$14:$C$41="Monthly")*'Experience Analysis'!$D$14:$D$41*'Experience Analysis'!$E$14:$E$41) -> 87
A31: 3 | B31: =SUMIFS('Experience Analysis'!$D$14:$D$41,'Experience Analysis'!$A$14:$A$41,$A31,'Experience Analysis'!$B$14:$B$41,"Term Life",'Experience Analysis'!$C$14:$C$41,"Annual") -> 327.4372 | C31: =SUMIFS('Experience Analysis'!$D$14:$D$41,'Experience Analysis'!$A$14:$A$41,$A31,'Experience Analysis'!$B$14:$B$41,"Term Life",'Experience Analysis'!$C$14:$C$41,"Monthly") -> 593.2943 | D31: =B31+C31 -> 920.7315 | E31: =I31+J31 -> 96 | F31: =MIN(1,MAX(Assumptions!$C$27,Assumptions!$C$13*Assumptions!$C$28^(A31-1))) -> 0.0867 | G31: =D31*F31 -> 79.827421 | H31: =IF(G31=0,"",E31/G31) -> 1.2025943 | I31: =SUMPRODUCT(('Experience Analysis'!$A$14:$A$41=$A31)*('Experience Analysis'!$B$14:$B$41="Term Life")*('Experience Analysis'!$C$14:$C$41="Annual")*'Experience Analysis'!$D$14:$D$41*'Experience Analysis'!$E$14:$E$41) -> 29 | J31: =SUMPRODUCT(('Experience Analysis'!$A$14:$A$41=$A31)*('Experience Analysis'!$B$14:$B$41="Term Life")*('Experience Analysis'!$C$14:$C$41="Monthly")*'Experience Analysis'!$D$14:$D$41*'Experience Analysis'!$E$14:$E$41) -> 67
A32: 4 | B32: =SUMIFS('Experience Analysis'!$D$14:$D$41,'Experience Analysis'!$A$14:$A$41,$A32,'Experience Analysis'!$B$14:$B$41,"Term Life",'Experience Analysis'!$C$14:$C$41,"Annual") -> 324.7444 | C32: =SUMIFS('Experience Analysis'!$D$14:$D$41,'Experience Analysis'!$A$14:$A$41,$A32,'Experience Analysis'!$B$14:$B$41,"Term Life",'Experience Analysis'!$C$14:$C$41,"Monthly") -> 602.6278 | D32: =B32+C32 -> 927.3722 | E32: =I32+J32 -> 86 | F32: =MIN(1,MAX(Assumptions!$C$27,Assumptions!$C$13*Assumptions!$C$28^(A32-1))) -> 0.073695 | G32: =D32*F32 -> 68.342694 | H32: =IF(G32=0,"",E32/G32) -> 1.2583642 | I32: =SUMPRODUCT(('Experience Analysis'!$A$14:$A$41=$A32)*('Experience Analysis'!$B$14:$B$41="Term Life")*('Experience Analysis'!$C$14:$C$41="Annual")*'Experience Analysis'!$D$14:$D$41*'Experience Analysis'!$E$14:$E$41) -> 25 | J32: =SUMPRODUCT(('Experience Analysis'!$A$14:$A$41=$A32)*('Experience Analysis'!$B$14:$B$41="Term Life")*('Experience Analysis'!$C$14:$C$41="Monthly")*'Experience Analysis'!$D$14:$D$41*'Experience Analysis'!$E$14:$E$41) -> 61
A33: 5 | B33: =SUMIFS('Experience Analysis'!$D$14:$D$41,'Experience Analysis'!$A$14:$A$41,$A33,'Experience Analysis'!$B$14:$B$41,"Term Life",'Experience Analysis'!$C$14:$C$41,"Annual") -> 352.9718 | C33: =SUMIFS('Experience Analysis'!$D$14:$D$41,'Experience Analysis'!$A$14:$A$41,$A33,'Experience Analysis'!$B$14:$B$41,"Term Life",'Experience Analysis'!$C$14:$C$41,"Monthly") -> 634.6725 | D33: =B33+C33 -> 987.6443 | E33: =I33+J33 -> 64 | F33: =MIN(1,MAX(Assumptions!$C$27,Assumptions!$C$13*Assumptions!$C$28^(A33-1))) -> 0.06264075 | G33: =D33*F33 -> 61.86678 | H33: =IF(G33=0,"",E33/G33) -> 1.0344809 | I33: =SUMPRODUCT(('Experience Analysis'!$A$14:$A$41=$A33)*('Experience Analysis'!$B$14:$B$41="Term Life")*('Experience Analysis'!$C$14:$C$41="Annual")*'Experience Analysis'!$D$14:$D$41*'Experience Analysis'!$E$14:$E$41) -> 14 | J33: =SUMPRODUCT(('Experience Analysis'!$A$14:$A$41=$A33)*('Experience Analysis'!$B$14:$B$41="Term Life")*('Experience Analysis'!$C$14:$C$41="Monthly")*'Experience Analysis'!$D$14:$D$41*'Experience Analysis'!$E$14:$E$41) -> 50
A34: 6 | B34: =SUMIFS('Experience Analysis'!$D$14:$D$41,'Experience Analysis'!$A$14:$A$41,$A34,'Experience Analysis'!$B$14:$B$41,"Term Life",'Experience Analysis'!$C$14:$C$41,"Annual") -> 342.7011 | C34: =SUMIFS('Experience Analysis'!$D$14:$D$41,'Experience Analysis'!$A$14:$A$41,$A34,'Experience Analysis'!$B$14:$B$41,"Term Life",'Experience Analysis'!$C$14:$C$41,"Monthly") -> 617.1423 | D34: =B34+C34 -> 959.8434 | E34: =I34+J34 -> 42 | F34: =MIN(1,MAX(Assumptions!$C$27,Assumptions!$C$13*Assumptions!$C$28^(A34-1))) -> 0.053244637 | G34: =D34*F34 -> 51.106514 | H34: =IF(G34=0,"",E34/G34) -> 0.82181305 | I34: =SUMPRODUCT(('Experience Analysis'!$A$14:$A$41=$A34)*('Experience Analysis'!$B$14:$B$41="Term Life")*('Experience Analysis'!$C$14:$C$41="Annual")*'Experience Analysis'!$D$14:$D$41*'Experience Analysis'!$E$14:$E$41) -> 13 | J34: =SUMPRODUCT(('Experience Analysis'!$A$14:$A$41=$A34)*('Experience Analysis'!$B$14:$B$41="Term Life")*('Experience Analysis'!$C$14:$C$41="Monthly")*'Experience Analysis'!$D$14:$D$41*'Experience Analysis'!$E$14:$E$41) -> 29
A35: 7 | B35: =SUMIFS('Experience Analysis'!$D$14:$D$41,'Experience Analysis'!$A$14:$A$41,$A35,'Experience Analysis'!$B$14:$B$41,"Term Life",'Experience Analysis'!$C$14:$C$41,"Annual") -> 300.4408 | C35: =SUMIFS('Experience Analysis'!$D$14:$D$41,'Experience Analysis'!$A$14:$A$41,$A35,'Experience Analysis'!$B$14:$B$41,"Term Life",'Experience Analysis'!$C$14:$C$41,"Monthly") -> 599.5011 | D35: =B35+C35 -> 899.9419 | E35: =I35+J35 -> 45 | F35: =MIN(1,MAX(Assumptions!$C$27,Assumptions!$C$13*Assumptions!$C$28^(A35-1))) -> 0.045257942 | G35: =D35*F35 -> 40.729518 | H35: =IF(G35=0,"",E35/G35) -> 1.1048498 | I35: =SUMPRODUCT(('Experience Analysis'!$A$14:$A$41=$A35)*('Experience Analysis'!$B$14:$B$41="Term Life")*('Experience Analysis'!$C$14:$C$41="Annual")*'Experience Analysis'!$D$14:$D$41*'Experience Analysis'!$E$14:$E$41) -> 13 | J35: =SUMPRODUCT(('Experience Analysis'!$A$14:$A$41=$A35)*('Experience Analysis'!$B$14:$B$41="Term Life")*('Experience Analysis'!$C$14:$C$41="Monthly")*'Experience Analysis'!$D$14:$D$41*'Experience Analysis'!$E$14:$E$41) -> 32
A36: Total | B36: =SUM(B29:B35) -> 2298.1191 | C36: =SUM(C29:C35) -> 4236.3326 | D36: =SUM(D29:D35) -> 6534.4517 | E36: =SUM(E29:E35) -> 600 | G36: =SUM(G29:G35) -> 505.71286 | H36: =E36/G36 -> 1.186444 | I36: =SUM(I29:I35) -> 167 | J36: =SUM(J29:J35) -> 433
A38: Actual lapse events (Term, d1–7) | B38: =E36 -> 600
A39: Lapse A/E – overall | B39: =H36 -> 1.186444 | C39: Pricing basis = Base_Lapse × Lapse_Decay^(d−1), floored
A40: A/E – annual-pay Term | B40: =I36/SUMPRODUCT(B29:B35,F29:F35) -> 0.9387592 | C40: Frequency-specific view
A41: A/E – monthly-pay Term | B41: =J36/SUMPRODUCT(C29:C35,F29:F35) -> 1.320853 | C41: Monthly payers lapse faster: consider a frequency-specific basis
A42: Credibility factor Z | B42: =MIN(1,SQRT(B38/B5)) -> 0.74459201 | C42: Same full-credibility standard as mortality
A43: Credibility-weighted A/E | B43: =B42*B39+(1-B42)*B8 -> 1.1388247
A44: Actuarial judgement override (optional) | C44: Leave blank to use the credibility result
A45: Potential lapse multiplier | B45: =IF(ISNUMBER(B44),B44,ROUND(B43,3)) -> 1.139 | C45: Applied multiplicatively to live Assumptions C22 in the impact test
A46: Interpretation | B46: =IF(ABS(B45-1)<0.025,"Retain current lapse basis",IF(B45>1,"Experience lapses exceed basis – consider higher lapse assumption (and frequency split)","Experience lapses below basis – consider lower lapse assumption")) -> Experience lapses exceed basis – consider higher lapse assumption (and frequency split)
A48: Individual policy: effect of the potential basis
A49: Metric | B49: Current basis | C49: Recommended basis | D49: Change | E49: Change % | F49: Source
A50: Quote PVFP at charged premium (AED) | B50: ='Policy Calculations'!AI23 -> 344.85011 | C50: ='Policy Calculations'!AI24 -> 294.54703 | D50: =C50-B50 -> -50.303084 | E50: =IF(B50=0,"",D50/ABS(B50)) -> -0.14586942 | F50: Formula comparison
A51: Quote NBM at charged premium | B51: ='Policy Calculations'!AJ23 -> 0.10461954 | C51: ='Policy Calculations'!AJ24 -> 0.093697552 | D51: =C51-B51 -> -0.010921983 | E51: =IF(B51=0,"",D51/ABS(B51)) -> -0.10439717 | F51: Formula comparison
A52: Quote technical premium to hit target NBM (AED) | B52: ='Policy Calculations'!AF23 -> 562.44258 | C52: ='Policy Calculations'!AF24 -> 569.91473 | D52: =C52-B52 -> 7.4721505 | E52: =IF(B52=0,"",D52/ABS(B52)) -> 0.013285179 | F52: Formula comparison

Sheet Sensitivities
A1: Sensitivities
A2: Sensitivity analysis of policy profitability and technical premium under alternative assumptions.
A3: Mortality, lapse and expense stresses are multiplicative; commission and discount stresses are additive.
A7: Lever | B7: Assumptions | C7: Base | D7: Upside | E7: Downside | F7: Custom | G7: Current value | H7: Matches base?
A8: Mortality multiplier | B8: Assumptions!C21 | C8: 1 | D8: 0.95 | E8: 1.1 | F8: 1.15 | G8: =Assumptions!C21 -> 1 | H8: =IF(ABS(G8-C8)<0.0000001,"Yes","No") -> Yes
A9: Lapse multiplier | B9: Assumptions!C22 | C9: 1 | D9: 0.9 | E9: 1.2 | F9: 1.5 | G9: =Assumptions!C22 -> 1 | H9: =IF(ABS(G9-C9)<0.0000001,"Yes","No") -> Yes
A10: Expense multiplier | B10: Assumptions!C23 | C10: 1 | D10: 0.95 | E10: 1.1 | F10: 1 | G10: =Assumptions!C23 -> 1 | H10: =IF(ABS(G10-C10)<0.0000001,"Yes","No") -> Yes
A11: Commission shift (pp) | B11: Assumptions!C24 | C11: 0 | D11: 0 | E11: 0.02 | F11: 0 | G11: =Assumptions!C24 -> 0 | H11: =IF(ABS(G11-C11)<0.0000001,"Yes","No") -> Yes
A12: Discount-rate shift | B12: Assumptions!C25 | C12: 0 | D12: 0.005 | E12: -0.005 | F12: 0 | G12: =Assumptions!C25 -> 0 | H12: =IF(ABS(G12-C12)<0.0000001,"Yes","No") -> Yes
A13: UL fund-return shift | B13: Assumptions!C26 | C13: 0 | D13: 0.01 | E13: -0.01 | F13: -0.02 | G13: =Assumptions!C26 -> 0 | H13: =IF(ABS(G13-C13)<0.0000001,"Yes","No") -> Yes
A16: Current pricing basis | C16: =IF(AND(ABS(G8-C8)<0.0000001,ABS(G9-C9)<0.0000001,ABS(G10-C10)<0.0000001,ABS(G11-C11)<0.0000001,ABS(G12-C12)<0.0000001,ABS(G13-C13)<0.0000001),"Base",IF(AND(ABS(G8-D8)<0.0000001,ABS(G9-D9)<0.0000001,ABS(G10-D10)<0.0000001,ABS(G11-D11)<0.0000001,ABS(G12-D12)<0.0000001,ABS(G13-D13)<0.0000001),"Upside",IF(AND(ABS(G8-E8)<0.0000001,ABS(G9-E9)<0.0000001,ABS(G10-E10)<0.0000001,ABS(G11-E11)<0.0000001,ABS(G12-E12)<0.0000001,ABS(G13-E13)<0.0000001),"Downside",IF(AND(ABS(G8-F8)<0.0000001,ABS(G9-F9)<0.0000001,ABS(G10-F10)<0.0000001,ABS(G11-F11)<0.0000001,ABS(G12-F12)<0.0000001,ABS(G13-F13)<0.0000001),"Custom","Manual inputs")))) -> Base
A18: Scenario comparison
A19: Scenario | B19: PVFP (AED) | C19: Δ PVFP vs Base | D19: NBM | E19: Technical premium | F19: Δ premium vs Base | G19: Profitability | H19: PV premiums | I19: RI effect on PVFP | J19: Comment
A20: Base | B20: ='Policy Calculations'!AI7 -> 344.85011 | C20: =B20-$B$20 -> 0 | D20: ='Policy Calculations'!AJ7 -> 0.10461954 | E20: ='Policy Calculations'!AF7 -> 562.44258 | F20: =IF(ISNUMBER(E20),E20/$E$20-1,"n.a.") -> 0 | G20: ='Policy Calculations'!AR7 -> At/above target | H20: ='Policy Calculations'!AH7 -> 3296.2306 | I20: ='Policy Calculations'!AN7 -> 0
A21: Upside | B21: ='Policy Calculations'!AI8 -> 499.21954 | C21: =B21-$B$20 -> 154.36943 | D21: ='Policy Calculations'!AJ8 -> 0.14966078 | E21: ='Policy Calculations'!AF8 -> 531.5962 | F21: =IF(ISNUMBER(E21),E21/$E$20-1,"n.a.") -> -0.054843616 | G21: ='Policy Calculations'!AR8 -> At/above target | H21: ='Policy Calculations'!AH8 -> 3335.6738 | I21: ='Policy Calculations'!AN8 -> 0
A22: Downside | B22: ='Policy Calculations'!AI9 -> -36.334589 | C22: =B22-$B$20 -> -381.1847 | D22: ='Policy Calculations'!AJ9 -> -0.011547275 | E22: ='Policy Calculations'!AF9 -> 643.68089 | F22: =IF(ISNUMBER(E22),E22/$E$20-1,"n.a.") -> 0.1444384 | G22: ='Policy Calculations'!AR9 -> Loss-making | H22: ='Policy Calculations'!AH9 -> 3146.5942 | I22: ='Policy Calculations'!AN9 -> 0 | J22: Downside combines adverse movements in the key pricing assumptions.
A23: Custom | B23: ='Policy Calculations'!AI10 -> 123.87827 | C23: =B23-$B$20 -> -220.97184 | D23: ='Policy Calculations'!AJ10 -> 0.04452363 | E23: ='Policy Calculations'!AF10 -> 603.7621 | F23: =IF(ISNUMBER(E23),E23/$E$20-1,"n.a.") -> 0.073464417 | G23: ='Policy Calculations'!AR10 -> Below target | H23: ='Policy Calculations'!AH10 -> 2782.304 | I23: ='Policy Calculations'!AN10 -> 0
A25: One-way sensitivity analysis
A26: Driver | B26: Stress (±) | C26: Stress size (input) | D26: NBM (up stress) | E26: PVFP down | F26: PVFP up | G26: Δ PVFP down | H26: Δ PVFP up | I26: PVFP range | J26: NBM down / up
A27: Mortality (qx) | B27: ="±"&TEXT(C27,"0%") -> ±10% | C27: 0.1 | D27: ='Policy Calculations'!AJ12 -> 0.094266193 | E27: ='Policy Calculations'!AI11 -> 379.05135 | F27: ='Policy Calculations'!AI12 -> 310.66441 | G27: =E27-'Policy Calculations'!$AI$6 -> 34.201242 | H27: =F27-'Policy Calculations'!$AI$6 -> -34.185704 | I27: =ABS(H27-G27)+ROW()/1000000000 -> 68.386946 | J27: =TEXT('Policy Calculations'!AJ11,"0.0%")&" / "&TEXT('Policy Calculations'!AJ12,"0.0%") -> 11.5% / 9.4%
A28: Lapse rates | B28: ="±"&TEXT(C28,"0%") -> ±20% | C28: 0.2 | D28: ='Policy Calculations'!AJ14 -> 0.087541527 | E28: ='Policy Calculations'!AI13 -> 425.61547 | F28: ='Policy Calculations'!AI14 -> 269.546 | G28: =E28-'Policy Calculations'!$AI$6 -> 80.765358 | H28: =F28-'Policy Calculations'!$AI$6 -> -75.304113 | I28: =ABS(H28-G28)+ROW()/1000000000 -> 156.06947 | J28: =TEXT('Policy Calculations'!AJ13,"0.0%")&" / "&TEXT('Policy Calculations'!AJ14,"0.0%") -> 12.1% / 8.8%
A29: Expenses | B29: ="±"&TEXT(C29,"0%") -> ±10% | C29: 0.1 | D29: ='Policy Calculations'!AJ16 -> 0.032866129 | E29: ='Policy Calculations'!AI15 -> 581.36588 | F29: ='Policy Calculations'!AI16 -> 108.33434 | G29: =E29-'Policy Calculations'!$AI$6 -> 236.51577 | H29: =F29-'Policy Calculations'!$AI$6 -> -236.51577 | I29: =ABS(H29-G29)+ROW()/1000000000 -> 473.03154 | J29: =TEXT('Policy Calculations'!AJ15,"0.0%")&" / "&TEXT('Policy Calculations'!AJ16,"0.0%") -> 17.6% / 3.3%
A30: Commission (pp) | B30: ="±"&TEXT(C30*100,"0.0")&"pp" -> ±5.0pp | C30: 0.05 | D30: ='Policy Calculations'!AJ18 -> 0.054619535 | E30: ='Policy Calculations'!AI17 -> 509.66164 | F30: ='Policy Calculations'!AI18 -> 180.03858 | G30: =E30-'Policy Calculations'!$AI$6 -> 164.81153 | H30: =F30-'Policy Calculations'!$AI$6 -> -164.81153 | I30: =ABS(H30-G30)+ROW()/1000000000 -> 329.62306 | J30: =TEXT('Policy Calculations'!AJ17,"0.0%")&" / "&TEXT('Policy Calculations'!AJ18,"0.0%") -> 15.5% / 5.5%
A31: Discount rate | B31: ="±"&TEXT(C31*10000,"0")&"bp" -> ±100bp | C31: 0.01 | D31: ='Policy Calculations'!AJ20 -> 0.096560132 | E31: ='Policy Calculations'!AI19 -> 388.32754 | F31: ='Policy Calculations'!AI20 -> 304.55847 | G31: =E31-'Policy Calculations'!$AI$6 -> 43.477434 | H31: =F31-'Policy Calculations'!$AI$6 -> -40.291635 | I31: =ABS(H31-G31)+ROW()/1000000000 -> 83.769069 | J31: =TEXT('Policy Calculations'!AJ19,"0.0%")&" / "&TEXT('Policy Calculations'!AJ20,"0.0%") -> 11.3% / 9.7%
A32: RI premium rate | B32: ="±"&TEXT(C32,"0%") -> ±20% | C32: 0.2 | D32: ='Policy Calculations'!AJ22 -> 0.10461954 | E32: ='Policy Calculations'!AI21 -> 344.85011 | F32: ='Policy Calculations'!AI22 -> 344.85011 | G32: =E32-'Policy Calculations'!$AI$6 -> 0 | H32: =F32-'Policy Calculations'!$AI$6 -> 0 | I32: =ABS(H32-G32)+ROW()/1000000000 -> 3.2e-08 | J32: =TEXT('Policy Calculations'!AJ21,"0.0%")&" / "&TEXT('Policy Calculations'!AJ22,"0.0%") -> 10.5% / 10.5%
A33: Base PVFP | E33: ='Policy Calculations'!AI6 -> 344.85011
A36: PVFP sensitivity ranking
A37: Rank | B37: Driver | C37: Δ PVFP (down stress) | D37: Δ PVFP (up stress) | E37: Range
A38: 1 | B38: =INDEX($A$27:$A$32,MATCH(E38,$I$27:$I$32,0))&" ("&INDEX($B$27:$B$32,MATCH(E38,$I$27:$I$32,0))&")" -> Expenses (±10%) | C38: =INDEX($G$27:$G$32,MATCH(E38,$I$27:$I$32,0)) -> 236.51577 | D38: =INDEX($H$27:$H$32,MATCH(E38,$I$27:$I$32,0)) -> -236.51577 | E38: =LARGE($I$27:$I$32,A38) -> 473.03154
A39: 2 | B39: =INDEX($A$27:$A$32,MATCH(E39,$I$27:$I$32,0))&" ("&INDEX($B$27:$B$32,MATCH(E39,$I$27:$I$32,0))&")" -> Commission (pp) (±5.0pp) | C39: =INDEX($G$27:$G$32,MATCH(E39,$I$27:$I$32,0)) -> 164.81153 | D39: =INDEX($H$27:$H$32,MATCH(E39,$I$27:$I$32,0)) -> -164.81153 | E39: =LARGE($I$27:$I$32,A39) -> 329.62306
A40: 3 | B40: =INDEX($A$27:$A$32,MATCH(E40,$I$27:$I$32,0))&" ("&INDEX($B$27:$B$32,MATCH(E40,$I$27:$I$32,0))&")" -> Lapse rates (±20%) | C40: =INDEX($G$27:$G$32,MATCH(E40,$I$27:$I$32,0)) -> 80.765358 | D40: =INDEX($H$27:$H$32,MATCH(E40,$I$27:$I$32,0)) -> -75.304113 | E40: =LARGE($I$27:$I$32,A40) -> 156.06947
A41: 4 | B41: =INDEX($A$27:$A$32,MATCH(E41,$I$27:$I$32,0))&" ("&INDEX($B$27:$B$32,MATCH(E41,$I$27:$I$32,0))&")" -> Discount rate (±100bp) | C41: =INDEX($G$27:$G$32,MATCH(E41,$I$27:$I$32,0)) -> 43.477434 | D41: =INDEX($H$27:$H$32,MATCH(E41,$I$27:$I$32,0)) -> -40.291635 | E41: =LARGE($I$27:$I$32,A41) -> 83.769069
A42: 5 | B42: =INDEX($A$27:$A$32,MATCH(E42,$I$27:$I$32,0))&" ("&INDEX($B$27:$B$32,MATCH(E42,$I$27:$I$32,0))&")" -> Mortality (qx) (±10%) | C42: =INDEX($G$27:$G$32,MATCH(E42,$I$27:$I$32,0)) -> 34.201242 | D42: =INDEX($H$27:$H$32,MATCH(E42,$I$27:$I$32,0)) -> -34.185704 | E42: =LARGE($I$27:$I$32,A42) -> 68.386946
A43: 6 | B43: =INDEX($A$27:$A$32,MATCH(E43,$I$27:$I$32,0))&" ("&INDEX($B$27:$B$32,MATCH(E43,$I$27:$I$32,0))&")" -> RI premium rate (±20%) | C43: =INDEX($G$27:$G$32,MATCH(E43,$I$27:$I$32,0)) -> 0 | D43: =INDEX($H$27:$H$32,MATCH(E43,$I$27:$I$32,0)) -> 0 | E43: =LARGE($I$27:$I$32,A43) -> 3.2e-08

Sheet IFRS 17 GMM
A1: IFRS 17 GMM
A3: Metric | B3: Value | C3: Unit | D3: Basis | F3: Year | G3: Opening CSM | H3: Accretion | I3: Future service Δ | J3: CSM before release | K3: Coverage units | L3: CSM release | M3: Closing CSM | N3: Opening BEL | O3: Gross outgo | P3: RA release | Q3: Closing BEL | R3: Closing RA | S3: LRC | T3: Roll-forward Δ | U3: CSM excess loss
A4: PV future premiums | B4: ='Profit Testing'!B4 -> 3296.2306 | C4: AED | D4: Gross underlying contracts | F4: 1 | G4: =$B$8 -> 256.3087 | H4: =G4*(Assumptions!$C$6+Assumptions!$C$25) -> 8.9708044 | I4: 0 | J4: =MAX(0,G4+H4+I4) -> 265.2795 | K4: =Cashflows!B4*'Premium Calculation'!$B$9 -> 100000 | L4: =IF(SUM(K4:$K$43)=0,0,J4*K4/SUM(K4:$K$43)) -> 38.422895 | M4: =J4-L4 -> 226.85661 | N4: =$B$5-$B$4 -> -344.85011 | O4: =Cashflows!F4+Cashflows!I4+Cashflows!J4 -> 1274.7576 | P4: =$B$6*IF(SUM($K$4:$K$43)=0,0,K4/SUM($K$4:$K$43)) -> 12.824275 | Q4: =N4*(1+Assumptions!$C$6+Assumptions!$C$25)+Cashflows!E4-O4 -> -1069.2349 | R4: =$B$6-P4 -> 75.717138 | S4: =Q4+R4+M4 -> -766.66115 | T4: =$B$15+Cashflows!E4-O4+N4*(Assumptions!$C$6+Assumptions!$C$25)+H4+I4-L4-P4+U4-S4 -> 0 | U4: =MAX(0,-(G4+H4+I4)) -> 0
A5: PV gross outgo | B5: =SUMPRODUCT(Cashflows!F4:F43,Cashflows!M4:M43)+SUMPRODUCT(Cashflows!I4:I43,Cashflows!M4:M43)+SUMPRODUCT(Cashflows!J4:J43,Cashflows!M4:M43) -> 2951.3804 | C5: AED | D5: Claims, expenses and commission before RI | F5: 2 | G5: =M4 -> 226.85661 | H5: =G5*(Assumptions!$C$6+Assumptions!$C$25) -> 7.9399812 | I5: 0 | J5: =MAX(0,G5+H5+I5) -> 234.79659 | K5: =Cashflows!B5*'Premium Calculation'!$B$9 -> 87962.803 | L5: =IF(SUM(K5:$K$43)=0,0,J5*K5/SUM(K5:$K$43)) -> 34.98078 | M5: =J5-L5 -> 199.81581 | N5: =Q4 -> -1069.2349 | O5: =Cashflows!F5+Cashflows!I5+Cashflows!J5 -> 266.27369 | P5: =$B$6*IF(SUM($K$4:$K$43)=0,0,K5/SUM($K$4:$K$43)) -> 11.280592 | Q5: =N5*(1+Assumptions!$C$6+Assumptions!$C$25)+Cashflows!E5-O5 -> -878.19154 | R5: =R4-P5 -> 64.436546 | S5: =Q5+R5+M5 -> -613.93918 | T5: =S4+Cashflows!E5-O5+N5*(Assumptions!$C$6+Assumptions!$C$25)+H5+I5-L5-P5+U5-S5 -> 0 | U5: =MAX(0,-(G5+H5+I5)) -> 0
A6: Initial risk adjustment | B6: =B5*Assumptions!C8 -> 88.541413 | C6: AED | D6: Illustrative risk adjustment | F6: 3 | G6: =M5 -> 199.81581 | H6: =G6*(Assumptions!$C$6+Assumptions!$C$25) -> 6.9935532 | I6: 0 | J6: =MAX(0,G6+H6+I6) -> 206.80936 | K6: =Cashflows!B6*'Premium Calculation'!$B$9 -> 78954.428 | L6: =IF(SUM(K6:$K$43)=0,0,J6*K6/SUM(K6:$K$43)) -> 32.497299 | M6: =J6-L6 -> 174.31206 | N6: =Q5 -> -878.19154 | O6: =Cashflows!F6+Cashflows!I6+Cashflows!J6 -> 249.24126 | P6: =$B$6*IF(SUM($K$4:$K$43)=0,0,K6/SUM($K$4:$K$43)) -> 10.125333 | Q6: =N6*(1+Assumptions!$C$6+Assumptions!$C$25)+Cashflows!E6-O6 -> -714.09618 | R6: =R5-P6 -> 54.311212 | S6: =Q6+R6+M6 -> -485.47291 | T6: =S5+Cashflows!E6-O6+N6*(Assumptions!$C$6+Assumptions!$C$25)+H6+I6-L6-P6+U6-S6 -> 0 | U6: =MAX(0,-(G6+H6+I6)) -> 0
A7: Initial FCF | B7: =B5+B6-B4 -> -256.3087 | C7: AED | D7: Liability shown as positive | F7: 4 | G7: =M6 -> 174.31206 | H7: =G7*(Assumptions!$C$6+Assumptions!$C$25) -> 6.1009221 | I7: 0 | J7: =MAX(0,G7+H7+I7) -> 180.41298 | K7: =Cashflows!B7*'Premium Calculation'!$B$9 -> 72073.31 | L7: =IF(SUM(K7:$K$43)=0,0,J7*K7/SUM(K7:$K$43)) -> 30.703338 | M7: =J7-L7 -> 149.70964 | N7: =Q6 -> -714.09618 | O7: =Cashflows!F7+Cashflows!I7+Cashflows!J7 -> 237.3567 | P7: =$B$6*IF(SUM($K$4:$K$43)=0,0,K7/SUM($K$4:$K$43)) -> 9.2428799 | Q7: =N7*(1+Assumptions!$C$6+Assumptions!$C$25)+Cashflows!E7-O7 -> -571.07525 | R7: =R6-P7 -> 45.068332 | S7: =Q7+R7+M7 -> -376.29728 | T7: =S6+Cashflows!E7-O7+N7*(Assumptions!$C$6+Assumptions!$C$25)+H7+I7-L7-P7+U7-S7 -> 0 | U7: =MAX(0,-(G7+H7+I7)) -> 0
A8: Initial CSM | B8: =MAX(-B7,0) -> 256.3087 | C8: AED | D8: CSM eliminates gain at initial recognition | F8: 5 | G8: =M7 -> 149.70964 | H8: =G8*(Assumptions!$C$6+Assumptions!$C$25) -> 5.2398376 | I8: 0 | J8: =MAX(0,G8+H8+I8) -> 154.94948 | K8: =Cashflows!B8*'Premium Calculation'!$B$9 -> 66725.994 | L8: =IF(SUM(K8:$K$43)=0,0,J8*K8/SUM(K8:$K$43)) -> 29.420262 | M8: =J8-L8 -> 125.52922 | N8: =Q7 -> -571.07525 | O8: =Cashflows!F8+Cashflows!I8+Cashflows!J8 -> 229.33788 | P8: =$B$6*IF(SUM($K$4:$K$43)=0,0,K8/SUM($K$4:$K$43)) -> 8.5571252 | Q8: =N8*(1+Assumptions!$C$6+Assumptions!$C$25)+Cashflows!E8-O8 -> -445.10536 | R8: =R7-P8 -> 36.511207 | S8: =Q8+R8+M8 -> -283.06493 | T8: =S7+Cashflows!E8-O8+N8*(Assumptions!$C$6+Assumptions!$C$25)+H8+I8-L8-P8+U8-S8 -> 0 | U8: =MAX(0,-(G8+H8+I8)) -> 0
A9: Initial loss component | B9: =MAX(B7,0) -> 0 | C9: AED | D9: Loss recognised at initial measurement | F9: 6 | G9: =M8 -> 125.52922 | H9: =G9*(Assumptions!$C$6+Assumptions!$C$25) -> 4.3935227 | I9: 0 | J9: =MAX(0,G9+H9+I9) -> 129.92274 | K9: =Cashflows!B9*'Premium Calculation'!$B$9 -> 62509.819 | L9: =IF(SUM(K9:$K$43)=0,0,J9*K9/SUM(K9:$K$43)) -> 28.525947 | M9: =J9-L9 -> 101.3968 | N9: =Q8 -> -445.10536 | O9: =Cashflows!F9+Cashflows!I9+Cashflows!J9 -> 224.31264 | P9: =$B$6*IF(SUM($K$4:$K$43)=0,0,K9/SUM($K$4:$K$43)) -> 8.0164314 | Q9: =N9*(1+Assumptions!$C$6+Assumptions!$C$25)+Cashflows!E9-O9 -> -333.41484 | R9: =R8-P9 -> 28.494776 | S9: =Q9+R9+M9 -> -203.52327 | T9: =S8+Cashflows!E9-O9+N9*(Assumptions!$C$6+Assumptions!$C$25)+H9+I9-L9-P9+U9-S9 -> 0 | U9: =MAX(0,-(G9+H9+I9)) -> 0
A10: Onerous? | B10: =IF(B9>0,"YES","NO") -> NO | D10: Single illustrative group | F10: 7 | G10: =M9 -> 101.3968 | H10: =G10*(Assumptions!$C$6+Assumptions!$C$25) -> 3.5488879 | I10: 0 | J10: =MAX(0,G10+H10+I10) -> 104.94568 | K10: =Cashflows!B10*'Premium Calculation'!$B$9 -> 59144.188 | L10: =IF(SUM(K10:$K$43)=0,0,J10*K10/SUM(K10:$K$43)) -> 27.934715 | M10: =J10-L10 -> 77.010969 | N10: =Q9 -> -333.41484 | O10: =Cashflows!F10+Cashflows!I10+Cashflows!J10 -> 221.67378 | P10: =$B$6*IF(SUM($K$4:$K$43)=0,0,K10/SUM($K$4:$K$43)) -> 7.5848136 | Q10: =N10*(1+Assumptions!$C$6+Assumptions!$C$25)+Cashflows!E10-O10 -> -234.10605 | R10: =R9-P10 -> 20.909962 | S10: =Q10+R10+M10 -> -136.18512 | T10: =S9+Cashflows!E10-O10+N10*(Assumptions!$C$6+Assumptions!$C$25)+H10+I10-L10-P10+U10-S10 -> 0 | U10: =MAX(0,-(G10+H10+I10)) -> 0
A11: Insurance revenue proxy | B11: =O4+L4+P4 -> 1326.0048 | C11: AED | D11: Expected outgo plus CSM and RA release | F11: 8 | G11: =M10 -> 77.010969 | H11: =G11*(Assumptions!$C$6+Assumptions!$C$25) -> 2.6953839 | I11: 0 | J11: =MAX(0,G11+H11+I11) -> 79.706353 | K11: =Cashflows!B11*'Premium Calculation'!$B$9 -> 56428.871 | L11: =IF(SUM(K11:$K$43)=0,0,J11*K11/SUM(K11:$K$43)) -> 27.585057 | M11: =J11-L11 -> 52.121296 | N11: =Q10 -> -234.10605 | O11: =Cashflows!F11+Cashflows!I11+Cashflows!J11 -> 220.99039 | P11: =$B$6*IF(SUM($K$4:$K$43)=0,0,K11/SUM($K$4:$K$43)) -> 7.2365938 | Q11: =N11*(1+Assumptions!$C$6+Assumptions!$C$25)+Cashflows!E11-O11 -> -145.91015 | R11: =R10-P11 -> 13.673368 | S11: =Q11+R11+M11 -> -80.115488 | T11: =S10+Cashflows!E11-O11+N11*(Assumptions!$C$6+Assumptions!$C$25)+H11+I11-L11-P11+U11-S11 -> 0 | U11: =MAX(0,-(G11+H11+I11)) -> 0
A12: Service expenses proxy | B12: =O4 -> 1274.7576 | C12: AED | D12: Actual experience assumed equal to expected | F12: 9 | G12: =M11 -> 52.121296 | H12: =G12*(Assumptions!$C$6+Assumptions!$C$25) -> 1.8242453 | I12: 0 | J12: =MAX(0,G12+H12+I12) -> 53.945541 | K12: =Cashflows!B12*'Premium Calculation'!$B$9 -> 54217.944 | L12: =IF(SUM(K12:$K$43)=0,0,J12*K12/SUM(K12:$K$43)) -> 27.431902 | M12: =J12-L12 -> 26.513639 | N12: =Q11 -> -145.91015 | O12: =Cashflows!F12+Cashflows!I12+Cashflows!J12 -> 221.95191 | P12: =$B$6*IF(SUM($K$4:$K$43)=0,0,K12/SUM($K$4:$K$43)) -> 6.9530585 | Q12: =N12*(1+Assumptions!$C$6+Assumptions!$C$25)+Cashflows!E12-O12 -> -68.024118 | R12: =R11-P12 -> 6.7203099 | S12: =Q12+R12+M12 -> -34.790169 | T12: =S11+Cashflows!E12-O12+N12*(Assumptions!$C$6+Assumptions!$C$25)+H12+I12-L12-P12+U12-S12 -> 0 | U12: =MAX(0,-(G12+H12+I12)) -> 0
A13: Insurance service result | B13: =B11-B12 -> 51.24717 | C13: AED | D13: CSM and RA release | F13: 10 | G13: =M12 -> 26.513639 | H13: =G13*(Assumptions!$C$6+Assumptions!$C$25) -> 0.92797736 | I13: 0 | J13: =MAX(0,G13+H13+I13) -> 27.441616 | K13: =Cashflows!B13*'Premium Calculation'!$B$9 -> 52403.037 | L13: =IF(SUM(K13:$K$43)=0,0,J13*K13/SUM(K13:$K$43)) -> 27.441616 | M13: =J13-L13 -> 0 | N13: =Q12 -> -68.024118 | O13: =Cashflows!F13+Cashflows!I13+Cashflows!J13 -> 224.33204 | P13: =$B$6*IF(SUM($K$4:$K$43)=0,0,K13/SUM($K$4:$K$43)) -> 6.7203099 | Q13: =N13*(1+Assumptions!$C$6+Assumptions!$C$25)+Cashflows!E13-O13 -> 1.3073986e-12 | R13: =R12-P13 -> 8.8817842e-15 | S13: =Q13+R13+M13 -> 1.3162804e-12 | T13: =S12+Cashflows!E13-O13+N13*(Assumptions!$C$6+Assumptions!$C$25)+H13+I13-L13-P13+U13-S13 -> 0 | U13: =MAX(0,-(G13+H13+I13)) -> 0
A14: Finance expense proxy | B14: =N4*(Assumptions!C6+Assumptions!C25)+H4 -> -3.0989495 | C14: AED | D14: Discount unwind and CSM accretion | F14: 11 | G14: =M13 -> 0 | H14: =G14*(Assumptions!$C$6+Assumptions!$C$25) -> 0 | I14: 0 | J14: =MAX(0,G14+H14+I14) -> 0 | K14: =Cashflows!B14*'Premium Calculation'!$B$9 -> 0 | L14: =IF(SUM(K14:$K$43)=0,0,J14*K14/SUM(K14:$K$43)) -> 0 | M14: =J14-L14 -> 0 | N14: =Q13 -> 1.3073986e-12 | O14: =Cashflows!F14+Cashflows!I14+Cashflows!J14 -> 0 | P14: =$B$6*IF(SUM($K$4:$K$43)=0,0,K14/SUM($K$4:$K$43)) -> 0 | Q14: =N14*(1+Assumptions!$C$6+Assumptions!$C$25)+Cashflows!E14-O14 -> 1.3531576e-12 | R14: =R13-P14 -> 8.8817842e-15 | S14: =Q14+R14+M14 -> 1.3620394e-12 | T14: =S13+Cashflows!E14-O14+N14*(Assumptions!$C$6+Assumptions!$C$25)+H14+I14-L14-P14+U14-S14 -> 0 | U14: =MAX(0,-(G14+H14+I14)) -> 0
A15: Opening LRC | B15: =B7+B8 -> 0 | C15: AED | D15: BEL + RA + CSM | F15: 12 | G15: =M14 -> 0 | H15: =G15*(Assumptions!$C$6+Assumptions!$C$25) -> 0 | I15: 0 | J15: =MAX(0,G15+H15+I15) -> 0 | K15: =Cashflows!B15*'Premium Calculation'!$B$9 -> 0 | L15: =IF(SUM(K15:$K$43)=0,0,J15*K15/SUM(K15:$K$43)) -> 0 | M15: =J15-L15 -> 0 | N15: =Q14 -> 1.3531576e-12 | O15: =Cashflows!F15+Cashflows!I15+Cashflows!J15 -> 0 | P15: =$B$6*IF(SUM($K$4:$K$43)=0,0,K15/SUM($K$4:$K$43)) -> 0 | Q15: =N15*(1+Assumptions!$C$6+Assumptions!$C$25)+Cashflows!E15-O15 -> 1.4005181e-12 | R15: =R14-P15 -> 8.8817842e-15 | S15: =Q15+R15+M15 -> 1.4093999e-12 | T15: =S14+Cashflows!E15-O15+N15*(Assumptions!$C$6+Assumptions!$C$25)+H15+I15-L15-P15+U15-S15 -> 0 | U15: =MAX(0,-(G15+H15+I15)) -> 0
A16: Closing LRC | B16: =Q4+R4+M4 -> -766.66115 | C16: AED | D16: BEL + remaining RA + CSM | F16: 13 | G16: =M15 -> 0 | H16: =G16*(Assumptions!$C$6+Assumptions!$C$25) -> 0 | I16: 0 | J16: =MAX(0,G16+H16+I16) -> 0 | K16: =Cashflows!B16*'Premium Calculation'!$B$9 -> 0 | L16: =IF(SUM(K16:$K$43)=0,0,J16*K16/SUM(K16:$K$43)) -> 0 | M16: =J16-L16 -> 0 | N16: =Q15 -> 1.4005181e-12 | O16: =Cashflows!F16+Cashflows!I16+Cashflows!J16 -> 0 | P16: =$B$6*IF(SUM($K$4:$K$43)=0,0,K16/SUM($K$4:$K$43)) -> 0 | Q16: =N16*(1+Assumptions!$C$6+Assumptions!$C$25)+Cashflows!E16-O16 -> 1.4495362e-12 | R16: =R15-P16 -> 8.8817842e-15 | S16: =Q16+R16+M16 -> 1.458418e-12 | T16: =S15+Cashflows!E16-O16+N16*(Assumptions!$C$6+Assumptions!$C$25)+H16+I16-L16-P16+U16-S16 -> 0 | U16: =MAX(0,-(G16+H16+I16)) -> 0
A17: Closing LIC | B17: 0 | C17: AED | D17: No outstanding claims assumed | F17: 14 | G17: =M16 -> 0 | H17: =G17*(Assumptions!$C$6+Assumptions!$C$25) -> 0 | I17: 0 | J17: =MAX(0,G17+H17+I17) -> 0 | K17: =Cashflows!B17*'Premium Calculation'!$B$9 -> 0 | L17: =IF(SUM(K17:$K$43)=0,0,J17*K17/SUM(K17:$K$43)) -> 0 | M17: =J17-L17 -> 0 | N17: =Q16 -> 1.4495362e-12 | O17: =Cashflows!F17+Cashflows!I17+Cashflows!J17 -> 0 | P17: =$B$6*IF(SUM($K$4:$K$43)=0,0,K17/SUM($K$4:$K$43)) -> 0 | Q17: =N17*(1+Assumptions!$C$6+Assumptions!$C$25)+Cashflows!E17-O17 -> 1.50027e-12 | R17: =R16-P17 -> 8.8817842e-15 | S17: =Q17+R17+M17 -> 1.5091518e-12 | T17: =S16+Cashflows!E17-O17+N17*(Assumptions!$C$6+Assumptions!$C$25)+H17+I17-L17-P17+U17-S17 -> 0 | U17: =MAX(0,-(G17+H17+I17)) -> 0
A18: LRC roll-forward residual | B18: =B15+Cashflows!E4-O4+B14+I4+U4-L4-P4-B16 -> 0 | C18: AED | F18: 15 | G18: =M17 -> 0 | H18: =G18*(Assumptions!$C$6+Assumptions!$C$25) -> 0 | I18: 0 | J18: =MAX(0,G18+H18+I18) -> 0 | K18: =Cashflows!B18*'Premium Calculation'!$B$9 -> 0 | L18: =IF(SUM(K18:$K$43)=0,0,J18*K18/SUM(K18:$K$43)) -> 0 | M18: =J18-L18 -> 0 | N18: =Q17 -> 1.50027e-12 | O18: =Cashflows!F18+Cashflows!I18+Cashflows!J18 -> 0 | P18: =$B$6*IF(SUM($K$4:$K$43)=0,0,K18/SUM($K$4:$K$43)) -> 0 | Q18: =N18*(1+Assumptions!$C$6+Assumptions!$C$25)+Cashflows!E18-O18 -> 1.5527795e-12 | R18: =R17-P18 -> 8.8817842e-15 | S18: =Q18+R18+M18 -> 1.5616612e-12 | T18: =S17+Cashflows!E18-O18+N18*(Assumptions!$C$6+Assumptions!$C$25)+H18+I18-L18-P18+U18-S18 -> 0 | U18: =MAX(0,-(G18+H18+I18)) -> 0
A19: CSM release reconciliation | B19: =B8+SUM(H4:H43)+SUM(I4:I43)-SUM(L4:L43)-M43 -> 1.1368684e-13 | C19: AED | D19: Reconciliation check | F19: 16 | G19: =M18 -> 0 | H19: =G19*(Assumptions!$C$6+Assumptions!$C$25) -> 0 | I19: 0 | J19: =MAX(0,G19+H19+I19) -> 0 | K19: =Cashflows!B19*'Premium Calculation'!$B$9 -> 0 | L19: =IF(SUM(K19:$K$43)=0,0,J19*K19/SUM(K19:$K$43)) -> 0 | M19: =J19-L19 -> 0 | N19: =Q18 -> 1.5527795e-12 | O19: =Cashflows!F19+Cashflows!I19+Cashflows!J19 -> 0 | P19: =$B$6*IF(SUM($K$4:$K$43)=0,0,K19/SUM($K$4:$K$43)) -> 0 | Q19: =N19*(1+Assumptions!$C$6+Assumptions!$C$25)+Cashflows!E19-O19 -> 1.6071267e-12 | R19: =R18-P19 -> 8.8817842e-15 | S19: =Q19+R19+M19 -> 1.6160085e-12 | T19: =S18+Cashflows!E19-O19+N19*(Assumptions!$C$6+Assumptions!$C$25)+H19+I19-L19-P19+U19-S19 -> 0 | U19: =MAX(0,-(G19+H19+I19)) -> 0
F20: 17 | G20: =M19 -> 0 | H20: =G20*(Assumptions!$C$6+Assumptions!$C$25) -> 0 | I20: 0 | J20: =MAX(0,G20+H20+I20) -> 0 | K20: =Cashflows!B20*'Premium Calculation'!$B$9 -> 0 | L20: =IF(SUM(K20:$K$43)=0,0,J20*K20/SUM(K20:$K$43)) -> 0 | M20: =J20-L20 -> 0 | N20: =Q19 -> 1.6071267e-12 | O20: =Cashflows!F20+Cashflows!I20+Cashflows!J20 -> 0 | P20: =$B$6*IF(SUM($K$4:$K$43)=0,0,K20/SUM($K$4:$K$43)) -> 0 | Q20: =N20*(1+Assumptions!$C$6+Assumptions!$C$25)+Cashflows!E20-O20 -> 1.6633762e-12 | R20: =R19-P20 -> 8.8817842e-15 | S20: =Q20+R20+M20 -> 1.672258e-12 | T20: =S19+Cashflows!E20-O20+N20*(Assumptions!$C$6+Assumptions!$C$25)+H20+I20-L20-P20+U20-S20 -> 0 | U20: =MAX(0,-(G20+H20+I20)) -> 0
F21: 18 | G21: =M20 -> 0 | H21: =G21*(Assumptions!$C$6+Assumptions!$C$25) -> 0 | I21: 0 | J21: =MAX(0,G21+H21+I21) -> 0 | K21: =Cashflows!B21*'Premium Calculation'!$B$9 -> 0 | L21: =IF(SUM(K21:$K$43)=0,0,J21*K21/SUM(K21:$K$43)) -> 0 | M21: =J21-L21 -> 0 | N21: =Q20 -> 1.6633762e-12 | O21: =Cashflows!F21+Cashflows!I21+Cashflows!J21 -> 0 | P21: =$B$6*IF(SUM($K$4:$K$43)=0,0,K21/SUM($K$4:$K$43)) -> 0 | Q21: =N21*(1+Assumptions!$C$6+Assumptions!$C$25)+Cashflows!E21-O21 -> 1.7215943e-12 | R21: =R20-P21 -> 8.8817842e-15 | S21: =Q21+R21+M21 -> 1.7304761e-12 | T21: =S20+Cashflows!E21-O21+N21*(Assumptions!$C$6+Assumptions!$C$25)+H21+I21-L21-P21+U21-S21 -> 0 | U21: =MAX(0,-(G21+H21+I21)) -> 0
A22: This section covers gross contracts only. Reinsurance-held contracts and detailed loss-component allocation are outside the scope of the model. | F22: 19 | G22: =M21 -> 0 | H22: =G22*(Assumptions!$C$6+Assumptions!$C$25) -> 0 | I22: 0 | J22: =MAX(0,G22+H22+I22) -> 0 | K22: =Cashflows!B22*'Premium Calculation'!$B$9 -> 0 | L22: =IF(SUM(K22:$K$43)=0,0,J22*K22/SUM(K22:$K$43)) -> 0 | M22: =J22-L22 -> 0 | N22: =Q21 -> 1.7215943e-12 | O22: =Cashflows!F22+Cashflows!I22+Cashflows!J22 -> 0 | P22: =$B$6*IF(SUM($K$4:$K$43)=0,0,K22/SUM($K$4:$K$43)) -> 0 | Q22: =N22*(1+Assumptions!$C$6+Assumptions!$C$25)+Cashflows!E22-O22 -> 1.7818501e-12 | R22: =R21-P22 -> 8.8817842e-15 | S22: =Q22+R22+M22 -> 1.7907319e-12 | T22: =S21+Cashflows!E22-O22+N22*(Assumptions!$C$6+Assumptions!$C$25)+H22+I22-L22-P22+U22-S22 -> 0 | U22: =MAX(0,-(G22+H22+I22)) -> 0
F23: 20 | G23: =M22 -> 0 | H23: =G23*(Assumptions!$C$6+Assumptions!$C$25) -> 0 | I23: 0 | J23: =MAX(0,G23+H23+I23) -> 0 | K23: =Cashflows!B23*'Premium Calculation'!$B$9 -> 0 | L23: =IF(SUM(K23:$K$43)=0,0,J23*K23/SUM(K23:$K$43)) -> 0 | M23: =J23-L23 -> 0 | N23: =Q22 -> 1.7818501e-12 | O23: =Cashflows!F23+Cashflows!I23+Cashflows!J23 -> 0 | P23: =$B$6*IF(SUM($K$4:$K$43)=0,0,K23/SUM($K$4:$K$43)) -> 0 | Q23: =N23*(1+Assumptions!$C$6+Assumptions!$C$25)+Cashflows!E23-O23 -> 1.8442149e-12 | R23: =R22-P23 -> 8.8817842e-15 | S23: =Q23+R23+M23 -> 1.8530967e-12 | T23: =S22+Cashflows!E23-O23+N23*(Assumptions!$C$6+Assumptions!$C$25)+H23+I23-L23-P23+U23-S23 -> 0 | U23: =MAX(0,-(G23+H23+I23)) -> 0
F24: 21 | G24: =M23 -> 0 | H24: =G24*(Assumptions!$C$6+Assumptions!$C$25) -> 0 | I24: 0 | J24: =MAX(0,G24+H24+I24) -> 0 | K24: =Cashflows!B24*'Premium Calculation'!$B$9 -> 0 | L24: =IF(SUM(K24:$K$43)=0,0,J24*K24/SUM(K24:$K$43)) -> 0 | M24: =J24-L24 -> 0 | N24: =Q23 -> 1.8442149e-12 | O24: =Cashflows!F24+Cashflows!I24+Cashflows!J24 -> 0 | P24: =$B$6*IF(SUM($K$4:$K$43)=0,0,K24/SUM($K$4:$K$43)) -> 0 | Q24: =N24*(1+Assumptions!$C$6+Assumptions!$C$25)+Cashflows!E24-O24 -> 1.9087624e-12 | R24: =R23-P24 -> 8.8817842e-15 | S24: =Q24+R24+M24 -> 1.9176442e-12 | T24: =S23+Cashflows!E24-O24+N24*(Assumptions!$C$6+Assumptions!$C$25)+H24+I24-L24-P24+U24-S24 -> 0 | U24: =MAX(0,-(G24+H24+I24)) -> 0
F25: 22 | G25: =M24 -> 0 | H25: =G25*(Assumptions!$C$6+Assumptions!$C$25) -> 0 | I25: 0 | J25: =MAX(0,G25+H25+I25) -> 0 | K25: =Cashflows!B25*'Premium Calculation'!$B$9 -> 0 | L25: =IF(SUM(K25:$K$43)=0,0,J25*K25/SUM(K25:$K$43)) -> 0 | M25: =J25-L25 -> 0 | N25: =Q24 -> 1.9087624e-12 | O25: =Cashflows!F25+Cashflows!I25+Cashflows!J25 -> 0 | P25: =$B$6*IF(SUM($K$4:$K$43)=0,0,K25/SUM($K$4:$K$43)) -> 0 | Q25: =N25*(1+Assumptions!$C$6+Assumptions!$C$25)+Cashflows!E25-O25 -> 1.9755691e-12 | R25: =R24-P25 -> 8.8817842e-15 | S25: =Q25+R25+M25 -> 1.9844509e-12 | T25: =S24+Cashflows!E25-O25+N25*(Assumptions!$C$6+Assumptions!$C$25)+H25+I25-L25-P25+U25-S25 -> 0 | U25: =MAX(0,-(G25+H25+I25)) -> 0
F26: 23 | G26: =M25 -> 0 | H26: =G26*(Assumptions!$C$6+Assumptions!$C$25) -> 0 | I26: 0 | J26: =MAX(0,G26+H26+I26) -> 0 | K26: =Cashflows!B26*'Premium Calculation'!$B$9 -> 0 | L26: =IF(SUM(K26:$K$43)=0,0,J26*K26/SUM(K26:$K$43)) -> 0 | M26: =J26-L26 -> 0 | N26: =Q25 -> 1.9755691e-12 | O26: =Cashflows!F26+Cashflows!I26+Cashflows!J26 -> 0 | P26: =$B$6*IF(SUM($K$4:$K$43)=0,0,K26/SUM($K$4:$K$43)) -> 0 | Q26: =N26*(1+Assumptions!$C$6+Assumptions!$C$25)+Cashflows!E26-O26 -> 2.044714e-12 | R26: =R25-P26 -> 8.8817842e-15 | S26: =Q26+R26+M26 -> 2.0535958e-12 | T26: =S25+Cashflows!E26-O26+N26*(Assumptions!$C$6+Assumptions!$C$25)+H26+I26-L26-P26+U26-S26 -> 0 | U26: =MAX(0,-(G26+H26+I26)) -> 0
F27: 24 | G27: =M26 -> 0 | H27: =G27*(Assumptions!$C$6+Assumptions!$C$25) -> 0 | I27: 0 | J27: =MAX(0,G27+H27+I27) -> 0 | K27: =Cashflows!B27*'Premium Calculation'!$B$9 -> 0 | L27: =IF(SUM(K27:$K$43)=0,0,J27*K27/SUM(K27:$K$43)) -> 0 | M27: =J27-L27 -> 0 | N27: =Q26 -> 2.044714e-12 | O27: =Cashflows!F27+Cashflows!I27+Cashflows!J27 -> 0 | P27: =$B$6*IF(SUM($K$4:$K$43)=0,0,K27/SUM($K$4:$K$43)) -> 0 | Q27: =N27*(1+Assumptions!$C$6+Assumptions!$C$25)+Cashflows!E27-O27 -> 2.116279e-12 | R27: =R26-P27 -> 8.8817842e-15 | S27: =Q27+R27+M27 -> 2.1251608e-12 | T27: =S26+Cashflows!E27-O27+N27*(Assumptions!$C$6+Assumptions!$C$25)+H27+I27-L27-P27+U27-S27 -> 0 | U27: =MAX(0,-(G27+H27+I27)) -> 0
F28: 25 | G28: =M27 -> 0 | H28: =G28*(Assumptions!$C$6+Assumptions!$C$25) -> 0 | I28: 0 | J28: =MAX(0,G28+H28+I28) -> 0 | K28: =Cashflows!B28*'Premium Calculation'!$B$9 -> 0 | L28: =IF(SUM(K28:$K$43)=0,0,J28*K28/SUM(K28:$K$43)) -> 0 | M28: =J28-L28 -> 0 | N28: =Q27 -> 2.116279e-12 | O28: =Cashflows!F28+Cashflows!I28+Cashflows!J28 -> 0 | P28: =$B$6*IF(SUM($K$4:$K$43)=0,0,K28/SUM($K$4:$K$43)) -> 0 | Q28: =N28*(1+Assumptions!$C$6+Assumptions!$C$25)+Cashflows!E28-O28 -> 2.1903488e-12 | R28: =R27-P28 -> 8.8817842e-15 | S28: =Q28+R28+M28 -> 2.1992306e-12 | T28: =S27+Cashflows!E28-O28+N28*(Assumptions!$C$6+Assumptions!$C$25)+H28+I28-L28-P28+U28-S28 -> 0 | U28: =MAX(0,-(G28+H28+I28)) -> 0
F29: 26 | G29: =M28 -> 0 | H29: =G29*(Assumptions!$C$6+Assumptions!$C$25) -> 0 | I29: 0 | J29: =MAX(0,G29+H29+I29) -> 0 | K29: =Cashflows!B29*'Premium Calculation'!$B$9 -> 0 | L29: =IF(SUM(K29:$K$43)=0,0,J29*K29/SUM(K29:$K$43)) -> 0 | M29: =J29-L29 -> 0 | N29: =Q28 -> 2.1903488e-12 | O29: =Cashflows!F29+Cashflows!I29+Cashflows!J29 -> 0 | P29: =$B$6*IF(SUM($K$4:$K$43)=0,0,K29/SUM($K$4:$K$43)) -> 0 | Q29: =N29*(1+Assumptions!$C$6+Assumptions!$C$25)+Cashflows!E29-O29 -> 2.267011e-12 | R29: =R28-P29 -> 8.8817842e-15 | S29: =Q29+R29+M29 -> 2.2758928e-12 | T29: =S28+Cashflows!E29-O29+N29*(Assumptions!$C$6+Assumptions!$C$25)+H29+I29-L29-P29+U29-S29 -> 0 | U29: =MAX(0,-(G29+H29+I29)) -> 0
F30: 27 | G30: =M29 -> 0 | H30: =G30*(Assumptions!$C$6+Assumptions!$C$25) -> 0 | I30: 0 | J30: =MAX(0,G30+H30+I30) -> 0 | K30: =Cashflows!B30*'Premium Calculation'!$B$9 -> 0 | L30: =IF(SUM(K30:$K$43)=0,0,J30*K30/SUM(K30:$K$43)) -> 0 | M30: =J30-L30 -> 0 | N30: =Q29 -> 2.267011e-12 | O30: =Cashflows!F30+Cashflows!I30+Cashflows!J30 -> 0 | P30: =$B$6*IF(SUM($K$4:$K$43)=0,0,K30/SUM($K$4:$K$43)) -> 0 | Q30: =N30*(1+Assumptions!$C$6+Assumptions!$C$25)+Cashflows!E30-O30 -> 2.3463564e-12 | R30: =R29-P30 -> 8.8817842e-15 | S30: =Q30+R30+M30 -> 2.3552381e-12 | T30: =S29+Cashflows!E30-O30+N30*(Assumptions!$C$6+Assumptions!$C$25)+H30+I30-L30-P30+U30-S30 -> 0 | U30: =MAX(0,-(G30+H30+I30)) -> 0
F31: 28 | G31: =M30 -> 0 | H31: =G31*(Assumptions!$C$6+Assumptions!$C$25) -> 0 | I31: 0 | J31: =MAX(0,G31+H31+I31) -> 0 | K31: =Cashflows!B31*'Premium Calculation'!$B$9 -> 0 | L31: =IF(SUM(K31:$K$43)=0,0,J31*K31/SUM(K31:$K$43)) -> 0 | M31: =J31-L31 -> 0 | N31: =Q30 -> 2.3463564e-12 | O31: =Cashflows!F31+Cashflows!I31+Cashflows!J31 -> 0 | P31: =$B$6*IF(SUM($K$4:$K$43)=0,0,K31/SUM($K$4:$K$43)) -> 0 | Q31: =N31*(1+Assumptions!$C$6+Assumptions!$C$25)+Cashflows!E31-O31 -> 2.4284788e-12 | R31: =R30-P31 -> 8.8817842e-15 | S31: =Q31+R31+M31 -> 2.4373606e-12 | T31: =S30+Cashflows!E31-O31+N31*(Assumptions!$C$6+Assumptions!$C$25)+H31+I31-L31-P31+U31-S31 -> 0 | U31: =MAX(0,-(G31+H31+I31)) -> 0
F32: 29 | G32: =M31 -> 0 | H32: =G32*(Assumptions!$C$6+Assumptions!$C$25) -> 0 | I32: 0 | J32: =MAX(0,G32+H32+I32) -> 0 | K32: =Cashflows!B32*'Premium Calculation'!$B$9 -> 0 | L32: =IF(SUM(K32:$K$43)=0,0,J32*K32/SUM(K32:$K$43)) -> 0 | M32: =J32-L32 -> 0 | N32: =Q31 -> 2.4284788e-12 | O32: =Cashflows!F32+Cashflows!I32+Cashflows!J32 -> 0 | P32: =$B$6*IF(SUM($K$4:$K$43)=0,0,K32/SUM($K$4:$K$43)) -> 0 | Q32: =N32*(1+Assumptions!$C$6+Assumptions!$C$25)+Cashflows!E32-O32 -> 2.5134756e-12 | R32: =R31-P32 -> 8.8817842e-15 | S32: =Q32+R32+M32 -> 2.5223574e-12 | T32: =S31+Cashflows!E32-O32+N32*(Assumptions!$C$6+Assumptions!$C$25)+H32+I32-L32-P32+U32-S32 -> 0 | U32: =MAX(0,-(G32+H32+I32)) -> 0
F33: 30 | G33: =M32 -> 0 | H33: =G33*(Assumptions!$C$6+Assumptions!$C$25) -> 0 | I33: 0 | J33: =MAX(0,G33+H33+I33) -> 0 | K33: =Cashflows!B33*'Premium Calculation'!$B$9 -> 0 | L33: =IF(SUM(K33:$K$43)=0,0,J33*K33/SUM(K33:$K$43)) -> 0 | M33: =J33-L33 -> 0 | N33: =Q32 -> 2.5134756e-12 | O33: =Cashflows!F33+Cashflows!I33+Cashflows!J33 -> 0 | P33: =$B$6*IF(SUM($K$4:$K$43)=0,0,K33/SUM($K$4:$K$43)) -> 0 | Q33: =N33*(1+Assumptions!$C$6+Assumptions!$C$25)+Cashflows!E33-O33 -> 2.6014472e-12 | R33: =R32-P33 -> 8.8817842e-15 | S33: =Q33+R33+M33 -> 2.610329e-12 | T33: =S32+Cashflows!E33-O33+N33*(Assumptions!$C$6+Assumptions!$C$25)+H33+I33-L33-P33+U33-S33 -> 0 | U33: =MAX(0,-(G33+H33+I33)) -> 0
F34: 31 | G34: =M33 -> 0 | H34: =G34*(Assumptions!$C$6+Assumptions!$C$25) -> 0 | I34: 0 | J34: =MAX(0,G34+H34+I34) -> 0 | K34: =Cashflows!B34*'Premium Calculation'!$B$9 -> 0 | L34: =IF(SUM(K34:$K$43)=0,0,J34*K34/SUM(K34:$K$43)) -> 0 | M34: =J34-L34 -> 0 | N34: =Q33 -> 2.6014472e-12 | O34: =Cashflows!F34+Cashflows!I34+Cashflows!J34 -> 0 | P34: =$B$6*IF(SUM($K$4:$K$43)=0,0,K34/SUM($K$4:$K$43)) -> 0 | Q34: =N34*(1+Assumptions!$C$6+Assumptions!$C$25)+Cashflows!E34-O34 -> 2.6924979e-12 | R34: =R33-P34 -> 8.8817842e-15 | S34: =Q34+R34+M34 -> 2.7013797e-12 | T34: =S33+Cashflows!E34-O34+N34*(Assumptions!$C$6+Assumptions!$C$25)+H34+I34-L34-P34+U34-S34 -> 0 | U34: =MAX(0,-(G34+H34+I34)) -> 0
... F43: 40 | G43: =M42 -> 0 | H43: =G43*(Assumptions!$C$6+Assumptions!$C$25) -> 0 | I43: 0 | J43: =MAX(0,G43+H43+I43) -> 0 | K43: =Cashflows!B43*'Premium Calculation'!$B$9 -> 0 | L43: =IF(SUM(K43:$K$43)=0,0,J43*K43/SUM(K43:$K$43)) -> 0 | M43: =J43-L43 -> 0 | N43: =Q42 -> 3.5455056e-12 | O43: =Cashflows!F43+Cashflows!I43+Cashflows!J43 -> 0 | P43: =$B$6*IF(SUM($K$4:$K$43)=0,0,K43/SUM($K$4:$K$43)) -> 0 | Q43: =N43*(1+Assumptions!$C$6+Assumptions!$C$25)+Cashflows!E43-O43 -> 3.6695983e-12 | R43: =R42-P43 -> 8.8817842e-15 | S43: =Q43+R43+M43 -> 3.67848e-12 | T43: =S42+Cashflows!E43-O43+N43*(Assumptions!$C$6+Assumptions!$C$25)+H43+I43-L43-P43+U43-S43 -> 0 | U43: =MAX(0,-(G43+H43+I43)) -> 0

Sheet Unit-Linked
A1: Unit-Linked
A3: Assumption | B3: Value | C3: Unit | D3: Source | F3: Year | G3: Opening Fund | H3: Allocated Premium | I3: Fund Growth | J3: Fund Charge | K3: Policy Charge | L3: Closing Fund | M3: Death benefit | N3: Surrender benefit | O3: Fund check
A4: Annual premium | B4: 12000 | C4: AED | D4: Input | F4: 1 | G4: =$B$11 -> 0 | H4: =IF(F4<=$B$5,$B$4*$B$7,0) -> 11400 | I4: =IF(F4<=$B$5,(G4+H4)*$B$6,0) -> 285 | J4: =IF(F4<=$B$5,(G4+H4+I4)*$B$8,0) -> 146.0625 | K4: =IF(F4<=$B$5,MIN($B$9,MAX(0,G4+H4+I4-J4)),0) -> 600 | L4: =G4+H4+I4-J4-K4 -> 10938.938 | M4: =IF(F4<=$B$5,L4*(1+$B$10),0) -> 11485.884 | N4: =IF(F4<=$B$5,L4,0) -> 10938.938 | O4: =G4+H4+I4-J4-K4-L4 -> 0
A5: Projection term | B5: 20 | C5: years | D5: Input | F5: 2 | G5: =L4 -> 10938.938 | H5: =IF(F5<=$B$5,$B$4*$B$7,0) -> 11400 | I5: =IF(F5<=$B$5,(G5+H5)*$B$6,0) -> 558.47344 | J5: =IF(F5<=$B$5,(G5+H5+I5)*$B$8,0) -> 286.21764 | K5: =IF(F5<=$B$5,MIN($B$9,MAX(0,G5+H5+I5-J5)),0) -> 600 | L5: =G5+H5+I5-J5-K5 -> 22011.193 | M5: =IF(F5<=$B$5,L5*(1+$B$10),0) -> 23111.753 | N5: =IF(F5<=$B$5,L5,0) -> 22011.193 | O5: =G5+H5+I5-J5-K5-L5 -> 0
A6: Fund return | B6: =Assumptions!C7+Assumptions!C26 -> 0.025 | C6: % | D6: Illustrative Assumptions | F6: 3 | G6: =L5 -> 22011.193 | H6: =IF(F6<=$B$5,$B$4*$B$7,0) -> 11400 | I6: =IF(F6<=$B$5,(G6+H6)*$B$6,0) -> 835.27983 | J6: =IF(F6<=$B$5,(G6+H6+I6)*$B$8,0) -> 428.08091 | K6: =IF(F6<=$B$5,MIN($B$9,MAX(0,G6+H6+I6-J6)),0) -> 600 | L6: =G6+H6+I6-J6-K6 -> 33218.392 | M6: =IF(F6<=$B$5,L6*(1+$B$10),0) -> 34879.312 | N6: =IF(F6<=$B$5,L6,0) -> 33218.392 | O6: =G6+H6+I6-J6-K6-L6 -> 0
A7: Premium allocation | B7: =Assumptions!$C$17 -> 0.95 | C7: % | D7: Assumptions sheet | F7: 4 | G7: =L6 -> 33218.392 | H7: =IF(F7<=$B$5,$B$4*$B$7,0) -> 11400 | I7: =IF(F7<=$B$5,(G7+H7)*$B$6,0) -> 1115.4598 | J7: =IF(F7<=$B$5,(G7+H7+I7)*$B$8,0) -> 571.67315 | K7: =IF(F7<=$B$5,MIN($B$9,MAX(0,G7+H7+I7-J7)),0) -> 600 | L7: =G7+H7+I7-J7-K7 -> 44562.179 | M7: =IF(F7<=$B$5,L7*(1+$B$10),0) -> 46790.288 | N7: =IF(F7<=$B$5,L7,0) -> 44562.179 | O7: =G7+H7+I7-J7-K7-L7 -> 0
A8: Fund management charge | B8: =Assumptions!$C$18 -> 0.0125 | C8: % p.a. | D8: Assumptions sheet | F8: 5 | G8: =L7 -> 44562.179 | H8: =IF(F8<=$B$5,$B$4*$B$7,0) -> 11400 | I8: =IF(F8<=$B$5,(G8+H8)*$B$6,0) -> 1399.0545 | J8: =IF(F8<=$B$5,(G8+H8+I8)*$B$8,0) -> 717.01542 | K8: =IF(F8<=$B$5,MIN($B$9,MAX(0,G8+H8+I8-J8)),0) -> 600 | L8: =G8+H8+I8-J8-K8 -> 56044.218 | M8: =IF(F8<=$B$5,L8*(1+$B$10),0) -> 58846.429 | N8: =IF(F8<=$B$5,L8,0) -> 56044.218 | O8: =G8+H8+I8-J8-K8-L8 -> 0
A9: Policy charge | B9: =Assumptions!$C$19 -> 600 | C9: AED p.a. | D9: Assumptions sheet | F9: 6 | G9: =L8 -> 56044.218 | H9: =IF(F9<=$B$5,$B$4*$B$7,0) -> 11400 | I9: =IF(F9<=$B$5,(G9+H9)*$B$6,0) -> 1686.1054 | J9: =IF(F9<=$B$5,(G9+H9+I9)*$B$8,0) -> 864.12904 | K9: =IF(F9<=$B$5,MIN($B$9,MAX(0,G9+H9+I9-J9)),0) -> 600 | L9: =G9+H9+I9-J9-K9 -> 67666.194 | M9: =IF(F9<=$B$5,L9*(1+$B$10),0) -> 71049.504 | N9: =IF(F9<=$B$5,L9,0) -> 67666.194 | O9: =G9+H9+I9-J9-K9-L9 -> 0
A10: Death benefit loading | B10: =Assumptions!$C$20 -> 0.05 | C10: % account value | D10: Assumptions sheet | F10: 7 | G10: =L9 -> 67666.194 | H10: =IF(F10<=$B$5,$B$4*$B$7,0) -> 11400 | I10: =IF(F10<=$B$5,(G10+H10)*$B$6,0) -> 1976.6549 | J10: =IF(F10<=$B$5,(G10+H10+I10)*$B$8,0) -> 1013.0356 | K10: =IF(F10<=$B$5,MIN($B$9,MAX(0,G10+H10+I10-J10)),0) -> 600 | L10: =G10+H10+I10-J10-K10 -> 79429.814 | M10: =IF(F10<=$B$5,L10*(1+$B$10),0) -> 83401.304 | N10: =IF(F10<=$B$5,L10,0) -> 79429.814 | O10: =G10+H10+I10-J10-K10-L10 -> 0
A11: Initial account value | B11: 0 | C11: AED | D11: Opening Balance | F11: 8 | G11: =L10 -> 79429.814 | H11: =IF(F11<=$B$5,$B$4*$B$7,0) -> 11400 | I11: =IF(F11<=$B$5,(G11+H11)*$B$6,0) -> 2270.7453 | J11: =IF(F11<=$B$5,(G11+H11+I11)*$B$8,0) -> 1163.757 | K11: =IF(F11<=$B$5,MIN($B$9,MAX(0,G11+H11+I11-J11)),0) -> 600 | L11: =G11+H11+I11-J11-K11 -> 91336.802 | M11: =IF(F11<=$B$5,L11*(1+$B$10),0) -> 95903.642 | N11: =IF(F11<=$B$5,L11,0) -> 91336.802 | O11: =G11+H11+I11-J11-K11-L11 -> 0
F12: 9 | G12: =L11 -> 91336.802 | H12: =IF(F12<=$B$5,$B$4*$B$7,0) -> 11400 | I12: =IF(F12<=$B$5,(G12+H12)*$B$6,0) -> 2568.42 | J12: =IF(F12<=$B$5,(G12+H12+I12)*$B$8,0) -> 1316.3153 | K12: =IF(F12<=$B$5,MIN($B$9,MAX(0,G12+H12+I12-J12)),0) -> 600 | L12: =G12+H12+I12-J12-K12 -> 103388.91 | M12: =IF(F12<=$B$5,L12*(1+$B$10),0) -> 108558.35 | N12: =IF(F12<=$B$5,L12,0) -> 103388.91 | O12: =G12+H12+I12-J12-K12-L12 -> 0
A13: Fund value at maturity | B13: {=INDEX(L4:L43,B5)} -> 246061.32 | F13: 10 | G13: =L12 -> 103388.91 | H13: =IF(F13<=$B$5,$B$4*$B$7,0) -> 11400 | I13: =IF(F13<=$B$5,(G13+H13)*$B$6,0) -> 2869.7227 | J13: =IF(F13<=$B$5,(G13+H13+I13)*$B$8,0) -> 1470.7329 | K13: =IF(F13<=$B$5,MIN($B$9,MAX(0,G13+H13+I13-J13)),0) -> 600 | L13: =G13+H13+I13-J13-K13 -> 115587.9 | M13: =IF(F13<=$B$5,L13*(1+$B$10),0) -> 121367.29 | N13: =IF(F13<=$B$5,L13,0) -> 115587.9 | O13: =G13+H13+I13-J13-K13-L13 -> 0
A14: Input status | B14: =IF(AND(COUNT(B4:B11)=8,B4>=0,B5>=1,B5<=40,B5=INT(B5),B6>-1,B7>=0,B7<=1,B8>=0,B8<=1,B9>=0,B10>=0,B11>=0),"VALID","INVALID INPUT") -> VALID | F14: 11 | G14: =L13 -> 115587.9 | H14: =IF(F14<=$B$5,$B$4*$B$7,0) -> 11400 | I14: =IF(F14<=$B$5,(G14+H14)*$B$6,0) -> 3174.6974 | J14: =IF(F14<=$B$5,(G14+H14+I14)*$B$8,0) -> 1627.0324 | K14: =IF(F14<=$B$5,MIN($B$9,MAX(0,G14+H14+I14-J14)),0) -> 600 | L14: =G14+H14+I14-J14-K14 -> 127935.56 | M14: =IF(F14<=$B$5,L14*(1+$B$10),0) -> 134332.34 | N14: =IF(F14<=$B$5,L14,0) -> 127935.56 | O14: =G14+H14+I14-J14-K14-L14 -> 0
F15: 12 | G15: =L14 -> 127935.56 | H15: =IF(F15<=$B$5,$B$4*$B$7,0) -> 11400 | I15: =IF(F15<=$B$5,(G15+H15)*$B$6,0) -> 3483.389 | J15: =IF(F15<=$B$5,(G15+H15+I15)*$B$8,0) -> 1785.2369 | K15: =IF(F15<=$B$5,MIN($B$9,MAX(0,G15+H15+I15-J15)),0) -> 600 | L15: =G15+H15+I15-J15-K15 -> 140433.71 | M15: =IF(F15<=$B$5,L15*(1+$B$10),0) -> 147455.4 | N15: =IF(F15<=$B$5,L15,0) -> 140433.71 | O15: =G15+H15+I15-J15-K15-L15 -> 0
F16: 13 | G16: =L15 -> 140433.71 | H16: =IF(F16<=$B$5,$B$4*$B$7,0) -> 11400 | I16: =IF(F16<=$B$5,(G16+H16)*$B$6,0) -> 3795.8428 | J16: =IF(F16<=$B$5,(G16+H16+I16)*$B$8,0) -> 1945.3695 | K16: =IF(F16<=$B$5,MIN($B$9,MAX(0,G16+H16+I16-J16)),0) -> 600 | L16: =G16+H16+I16-J16-K16 -> 153084.19 | M16: =IF(F16<=$B$5,L16*(1+$B$10),0) -> 160738.4 | N16: =IF(F16<=$B$5,L16,0) -> 153084.19 | O16: =G16+H16+I16-J16-K16-L16 -> 0
A17: Illustrative unit-linked projection based on the assumptions shown above; no policyholder or insurer data is used. | F17: 14 | G17: =L16 -> 153084.19 | H17: =IF(F17<=$B$5,$B$4*$B$7,0) -> 11400 | I17: =IF(F17<=$B$5,(G17+H17)*$B$6,0) -> 4112.1047 | J17: =IF(F17<=$B$5,(G17+H17+I17)*$B$8,0) -> 2107.4536 | K17: =IF(F17<=$B$5,MIN($B$9,MAX(0,G17+H17+I17-J17)),0) -> 600 | L17: =G17+H17+I17-J17-K17 -> 165888.84 | M17: =IF(F17<=$B$5,L17*(1+$B$10),0) -> 174183.28 | N17: =IF(F17<=$B$5,L17,0) -> 165888.84 | O17: =G17+H17+I17-J17-K17-L17 -> 0
F18: 15 | G18: =L17 -> 165888.84 | H18: =IF(F18<=$B$5,$B$4*$B$7,0) -> 11400 | I18: =IF(F18<=$B$5,(G18+H18)*$B$6,0) -> 4432.221 | J18: =IF(F18<=$B$5,(G18+H18+I18)*$B$8,0) -> 2271.5132 | K18: =IF(F18<=$B$5,MIN($B$9,MAX(0,G18+H18+I18-J18)),0) -> 600 | L18: =G18+H18+I18-J18-K18 -> 178849.55 | M18: =IF(F18<=$B$5,L18*(1+$B$10),0) -> 187792.02 | N18: =IF(F18<=$B$5,L18,0) -> 178849.55 | O18: =G18+H18+I18-J18-K18-L18 -> 0
F19: 16 | G19: =L18 -> 178849.55 | H19: =IF(F19<=$B$5,$B$4*$B$7,0) -> 11400 | I19: =IF(F19<=$B$5,(G19+H19)*$B$6,0) -> 4756.2386 | J19: =IF(F19<=$B$5,(G19+H19+I19)*$B$8,0) -> 2437.5723 | K19: =IF(F19<=$B$5,MIN($B$9,MAX(0,G19+H19+I19-J19)),0) -> 600 | L19: =G19+H19+I19-J19-K19 -> 191968.21 | M19: =IF(F19<=$B$5,L19*(1+$B$10),0) -> 201566.62 | N19: =IF(F19<=$B$5,L19,0) -> 191968.21 | O19: =G19+H19+I19-J19-K19-L19 -> 0
F20: 17 | G20: =L19 -> 191968.21 | H20: =IF(F20<=$B$5,$B$4*$B$7,0) -> 11400 | I20: =IF(F20<=$B$5,(G20+H20)*$B$6,0) -> 5084.2053 | J20: =IF(F20<=$B$5,(G20+H20+I20)*$B$8,0) -> 2605.6552 | K20: =IF(F20<=$B$5,MIN($B$9,MAX(0,G20+H20+I20-J20)),0) -> 600 | L20: =G20+H20+I20-J20-K20 -> 205246.76 | M20: =IF(F20<=$B$5,L20*(1+$B$10),0) -> 215509.1 | N20: =IF(F20<=$B$5,L20,0) -> 205246.76 | O20: =G20+H20+I20-J20-K20-L20 -> 0
F21: 18 | G21: =L20 -> 205246.76 | H21: =IF(F21<=$B$5,$B$4*$B$7,0) -> 11400 | I21: =IF(F21<=$B$5,(G21+H21)*$B$6,0) -> 5416.1691 | J21: =IF(F21<=$B$5,(G21+H21+I21)*$B$8,0) -> 2775.7866 | K21: =IF(F21<=$B$5,MIN($B$9,MAX(0,G21+H21+I21-J21)),0) -> 600 | L21: =G21+H21+I21-J21-K21 -> 218687.14 | M21: =IF(F21<=$B$5,L21*(1+$B$10),0) -> 229621.5 | N21: =IF(F21<=$B$5,L21,0) -> 218687.14 | O21: =G21+H21+I21-J21-K21-L21 -> 0
F22: 19 | G22: =L21 -> 218687.14 | H22: =IF(F22<=$B$5,$B$4*$B$7,0) -> 11400 | I22: =IF(F22<=$B$5,(G22+H22)*$B$6,0) -> 5752.1786 | J22: =IF(F22<=$B$5,(G22+H22+I22)*$B$8,0) -> 2947.9915 | K22: =IF(F22<=$B$5,MIN($B$9,MAX(0,G22+H22+I22-J22)),0) -> 600 | L22: =G22+H22+I22-J22-K22 -> 232291.33 | M22: =IF(F22<=$B$5,L22*(1+$B$10),0) -> 243905.9 | N22: =IF(F22<=$B$5,L22,0) -> 232291.33 | O22: =G22+H22+I22-J22-K22-L22 -> 0
F23: 20 | G23: =L22 -> 232291.33 | H23: =IF(F23<=$B$5,$B$4*$B$7,0) -> 11400 | I23: =IF(F23<=$B$5,(G23+H23)*$B$6,0) -> 6092.2833 | J23: =IF(F23<=$B$5,(G23+H23+I23)*$B$8,0) -> 3122.2952 | K23: =IF(F23<=$B$5,MIN($B$9,MAX(0,G23+H23+I23-J23)),0) -> 600 | L23: =G23+H23+I23-J23-K23 -> 246061.32 | M23: =IF(F23<=$B$5,L23*(1+$B$10),0) -> 258364.39 | N23: =IF(F23<=$B$5,L23,0) -> 246061.32 | O23: =G23+H23+I23-J23-K23-L23 -> 0
F24: 21 | G24: =L23 -> 246061.32 | H24: =IF(F24<=$B$5,$B$4*$B$7,0) -> 0 | I24: =IF(F24<=$B$5,(G24+H24)*$B$6,0) -> 0 | J24: =IF(F24<=$B$5,(G24+H24+I24)*$B$8,0) -> 0 | K24: =IF(F24<=$B$5,MIN($B$9,MAX(0,G24+H24+I24-J24)),0) -> 0 | L24: =G24+H24+I24-J24-K24 -> 246061.32 | M24: =IF(F24<=$B$5,L24*(1+$B$10),0) -> 0 | N24: =IF(F24<=$B$5,L24,0) -> 0 | O24: =G24+H24+I24-J24-K24-L24 -> 0
F25: 22 | G25: =L24 -> 246061.32 | H25: =IF(F25<=$B$5,$B$4*$B$7,0) -> 0 | I25: =IF(F25<=$B$5,(G25+H25)*$B$6,0) -> 0 | J25: =IF(F25<=$B$5,(G25+H25+I25)*$B$8,0) -> 0 | K25: =IF(F25<=$B$5,MIN($B$9,MAX(0,G25+H25+I25-J25)),0) -> 0 | L25: =G25+H25+I25-J25-K25 -> 246061.32 | M25: =IF(F25<=$B$5,L25*(1+$B$10),0) -> 0 | N25: =IF(F25<=$B$5,L25,0) -> 0 | O25: =G25+H25+I25-J25-K25-L25 -> 0
F26: 23 | G26: =L25 -> 246061.32 | H26: =IF(F26<=$B$5,$B$4*$B$7,0) -> 0 | I26: =IF(F26<=$B$5,(G26+H26)*$B$6,0) -> 0 | J26: =IF(F26<=$B$5,(G26+H26+I26)*$B$8,0) -> 0 | K26: =IF(F26<=$B$5,MIN($B$9,MAX(0,G26+H26+I26-J26)),0) -> 0 | L26: =G26+H26+I26-J26-K26 -> 246061.32 | M26: =IF(F26<=$B$5,L26*(1+$B$10),0) -> 0 | N26: =IF(F26<=$B$5,L26,0) -> 0 | O26: =G26+H26+I26-J26-K26-L26 -> 0
F27: 24 | G27: =L26 -> 246061.32 | H27: =IF(F27<=$B$5,$B$4*$B$7,0) -> 0 | I27: =IF(F27<=$B$5,(G27+H27)*$B$6,0) -> 0 | J27: =IF(F27<=$B$5,(G27+H27+I27)*$B$8,0) -> 0 | K27: =IF(F27<=$B$5,MIN($B$9,MAX(0,G27+H27+I27-J27)),0) -> 0 | L27: =G27+H27+I27-J27-K27 -> 246061.32 | M27: =IF(F27<=$B$5,L27*(1+$B$10),0) -> 0 | N27: =IF(F27<=$B$5,L27,0) -> 0 | O27: =G27+H27+I27-J27-K27-L27 -> 0
F28: 25 | G28: =L27 -> 246061.32 | H28: =IF(F28<=$B$5,$B$4*$B$7,0) -> 0 | I28: =IF(F28<=$B$5,(G28+H28)*$B$6,0) -> 0 | J28: =IF(F28<=$B$5,(G28+H28+I28)*$B$8,0) -> 0 | K28: =IF(F28<=$B$5,MIN($B$9,MAX(0,G28+H28+I28-J28)),0) -> 0 | L28: =G28+H28+I28-J28-K28 -> 246061.32 | M28: =IF(F28<=$B$5,L28*(1+$B$10),0) -> 0 | N28: =IF(F28<=$B$5,L28,0) -> 0 | O28: =G28+H28+I28-J28-K28-L28 -> 0
F29: 26 | G29: =L28 -> 246061.32 | H29: =IF(F29<=$B$5,$B$4*$B$7,0) -> 0 | I29: =IF(F29<=$B$5,(G29+H29)*$B$6,0) -> 0 | J29: =IF(F29<=$B$5,(G29+H29+I29)*$B$8,0) -> 0 | K29: =IF(F29<=$B$5,MIN($B$9,MAX(0,G29+H29+I29-J29)),0) -> 0 | L29: =G29+H29+I29-J29-K29 -> 246061.32 | M29: =IF(F29<=$B$5,L29*(1+$B$10),0) -> 0 | N29: =IF(F29<=$B$5,L29,0) -> 0 | O29: =G29+H29+I29-J29-K29-L29 -> 0
... F43: 40 | G43: =L42 -> 246061.32 | H43: =IF(F43<=$B$5,$B$4*$B$7,0) -> 0 | I43: =IF(F43<=$B$5,(G43+H43)*$B$6,0) -> 0 | J43: =IF(F43<=$B$5,(G43+H43+I43)*$B$8,0) -> 0 | K43: =IF(F43<=$B$5,MIN($B$9,MAX(0,G43+H43+I43-J43)),0) -> 0 | L43: =G43+H43+I43-J43-K43 -> 246061.32 | M43: =IF(F43<=$B$5,L43*(1+$B$10),0) -> 0 | N43: =IF(F43<=$B$5,L43,0) -> 0 | O43: =G43+H43+I43-J43-K43-L43 -> 0

Sheet IFRS 17 VFA
A1: IFRS 17 VFA: Unit-Linked
A3: VFA eligibility criteria | B3: Assessment | C3: Rationale | F3: Feature | G3: GMM | H3: VFA | I3: Comment
A4: Clearly identified underlying items | B4: Yes | C4: Policyholder account is linked to a defined fund pool | F4: Typical focus | G4: Non-direct participating protection | H4: Direct participating / underlying items | I4: Assessment depends on product features
A5: Substantial share of fair value returns paid to policyholder | B5: Yes | C5: Account value reflects fund performance net of charges | F5: CSM response to financial changes | G5: More limited | H5: Variable fee-related changes can adjust CSM | I5: Financial changes may adjust the CSM under VFA
A6: Substantial variability with underlying items | B6: Yes | C6: Benefits vary with account value | F6: Underlying items | G6: Not central | H6: Clearly identified | I6: Relevant to VFA eligibility
F7: Investment service | G7: May exist | H7: Investment-related service integral | I7: Reflects investment-related service
A8: Metric | B8: Value | C8: Unit | D8: Comment | F8: Reinsurance held | G8: Separate measurement | H8: VFA does not apply to reinsurance held | I8: Separate treatment under IFRS 17
A9: Year 1 underlying items / closing fund | B9: ='Unit-Linked'!L4 -> 10938.938 | C9: AED | D9: Unit-linked closing fund
A10: Year 1 fund and policy charges | B10: ='Unit-Linked'!J4+'Unit-Linked'!K4 -> 746.0625 | C10: AED | D10: Illustrative charge income
A11: Death benefit | B11: =B9*(1+Assumptions!$C$20) -> 11485.884 | C11: AED | D11: Account value plus death loading
A12: Opening CSM | B12: 5000 | C12: AED | D12: Illustrative
A13: Investment performance adjustment | B13: =('Unit-Linked'!B11+'Unit-Linked'!B4*'Unit-Linked'!B7)*Assumptions!C26*'Unit-Linked'!B8 -> 0 | C13: AED | D13: Illustrative adjustment for changes in future fees
A14: Closing CSM before release | B14: =MAX(0,B12+B13) -> 5000 | C14: AED | D14: Opening CSM adjusted for changes in the variable fee
A15: CSM release | B15: =B14/'Unit-Linked'!B5 -> 250 | C15: AED | D15: CSM release based on service units
A16: Closing CSM | B16: =B14-B15 -> 4750 | C16: AED | D16: CSM after release
A17: CSM reconciliation | B17: =B12+B13+MAX(0,-(B12+B13))-B15-B16 -> 0 | C17: AED
A18: Surrender benefit | B18: ='Unit-Linked'!N4 -> 10938.938 | C18: AED | D18: Account value with surrender penalty
A21: CSM roll-forward
A22: Year | B22: Opening CSM | C22: Fee change | D22: Excess loss | E22: Before release | F22: Service units | G22: CSM release | H22: Closing CSM | I22: Difference
A23: 1 | B23: =$B$12 -> 5000 | C23: =$B$13 -> 0 | D23: =MAX(0,-(B23+C23)) -> 0 | E23: =B23+C23+D23 -> 5000 | F23: =IF(A23<='Unit-Linked'!$B$5,1,0) -> 1 | G23: =IF(SUM(F23:$F$62)=0,0,E23*F23/SUM(F23:$F$62)) -> 250 | H23: =E23-G23 -> 4750 | I23: =B23+C23+D23-G23-H23 -> 0
A24: 2 | B24: =H23 -> 4750 | C24: =0 -> 0 | D24: =MAX(0,-(B24+C24)) -> 0 | E24: =B24+C24+D24 -> 4750 | F24: =IF(A24<='Unit-Linked'!$B$5,1,0) -> 1 | G24: =IF(SUM(F24:$F$62)=0,0,E24*F24/SUM(F24:$F$62)) -> 250 | H24: =E24-G24 -> 4500 | I24: =B24+C24+D24-G24-H24 -> 0
A25: 3 | B25: =H24 -> 4500 | C25: =0 -> 0 | D25: =MAX(0,-(B25+C25)) -> 0 | E25: =B25+C25+D25 -> 4500 | F25: =IF(A25<='Unit-Linked'!$B$5,1,0) -> 1 | G25: =IF(SUM(F25:$F$62)=0,0,E25*F25/SUM(F25:$F$62)) -> 250 | H25: =E25-G25 -> 4250 | I25: =B25+C25+D25-G25-H25 -> 0
A26: 4 | B26: =H25 -> 4250 | C26: =0 -> 0 | D26: =MAX(0,-(B26+C26)) -> 0 | E26: =B26+C26+D26 -> 4250 | F26: =IF(A26<='Unit-Linked'!$B$5,1,0) -> 1 | G26: =IF(SUM(F26:$F$62)=0,0,E26*F26/SUM(F26:$F$62)) -> 250 | H26: =E26-G26 -> 4000 | I26: =B26+C26+D26-G26-H26 -> 0
A27: 5 | B27: =H26 -> 4000 | C27: =0 -> 0 | D27: =MAX(0,-(B27+C27)) -> 0 | E27: =B27+C27+D27 -> 4000 | F27: =IF(A27<='Unit-Linked'!$B$5,1,0) -> 1 | G27: =IF(SUM(F27:$F$62)=0,0,E27*F27/SUM(F27:$F$62)) -> 250 | H27: =E27-G27 -> 3750 | I27: =B27+C27+D27-G27-H27 -> 0
A28: 6 | B28: =H27 -> 3750 | C28: =0 -> 0 | D28: =MAX(0,-(B28+C28)) -> 0 | E28: =B28+C28+D28 -> 3750 | F28: =IF(A28<='Unit-Linked'!$B$5,1,0) -> 1 | G28: =IF(SUM(F28:$F$62)=0,0,E28*F28/SUM(F28:$F$62)) -> 250 | H28: =E28-G28 -> 3500 | I28: =B28+C28+D28-G28-H28 -> 0
A29: 7 | B29: =H28 -> 3500 | C29: =0 -> 0 | D29: =MAX(0,-(B29+C29)) -> 0 | E29: =B29+C29+D29 -> 3500 | F29: =IF(A29<='Unit-Linked'!$B$5,1,0) -> 1 | G29: =IF(SUM(F29:$F$62)=0,0,E29*F29/SUM(F29:$F$62)) -> 250 | H29: =E29-G29 -> 3250 | I29: =B29+C29+D29-G29-H29 -> 0
A30: 8 | B30: =H29 -> 3250 | C30: =0 -> 0 | D30: =MAX(0,-(B30+C30)) -> 0 | E30: =B30+C30+D30 -> 3250 | F30: =IF(A30<='Unit-Linked'!$B$5,1,0) -> 1 | G30: =IF(SUM(F30:$F$62)=0,0,E30*F30/SUM(F30:$F$62)) -> 250 | H30: =E30-G30 -> 3000 | I30: =B30+C30+D30-G30-H30 -> 0
A31: 9 | B31: =H30 -> 3000 | C31: =0 -> 0 | D31: =MAX(0,-(B31+C31)) -> 0 | E31: =B31+C31+D31 -> 3000 | F31: =IF(A31<='Unit-Linked'!$B$5,1,0) -> 1 | G31: =IF(SUM(F31:$F$62)=0,0,E31*F31/SUM(F31:$F$62)) -> 250 | H31: =E31-G31 -> 2750 | I31: =B31+C31+D31-G31-H31 -> 0
A32: 10 | B32: =H31 -> 2750 | C32: =0 -> 0 | D32: =MAX(0,-(B32+C32)) -> 0 | E32: =B32+C32+D32 -> 2750 | F32: =IF(A32<='Unit-Linked'!$B$5,1,0) -> 1 | G32: =IF(SUM(F32:$F$62)=0,0,E32*F32/SUM(F32:$F$62)) -> 250 | H32: =E32-G32 -> 2500 | I32: =B32+C32+D32-G32-H32 -> 0
A33: 11 | B33: =H32 -> 2500 | C33: =0 -> 0 | D33: =MAX(0,-(B33+C33)) -> 0 | E33: =B33+C33+D33 -> 2500 | F33: =IF(A33<='Unit-Linked'!$B$5,1,0) -> 1 | G33: =IF(SUM(F33:$F$62)=0,0,E33*F33/SUM(F33:$F$62)) -> 250 | H33: =E33-G33 -> 2250 | I33: =B33+C33+D33-G33-H33 -> 0
A34: 12 | B34: =H33 -> 2250 | C34: =0 -> 0 | D34: =MAX(0,-(B34+C34)) -> 0 | E34: =B34+C34+D34 -> 2250 | F34: =IF(A34<='Unit-Linked'!$B$5,1,0) -> 1 | G34: =IF(SUM(F34:$F$62)=0,0,E34*F34/SUM(F34:$F$62)) -> 250 | H34: =E34-G34 -> 2000 | I34: =B34+C34+D34-G34-H34 -> 0
A35: 13 | B35: =H34 -> 2000 | C35: =0 -> 0 | D35: =MAX(0,-(B35+C35)) -> 0 | E35: =B35+C35+D35 -> 2000 | F35: =IF(A35<='Unit-Linked'!$B$5,1,0) -> 1 | G35: =IF(SUM(F35:$F$62)=0,0,E35*F35/SUM(F35:$F$62)) -> 250 | H35: =E35-G35 -> 1750 | I35: =B35+C35+D35-G35-H35 -> 0
... A62: 40 | B62: =H61 -> 0 | C62: =0 -> 0 | D62: =MAX(0,-(B62+C62)) -> 0 | E62: =B62+C62+D62 -> 0 | F62: =IF(A62<='Unit-Linked'!$B$5,1,0) -> 0 | G62: =IF(SUM(F62:$F$62)=0,0,E62*F62/SUM(F62:$F$62)) -> 0 | H62: =E62-G62 -> 0 | I62: =B62+C62+D62-G62-H62 -> 0
A65: Opening CSM is an illustrative assumption. Equal service units are used for the CSM release.
A66: VFA eligibility depends on the contract terms and the policyholder's participation in the underlying items.

Sheet Policy Data
A1: Policy Data
A3: Policy ID | B3: Product | C3: Entry age | D3: Sex | E3: Smoker status | F3: UW class | G3: Term (years) | H3: Sum assured (AED) | I3: Premium frequency | J3: Channel | K3: Duration | L3: Exposure years | M3: Experience qx | N3: Expected deaths | O3: Death event | P3: Experience lapse rate | Q3: Lapse event | R3: Annual premium (AED)
A4: POL100000 | B4: Term Life | C4: 55 | D4: Male | E4: Non-smoker | F4: Standard | G4: 20 | H4: 250000 | I4: Monthly | J4: Broker | K4: 6 | L4: 0.9267 | M4: 0.00382384 | N4: 0.003544 | O4: 0 | P4: 0.05965 | Q4: 0 | R4: 1745.53
A5: POL100001 | B5: Term Life | C5: 43 | D5: Male | E5: Non-smoker | F5: Standard | G5: 15 | H5: 250000 | I5: Monthly | J5: Bancassurance | K5: 5 | L5: 0.6377 | M5: 0.00146412 | N5: 0.000934 | O5: 0 | P5: 0.074329 | Q5: 0 | R5: 1200
A6: POL100002 | B6: Term Life | C6: 32 | D6: Male | E6: Non-smoker | F6: Standard | G6: 20 | H6: 2000000 | I6: Annual | J6: Broker | K6: 6 | L6: 0.6206 | M6: 0.00060729 | N6: 0.000377 | O6: 0 | P6: 0.046868 | Q6: 0 | R6: 3013.21
A7: POL100003 | B7: Term Life | C7: 38 | D7: Male | E7: Non-smoker | F7: Standard | G7: 10 | H7: 500000 | I7: Annual | J7: Broker | K7: 5 | L7: 0.5174 | M7: 0.00098143 | N7: 0.000508 | O7: 0 | P7: 0.058401 | Q7: 0 | R7: 1334.04
A8: POL100004 | B8: Term Life | C8: 50 | D8: Male | E8: Non-smoker | F8: Standard | G8: 20 | H8: 1000000 | I8: Annual | J8: Broker | K8: 4 | L8: 0.8164 | M8: 0.00256319 | N8: 0.002093 | O8: 0 | P8: 0.072773 | Q8: 0 | R8: 4054.57
A9: POL100005 | B9: Unit-Linked | C9: 27 | D9: Male | E9: Smoker | F9: Standard | G9: 25 | H9: 250000 | I9: Annual | J9: Broker | K9: 3 | L9: 0.9511 | M9: 0.00067168 | N9: 0.000639 | O9: 0 | P9: 0.081612 | Q9: 0 | R9: 7429
A10: POL100006 | B10: Term Life | C10: 46 | D10: Female | E10: Non-smoker | F10: Standard | G10: 10 | H10: 2000000 | I10: Monthly | J10: Bancassurance | K10: 1 | L10: 0.6063 | M10: 0.00137571 | N10: 0.000834 | O10: 0 | P10: 0.1792 | Q10: 0 | R10: 4826.69
A11: POL100007 | B11: Unit-Linked | C11: 57 | D11: Male | E11: Non-smoker | F11: Preferred | G11: 15 | H11: 500000 | I11: Monthly | J11: Broker | K11: 5 | L11: 0.9418 | M11: 0.00358985 | N11: 0.003381 | O11: 0 | P11: 0.066896 | Q11: 0 | R11: 12562.62
A12: POL100008 | B12: Term Life | C12: 54 | D12: Male | E12: Non-smoker | F12: Preferred | G12: 25 | H12: 250000 | I12: Monthly | J12: Bancassurance | K12: 4 | L12: 0.657 | M12: 0.00282388 | N12: 0.001855 | O12: 0 | P12: 0.09262 | Q12: 1 | R12: 1450.54
A13: POL100009 | B13: Term Life | C13: 30 | D13: Male | E13: Smoker | F13: Standard | G13: 10 | H13: 250000 | I13: Annual | J13: Direct | K13: 7 | L13: 0.7824 | M13: 0.00085387 | N13: 0.000668 | O13: 0 | P13: 0.037613 | Q13: 0 | R13: 1200
A14: POL100010 | B14: Term Life | C14: 28 | D14: Female | E14: Non-smoker | F14: Preferred | G14: 10 | H14: 500000 | I14: Monthly | J14: Bancassurance | K14: 1 | L14: 0.9305 | M14: 0.00026076 | N14: 0.000243 | O14: 0 | P14: 0.1792 | Q14: 0 | R14: 1200
A15: POL100011 | B15: Term Life | C15: 46 | D15: Male | E15: Non-smoker | F15: Standard | G15: 15 | H15: 500000 | I15: Annual | J15: Bancassurance | K15: 7 | L15: 0.9822 | M15: 0.00186126 | N15: 0.001828 | O15: 0 | P15: 0.037613 | Q15: 0 | R15: 1853.14
... A253: POL100249 | B253: Term Life | C253: 58 | D253: Male | E253: Non-smoker | F253: Rated | G253: 25 | H253: 250000 | I253: Monthly | J253: Broker | K253: 1 | L253: 0.698 | M253: 0.00753463 | N253: 0.005259 | O253: 0 | P253: 0.1792 | Q253: 0 | R253: 2840.21

Sheet Checks
A1: Checks
A3: Check | B3: Result | C3: Tolerance | D3: Status
A4: Quote input validity | B4: ='Premium Calculation'!B27 -> VALID | C4: VALID | D4: =IFERROR(IF(B4="VALID","PASS","FAIL"),"FAIL") -> PASS
A5: Premium equation reconciliation | B5: ='Premium Calculation'!B26 -> 0 | C5: abs < 0.01 | D5: =IFERROR(IF(ABS(B5)<0.01,"PASS","FAIL"),"FAIL") -> PASS
A6: Claims reconciliation | B6: =SUM(Cashflows!F4:F43)-SUM(Cashflows!G4:G43)-SUM(Cashflows!H4:H43) -> 0 | C6: abs < 0.01 | D6: =IFERROR(IF(ABS(B6)<0.01,"PASS","FAIL"),"FAIL") -> PASS
A7: Profit bridge | B7: ='Profit Testing'!B11 -> -1.1937118e-12 | C7: abs < 0.01 | D7: =IFERROR(IF(ABS(B7)<0.01,"PASS","FAIL"),"FAIL") -> PASS
A8: Minimum in-force | B8: =MIN(Cashflows!B4:B43) -> 0 | C8: >=0 | D8: =IFERROR(IF(B8>=0,"PASS","FAIL"),"FAIL") -> PASS
A9: Maximum qx | B9: =MAX(Cashflows!C4:C43) -> 0.00086839029 | C9: <=1 | D9: =IFERROR(IF(AND(B9>=0,B9<=1),"PASS","FAIL"),"FAIL") -> PASS
A10: Decrement conservation | B10: =SUMPRODUCT(Cashflows!U4:U43,Cashflows!U4:U43) -> 7.2372836e-33 | C10: abs < 0.00000001 | D10: =IFERROR(IF(ABS(B10)<0.00000001,"PASS","FAIL"),"FAIL") -> PASS
A11: GMM CSM / loss component check | B11: ='IFRS 17 GMM'!B8*'IFRS 17 GMM'!B9 -> 0 | C11: abs < 0.01 | D11: =IFERROR(IF(ABS(B11)<0.01,"PASS","FAIL"),"FAIL") -> PASS
A12: GMM CSM run-off | B12: ='IFRS 17 GMM'!B19 -> 1.1368684e-13 | C12: abs < 0.01 | D12: =IFERROR(IF(ABS(B12)<0.01,"PASS","FAIL"),"FAIL") -> PASS
A13: GMM liability roll-forward | B13: =SUMPRODUCT('IFRS 17 GMM'!T4:T43,'IFRS 17 GMM'!T4:T43) -> 0 | C13: abs < 0.0001 | D13: =IFERROR(IF(ABS(B13)<0.0001,"PASS","FAIL"),"FAIL") -> PASS
A14: GMM terminal BEL | B14: ='IFRS 17 GMM'!Q43 -> 3.6695983e-12 | C14: abs < 0.01 | D14: =IFERROR(IF(ABS(B14)<0.01,"PASS","FAIL"),"FAIL") -> PASS
A15: UL fund conservation | B15: =SUMPRODUCT('Unit-Linked'!O4:O43,'Unit-Linked'!O4:O43) -> 0 | C15: abs < 0.0001 | D15: =IFERROR(IF(ABS(B15)<0.0001,"PASS","FAIL"),"FAIL") -> PASS
A16: UL input validity | B16: ='Unit-Linked'!B14 -> VALID | C16: VALID | D16: =IFERROR(IF(B16="VALID","PASS","FAIL"),"FAIL") -> PASS
A17: VFA CSM roll-forward | B17: ='IFRS 17 VFA'!B17 -> 0 | C17: abs < 0.01 | D17: =IFERROR(IF(ABS(B17)<0.01,"PASS","FAIL"),"FAIL") -> PASS
A18: Experience death total | B18: =SUM('Experience Analysis'!D5:D10)-'Experience Analysis'!B48 -> 0 | C18: zero | D18: =IFERROR(IF(B18=0,"PASS","FAIL"),"FAIL") -> PASS
A19: Experience expected total | B19: =SUM('Experience Analysis'!E5:E10)-'Experience Analysis'!B49 -> 0 | C19: abs < 0.00001 | D19: =IFERROR(IF(ABS(B19)<0.00001,"PASS","FAIL"),"FAIL") -> PASS
A20: Policy PVFP reconciliation | B20: ='Policy Calculations'!AI6-'Profit Testing'!B7 -> 1.080025e-12 | C20: abs < 0.01 | D20: =IFERROR(IF(ABS(B20)<0.01,"PASS","FAIL"),"FAIL") -> PASS
A21: Policy PV premiums reconciliation | B21: ='Policy Calculations'!AH6-'Profit Testing'!B4 -> 0 | C21: abs < 0.01 | D21: =IFERROR(IF(ABS(B21)<0.01,"PASS","FAIL"),"FAIL") -> PASS
A22: Technical premium reconciliation | B22: ='Policy Calculations'!AF6-'Premium Calculation'!B19 -> 0 | C22: abs < 0.01 | D22: =IFERROR(IF(ABS(B22)<0.01,"PASS","FAIL"),"FAIL") -> PASS
A23: RI impact reconciliation | B23: ='Policy Calculations'!AN6-Reinsurance!B11 -> 0 | C23: abs < 0.01 | D23: =IFERROR(IF(ABS(B23)<0.01,"PASS","FAIL"),"FAIL") -> PASS
A24: Policy calculation PVFP without RI = Reinsurance | B24: ='Policy Calculations'!AO6-Reinsurance!B12 -> 1.080025e-12 | C24: abs < 0.01 | D24: =IFERROR(IF(ABS(B24)<0.01,"PASS","FAIL"),"FAIL") -> PASS
A25: Portfolio record completeness | B25: ='Portfolio Totals'!B8+'Portfolio Totals'!B9+'Portfolio Totals'!B10-'Portfolio Totals'!B6 -> 0 | C25: abs < 0.01 | D25: =IFERROR(IF(ABS(B25)<0.01,"PASS","FAIL"),"FAIL") -> PASS
A26: Segment reconciliation | B26: =ABS('Portfolio Analysis'!K22)+ABS('Portfolio Analysis'!K31)+ABS('Portfolio Analysis'!K37)+ABS('Portfolio Analysis'!K43)+ABS('Portfolio Analysis'!K50)+ABS('Portfolio Analysis'!K58)+ABS('Portfolio Analysis'!K64)+ABS('Portfolio Analysis'!K72) -> 0 | C26: abs < 0.01 | D26: =IFERROR(IF(ABS(B26)<0.01,"PASS","FAIL"),"FAIL") -> PASS
A27: NBM band reconciliation | B27: ='Portfolio Totals'!I12 -> 0 | C27: abs < 0.01 | D27: =IFERROR(IF(ABS(B27)<0.01,"PASS","FAIL"),"FAIL") -> PASS
A28: Lapse exposure reconciliation | B28: ='Assumption Review'!D36-SUMIFS('Experience Analysis'!D14:D41,'Experience Analysis'!B14:B41,"Term Life") -> 0 | C28: abs < 0.01 | D28: =IFERROR(IF(ABS(B28)<0.01,"PASS","FAIL"),"FAIL") -> PASS
A29: Credibility factor bounds | B29: =IF(AND('Assumption Review'!B20>=0,'Assumption Review'!B20<=1,'Assumption Review'!B42>=0,'Assumption Review'!B42<=1),0,1) -> 0 | C29: abs < 0.01 | D29: =IFERROR(IF(ABS(B29)<0.01,"PASS","FAIL"),"FAIL") -> PASS
A30: Channel commission applied in cash flows | B30: =Cashflows!J4-Cashflows!E4*('Premium Calculation'!B32+Assumptions!C24) -> 0 | C30: abs < 0.01 | D30: =IFERROR(IF(ABS(B30)<0.01,"PASS","FAIL"),"FAIL") -> PASS
A31: VFA CSM reconciliation | B31: =SUMPRODUCT('IFRS 17 VFA'!I23:I62,'IFRS 17 VFA'!I23:I62) -> 0 | C31: abs < 0.0001 | D31: =IFERROR(IF(ABS(B31)<0.0001,"PASS","FAIL"),"FAIL") -> PASS
A32: VFA terminal CSM | B32: ='IFRS 17 VFA'!H62 -> 0 | C32: abs < 0.01 | D32: =IFERROR(IF(ABS(B32)<0.01,"PASS","FAIL"),"FAIL") -> PASS
A33: Summary policy PVFP | B33: ='Results Summary'!E5-'Profit Testing'!B7 -> 0 | C33: abs < 0.01 | D33: =IFERROR(IF(ABS(B33)<0.01,"PASS","FAIL"),"FAIL") -> PASS
A34: Summary portfolio NBM | B34: ='Results Summary'!E8-'Portfolio Totals'!B14 -> 0 | C34: abs < 0.01 | D34: =IFERROR(IF(ABS(B34)<0.01,"PASS","FAIL"),"FAIL") -> PASS
A35: Summary mortality A/E | B35: ='Results Summary'!I8-'Experience Analysis'!B50 -> 0 | C35: abs < 0.000001 | D35: =IFERROR(IF(ABS(B35)<0.000001,"PASS","FAIL"),"FAIL") -> PASS
A36: Pricing mortality lower bound | B36: =MIN('Policy Calculations'!AU6:CH279) -> 0 | C36: >=0 | D36: =IFERROR(IF(B36>=0,"PASS","FAIL"),"FAIL") -> PASS
A37: Pricing mortality upper bound | B37: =MAX('Policy Calculations'!AU6:CH279) -> 0.039726939 | C37: <=1 | D37: =IFERROR(IF(B37<=1,"PASS","FAIL"),"FAIL") -> PASS
A38: Formula errors across calculation sheets | B38: =0+SUMPRODUCT(--ISERROR('Results Summary'!A1:M135))+SUMPRODUCT(--ISERROR('Pricing Calculator'!A1:Y95))+SUMPRODUCT(--ISERROR('Portfolio Totals'!A1:Y92))+SUMPRODUCT(--ISERROR('Portfolio Analysis'!A1:Y91))+SUMPRODUCT(--ISERROR(Sensitivities!A1:Z95))+SUMPRODUCT(--ISERROR('Assumption Review'!A1:Z93))+SUMPRODUCT(--ISERROR(Assumptions!A1:Z95))+SUMPRODUCT(--ISERROR(Mortality!A1:Z95))+SUMPRODUCT(--ISERROR('Policy Data'!A1:Z253))+SUMPRODUCT(--ISERROR('Premium Calculation'!A1:Z95))+SUMPRODUCT(--ISERROR('Unit-Linked'!A1:Z95))+SUMPRODUCT(--ISERROR(Cashflows!A1:Z95))+SUMPRODUCT(--ISERROR(Reinsurance!A1:Z95))+SUMPRODUCT(--ISERROR('Profit Testing'!A1:Z95))+SUMPRODUCT(--ISERROR('Policy Calculations'!A1:ED279))+SUMPRODUCT(--ISERROR('Experience Analysis'!A1:Z96))+SUMPRODUCT(--ISERROR('IFRS 17 GMM'!A1:Z95))+SUMPRODUCT(--ISERROR('IFRS 17 VFA'!A1:I95)) -> 0 | C38: zero | D38: =IFERROR(IF(B38=0,"PASS","FAIL"),"FAIL") -> PASS
A39: Investigation list reconciliation | B39: =COUNT('Portfolio Analysis'!B80:B89)-MIN(10,'Portfolio Totals'!B8) -> 0 | C39: zero | D39: =IF(B39=0,"PASS","FAIL") -> PASS
A40: Overall checks | B40: =IF(COUNTIF(D4:D39,"PASS")=36,"PASS","FAIL") -> PASS

Sheet Portfolio Totals
A1: Portfolio Totals
A2: Summary of pricing and profitability results for the synthetic term life portfolio.
A5: Portfolio metric | B5: Value | C5: Definition | E5: NBM band | F5: Policies | G5: Charged prem. | H5: PV premiums | I5: PVFP
A6: Total Policies | B6: =COUNTA('Policy Calculations'!$A$30:$A$279) -> 250 | E6: < −50% | F6: =COUNTIFS('Policy Calculations'!$AJ$30:$AJ$279,"<-0.5",'Policy Calculations'!$T$30:$T$279,1) -> 1 | G6: =SUMIFS('Policy Calculations'!$M$30:$M$279,'Policy Calculations'!$AJ$30:$AJ$279,"<-0.5",'Policy Calculations'!$T$30:$T$279,1) -> 1699.41 | H6: =SUMIFS('Policy Calculations'!$AH$30:$AH$279,'Policy Calculations'!$AJ$30:$AJ$279,"<-0.5",'Policy Calculations'!$T$30:$T$279,1) -> 15346.78 | I6: =SUMIFS('Policy Calculations'!$AI$30:$AI$279,'Policy Calculations'!$AJ$30:$AJ$279,"<-0.5",'Policy Calculations'!$T$30:$T$279,1) -> -7821.7159
A7: Term Life policies | B7: =COUNTIF('Policy Calculations'!$C$30:$C$279,"Term Life") -> 183 | E7: −50% to −20% | F7: =COUNTIFS('Policy Calculations'!$AJ$30:$AJ$279,">=-0.5",'Policy Calculations'!$AJ$30:$AJ$279,"<-0.2",'Policy Calculations'!$T$30:$T$279,1) -> 25 | G7: =SUMIFS('Policy Calculations'!$M$30:$M$279,'Policy Calculations'!$AJ$30:$AJ$279,">=-0.5",'Policy Calculations'!$AJ$30:$AJ$279,"<-0.2",'Policy Calculations'!$T$30:$T$279,1) -> 58414.53 | H7: =SUMIFS('Policy Calculations'!$AH$30:$AH$279,'Policy Calculations'!$AJ$30:$AJ$279,">=-0.5",'Policy Calculations'!$AJ$30:$AJ$279,"<-0.2",'Policy Calculations'!$T$30:$T$279,1) -> 468921.76 | I7: =SUMIFS('Policy Calculations'!$AI$30:$AI$279,'Policy Calculations'!$AJ$30:$AJ$279,">=-0.5",'Policy Calculations'!$AJ$30:$AJ$279,"<-0.2",'Policy Calculations'!$T$30:$T$279,1) -> -156344.4
A8: Policies priced | B8: =SUM('Policy Calculations'!$T$30:$T$279) -> 169 | C8: Term Life within table/term bounds | E8: −20% to 0% | F8: =COUNTIFS('Policy Calculations'!$AJ$30:$AJ$279,">=-0.2",'Policy Calculations'!$AJ$30:$AJ$279,"<0",'Policy Calculations'!$T$30:$T$279,1) -> 39 | G8: =SUMIFS('Policy Calculations'!$M$30:$M$279,'Policy Calculations'!$AJ$30:$AJ$279,">=-0.2",'Policy Calculations'!$AJ$30:$AJ$279,"<0",'Policy Calculations'!$T$30:$T$279,1) -> 83425.94 | H8: =SUMIFS('Policy Calculations'!$AH$30:$AH$279,'Policy Calculations'!$AJ$30:$AJ$279,">=-0.2",'Policy Calculations'!$AJ$30:$AJ$279,"<0",'Policy Calculations'!$T$30:$T$279,1) -> 596661.67 | I8: =SUMIFS('Policy Calculations'!$AI$30:$AI$279,'Policy Calculations'!$AJ$30:$AJ$279,">=-0.2",'Policy Calculations'!$AJ$30:$AJ$279,"<0",'Policy Calculations'!$T$30:$T$279,1) -> -55029.656
A9: Unit-linked policies | B9: =COUNTIF('Policy Calculations'!$C$30:$C$279,"Unit-Linked") -> 67 | C9: Out of term-pricing scope (see Unit-Linked) | E9: 0% to target | F9: =COUNTIFS('Policy Calculations'!$AJ$30:$AJ$279,">=0",'Policy Calculations'!$AJ$30:$AJ$279,"<"&(Assumptions!$C$16-0.00001),'Policy Calculations'!$T$30:$T$279,1) -> 19 | G9: =SUMIFS('Policy Calculations'!$M$30:$M$279,'Policy Calculations'!$AJ$30:$AJ$279,">=0",'Policy Calculations'!$AJ$30:$AJ$279,"<"&(Assumptions!$C$16-0.00001),'Policy Calculations'!$T$30:$T$279,1) -> 31065.46 | H9: =SUMIFS('Policy Calculations'!$AH$30:$AH$279,'Policy Calculations'!$AJ$30:$AJ$279,">=0",'Policy Calculations'!$AJ$30:$AJ$279,"<"&(Assumptions!$C$16-0.00001),'Policy Calculations'!$T$30:$T$279,1) -> 249909.39 | I9: =SUMIFS('Policy Calculations'!$AI$30:$AI$279,'Policy Calculations'!$AJ$30:$AJ$279,">=0",'Policy Calculations'!$AJ$30:$AJ$279,"<"&(Assumptions!$C$16-0.00001),'Policy Calculations'!$T$30:$T$279,1) -> 12963.388
A10: Term policies outside pricing scope | B10: =COUNTIFS('Policy Calculations'!$C$30:$C$279,"Term Life",'Policy Calculations'!$T$30:$T$279,0) -> 14 | C10: Entry age + term − 1 > 80 | E10: ≥ target | F10: =COUNTIFS('Policy Calculations'!$AJ$30:$AJ$279,">="&(Assumptions!$C$16-0.00001),'Policy Calculations'!$T$30:$T$279,1) -> 85 | G10: =SUMIFS('Policy Calculations'!$M$30:$M$279,'Policy Calculations'!$AJ$30:$AJ$279,">="&(Assumptions!$C$16-0.00001),'Policy Calculations'!$T$30:$T$279,1) -> 255275.56 | H10: =SUMIFS('Policy Calculations'!$AH$30:$AH$279,'Policy Calculations'!$AJ$30:$AJ$279,">="&(Assumptions!$C$16-0.00001),'Policy Calculations'!$T$30:$T$279,1) -> 1872981.2 | I10: =SUMIFS('Policy Calculations'!$AI$30:$AI$279,'Policy Calculations'!$AJ$30:$AJ$279,">="&(Assumptions!$C$16-0.00001),'Policy Calculations'!$T$30:$T$279,1) -> 462499.63
A11: Charged annualised premium (AED) | B11: =SUMIFS('Policy Calculations'!$M$30:$M$279,'Policy Calculations'!$T$30:$T$279,1) -> 429880.9 | C11: Sum of synthetic charged premiums, priced policies | E11: Total | F11: =SUM(F6:F10) -> 169 | G11: =SUM(G6:G10) -> 429880.9 | H11: =SUM(H6:H10) -> 3203820.8 | I11: =SUM(I6:I10) -> 256267.25
A12: PV premiums at charged premium (AED) | B12: =SUMIFS('Policy Calculations'!$AH$30:$AH$279,'Policy Calculations'!$T$30:$T$279,1) -> 3203820.8 | E12: Band total check (PVFP) | I12: =I11-B13 -> 0
A13: PVFP (AED) | B13: =SUMIFS('Policy Calculations'!$AI$30:$AI$279,'Policy Calculations'!$T$30:$T$279,1) -> 256267.25 | C13: Before tax and cost of capital
A14: Portfolio NBM | B14: =IF(B12=0,"",B13/B12) -> 0.07998801 | C14: PVFP ÷ PV premiums
A15: Target NBM | B15: =Assumptions!C16 -> 0.08
A16: Technical annualised premium (AED) | B16: =SUMIFS('Policy Calculations'!$AF$30:$AF$279,'Policy Calculations'!$T$30:$T$279,1) -> 432358.1 | C16: Premium re-solved to target NBM
A17: Premium adequacy | B17: =IF(B16=0,"",B11/B16) -> 0.9942705 | C17: Charged premium / technical premium
A18: Loss-making policies | B18: =COUNTIF('Policy Calculations'!$AR$30:$AR$279,"Loss-making") -> 65 | C18: PVFP < 0 at charged premium
A19: Below-target profitable policies | B19: =COUNTIF('Policy Calculations'!$AR$30:$AR$279,"Below target") -> 19
A20: At/above target policies | B20: =COUNTIF('Policy Calculations'!$AR$30:$AR$279,"At/above target") -> 85
A21: PVFP of loss-making policies (AED) | B21: =SUMIFS('Policy Calculations'!$AI$30:$AI$279,'Policy Calculations'!$AR$30:$AR$279,"Loss-making") -> -219195.77 | C21: Value destroyed by loss-making business
A22: Total sum assured – priced (AED) | B22: =SUMIFS('Policy Calculations'!$I$30:$I$279,'Policy Calculations'!$T$30:$T$279,1) -> 114000000
A23: Ceded sum assured (AED) | B23: =SUMIFS('Policy Calculations'!$Z$30:$Z$279,'Policy Calculations'!$T$30:$T$279,1) -> 43000000 | C23: Surplus above retention
A24: RI impact on PVFP (AED) | B24: =SUMIFS('Policy Calculations'!$AN$30:$AN$279,'Policy Calculations'!$T$30:$T$279,1) -> 648622.16 | C24: PV recoveries − PV RI premiums
A25: PVFP without reinsurance (AED) | B25: =B13-B24 -> -392354.91
A28: Policies selected for further investigation
A29: Rank · Policy ID | B29: Entry age | C29: Profile (sex · smoker · UW class) | D29: Term | E29: Sum assured | F29: Channel | G29: Frequency | H29: Charged prem. | I29: Technical prem. | J29: Adequacy | K29: PVFP | L29: NBM
A30: =IFERROR("1. "&INDEX('Policy Calculations'!$A$30:$A$279,MATCH(SMALL('Policy Calculations'!$AS$30:$AS$279,1),'Policy Calculations'!$AS$30:$AS$279,0)),"") -> 1. POL100246 | B30: =IFERROR(INDEX('Policy Calculations'!$D$30:$D$279,MATCH(SMALL('Policy Calculations'!$AS$30:$AS$279,1),'Policy Calculations'!$AS$30:$AS$279,0)),"") -> 59 | C30: =IFERROR(INDEX('Policy Calculations'!$E$30:$E$279,MATCH(SMALL('Policy Calculations'!$AS$30:$AS$279,1),'Policy Calculations'!$AS$30:$AS$279,0))&" · "&INDEX('Policy Calculations'!$F$30:$F$279,MATCH(SMALL('Policy Calculations'!$AS$30:$AS$279,1),'Policy Calculations'!$AS$30:$AS$279,0))&" · "&INDEX('Policy Calculations'!$G$30:$G$279,MATCH(SMALL('Policy Calculations'!$AS$30:$AS$279,1),'Policy Calculations'!$AS$30:$AS$279,0)),"") -> Male · Non-smoker · Standard | D30: =IFERROR(INDEX('Policy Calculations'!$H$30:$H$279,MATCH(SMALL('Policy Calculations'!$AS$30:$AS$279,1),'Policy Calculations'!$AS$30:$AS$279,0)),"") -> 20 | E30: =IFERROR(INDEX('Policy Calculations'!$I$30:$I$279,MATCH(SMALL('Policy Calculations'!$AS$30:$AS$279,1),'Policy Calculations'!$AS$30:$AS$279,0)),"") -> 500000 | F30: =IFERROR(INDEX('Policy Calculations'!$K$30:$K$279,MATCH(SMALL('Policy Calculations'!$AS$30:$AS$279,1),'Policy Calculations'!$AS$30:$AS$279,0)),"") -> Bancassurance | G30: =IFERROR(INDEX('Policy Calculations'!$J$30:$J$279,MATCH(SMALL('Policy Calculations'!$AS$30:$AS$279,1),'Policy Calculations'!$AS$30:$AS$279,0)),"") -> Monthly | H30: =IFERROR(INDEX('Policy Calculations'!$M$30:$M$279,MATCH(SMALL('Policy Calculations'!$AS$30:$AS$279,1),'Policy Calculations'!$AS$30:$AS$279,0)),"") -> 3861.89 | I30: =IFERROR(INDEX('Policy Calculations'!$AF$30:$AF$279,MATCH(SMALL('Policy Calculations'!$AS$30:$AS$279,1),'Policy Calculations'!$AS$30:$AS$279,0)),"") -> 6488.4779 | J30: =IFERROR(INDEX('Policy Calculations'!$AK$30:$AK$279,MATCH(SMALL('Policy Calculations'!$AS$30:$AS$279,1),'Policy Calculations'!$AS$30:$AS$279,0)),"") -> 0.59519198 | K30: =IFERROR(INDEX('Policy Calculations'!$AI$30:$AI$279,MATCH(SMALL('Policy Calculations'!$AS$30:$AS$279,1),'Policy Calculations'!$AS$30:$AS$279,0)),"") -> -14415.996 | L30: =IFERROR(INDEX('Policy Calculations'!$AJ$30:$AJ$279,MATCH(SMALL('Policy Calculations'!$AS$30:$AS$279,1),'Policy Calculations'!$AS$30:$AS$279,0)),"") -> -0.45791743
